Workbook

Sheet AI Events_MD&A
A1: Wolters Kluwer — AI Evidence, MD&A & Commercialization Timeline
A2: A. AI & Digital Commercialization Timeline
A3: Date / Year | B3: Phase | C3: Scope | D3: Official Evidence / Management Commentary | E3: Quantified Evidence | F3: Financial Mechanism | G3: Model Use | H3: Document / Release
A4: 2021 | B4: Historical AI / cloud foundation | C4: Group / T&A | D4: AI, NLP, RPA and predictive analytics were already deployed; CCH Axcess cloud adoption supported professional workflows. 2021–23 is pre-GenAI acceleration, not pre-AI. | E4: Product development = 10% of revenue | F4: Cloud migration + workflow embedment + recurring revenue durability | G4: Historical baseline / attribution guardrail | H4: 2021 Annual Report
A5: 2022 | B5: Expert solutions / cloud scale | C5: Group | D5: Recurring digital/cloud expert solutions supported 6% organic growth while management raised product development to a record level. | E5: 11% of revenue invested in product development; expert solutions = 56% of revenue | F5: Recurring/cloud mix + product investment | G5: Baseline before accelerated GenAI commercialization | H5: 2022 Annual Report
A6: 2023 | B6: GenAI experimentation | C6: Group / T&A | D6: Management shifted attention and funding toward generative-AI opportunities; first GenAI-enabled products were released. AI had already been used for more than a decade. | E6: ≈€615m product development; ≈50% of digital revenue from products with AI embedded; T&A cloud +17% | F6: Product innovation + cloud adoption + future AI monetization | G6: Marks GenAI ramp-up; no direct AI revenue attribution | H6: 2023 Annual Report
A7: 2023-10-20 | B7: GenAI showcase | C7: T&A direct | D7: Five GenAI use cases demonstrated across search, firm guidance, client relationships, scorecards and benchmarking. | E7: 5 showcased GenAI use cases | F7: Customer productivity + client service + profitability insights | G7: Evidence of experimentation before commercial launch | H7: CCH Connections GenAI Showcase
A8: 2024 | B8: Commercial GenAI | C8: Group / T&A | D8: GenAI search, summarization, Q&A and virtual assistants rolled out. T&A cloud growth was driven by CCH Axcess migration and additional workflow modules. | E8: ≈€660m product development; T&A cloud +19% organic; N.A. cloud +20%; >50% digital revenue from AI-leveraging products | F8: Subscription/cloud growth + workflow upsell + operating leverage | G8: Core 2024 commercialization rationale | H8: 2024 Annual Report / FY Results
A9: 2024-05-06 | B9: Commercial GenAI launch | C9: T&A direct | D9: GenAI Q&A launched inside CCH AnswerConnect, embedding natural-language assistance into the tax research workflow. | E9: Commercial GenAI launch | F9: Research time savings + premium product value | G9: Commercialization breakpoint | H9: CCH AnswerConnect GenAI
A10: 2025 | B10: Expert AI / agentic commercialization | C10: Group / T&A | D10: Management identified AI growth channels through retention, upsell, new products and adjacent segments. Expert AI was embedded into multiple high-value workflows. | E10: ≈€650m product development; nearly 70% digital revenue AI-powered; 83% recurring; >90% renewal rates for most core solutions | F10: Retention + upsell + new products + adjacency + recurring-revenue durability | G10: Defines monetization channels used in ROI | H10: 2025 Annual Report
A11: 2025-10-15 | B11: Agentic platform launch | C11: T&A direct | D11: CCH Axcess Expert AI launched as an agentic-ready platform across tax, audit and firm management; FY commentary cited significant productivity benefits. | E11: CCH Axcess native cloud +19% organic in FY2025 | F11: AI module upsell + workflow automation + cloud retention | G11: Primary AI ROI initiative launch point | H11: CCH Axcess Expert AI launch
A12: 2026-Q1 | B12: Early agentic adoption | C12: T&A direct | D12: Recurring T&A revenue sustained 7% organic growth, driven by cloud solutions. Early commercial adoption of new CCH Axcess agentic modules was reported. | E12: >150 firms using Intelligence / Client Collaboration | F12: Adoption + cloud recurring revenue | G12: Early adoption bridge into 2026E | H12: Q1 2026 Trading Update
A13: 2026-05-13 | B13: Agentic expansion | C13: T&A direct | D13: CCH Axcess Advisor became generally available, using client/compliance data to identify and scale advisory opportunities. | E13: Commercial product launch | F13: New product + advisory upsell + customer revenue opportunity | G13: Supports commercial-expansion value channel | H13: CCH Axcess Advisor launch
A14: 2026-06 | B14: Enterprise AI collaboration | C14: T&A direct / Group | D14: Wolters Kluwer and OpenAI expanded enterprise collaboration; OpenAI models power CCH Axcess Expert AI agentic workflows. | E14: Company-reported 20–30% reduction in manual tasks from CCH Axcess agentic solutions | F14: Customer productivity + AI delivery architecture | G14: Operating-benefit evidence; not WK contract pricing | H14: Wolters Kluwer + OpenAI collaboration
A15: 2026-06-29 | B15: Workflow automation scale | C15: T&A direct | D15: AI-powered Scan and complex K-1 ingestion expanded low-touch tax preparation and document automation. | E15: Early users: 30–70% efficiency gains; K-1 manual effort down 60–80% | F15: Customer productivity + capacity + retention | G15: Supporting workflow-specific evidence only | H15: Expert AI Scan / K-1 expansion
A16: 2026-H1 | B16: Commercial adoption / scaling | C16: T&A direct | D16: T&A recurring growth remained strong and North American cloud growth sustained double digits as firms migrated and added workflow modules. | E16: T&A revenue €847m; organic +6%; margin 36.3%; recurring 93%; N.A. cloud +18%; ≈250 AI-module firms | F16: Observed adoption + recurring/cloud growth + operating leverage | G16: Anchors 2026 adoption and before/after analysis | H16: 2026 Half-Year Results
A17: 2026 onward | B17: AI investment scale-up | C17: Group | D17: Management plans to raise annual product-development spending to 12–13% of revenue to advance the AI strategy while still targeting margin expansion. | E17: 12–13% product development; 2026 adjusted operating margin ≈28% | F17: Higher near-term investment for future recurring growth / monetization | G17: Key forecast cost/investment anchor | H17: 2025 Annual Report / 2026 H1 Results
A19: B. AI Capital Allocation, Market Demand & Cross-Division Commercialization Evidence
A20: Date / Year | B20: Phase | C20: Scope | D20: Official Evidence / Management Commentary | E20: Quantified Evidence | F20: Financial Mechanism | G20: Model Use | H20: Document / Release
A21: 2021 | B21: AI / analytics acquisition precedent | C21: Former CCH Tagetik / CP&ESG | D21: Vanguard Software acquired to extend planning and predictive analytics capabilities. | E21: ≈$110m cash; 2020 revenue ≈$7.2m; ≈55% subscription-cloud mix; recurring cloud +33%; ROIC >8% WACC within 3–5 years | F21: AI/analytics M&A discipline + hurdle-rate precedent | G21: WACC / capital-allocation precedent | H21: Vanguard Software acquisition
A22: 2022 | B22: AI acquisition precedent | C22: Legal & Regulatory | D22: Della AI, an NLP/contract-analysis specialist, acquired to strengthen legal AI capabilities. | E22: ROIC expected above 8% WACC within 3–5 years | F22: Repeated company hurdle for AI-related investment | G22: WACC / capital-allocation precedent | H22: Della AI acquisition
A23: 2025 | B23: AI M&A commercialization precedent | C23: Legal & Regulatory | D23: Wolters Kluwer agreed to acquire Libra Technology, a legal AI assistant provider. | E23: Up to €90m consideration; €30m upfront; ≈€5m ARR expected; ROIC at/above 8% after-tax WACC within 3–5 years | F23: Concrete AI transaction economics + investment hurdle | G23: Supports 8% WACC anchor and 3–5 year return discipline | H23: Libra Technology acquisition
A24: 2025 | B24: Market demand evidence | C24: Accounting industry | D24: Future Ready Accountant reported rapid movement from experimentation to regular AI use across accounting firms. | E24: AI adoption 9%→41%; 77% plan more AI investment; 35% daily use; 73% of regular users report better-than-expected outcomes | F24: Rising addressable demand for AI workflow modules | G24: Adoption rationale only — not CCH Axcess adoption | H24: 2025 Future Ready Accountant
A25: 2026-01 | B25: Post-acquisition commercialization | C25: Legal & Regulatory | D25: Libra technology integrated with Wolters Kluwer content and launched as the Libra Legal AI Workspace in the Netherlands. | E25: Acquisition-to-launch sequence | F25: Build/buy/integrate/monetize precedent | G25: Cross-division commercialization precedent | H25: Libra Legal AI Workspace launch
A26: 2026 | B26: Workflow productivity evidence | C26: Legal & Regulatory | D26: Passport introduced AI-powered matter-summary capabilities across legal matter documents, invoices and tasks. | E26: Clients reduced time spent on strategic matter reviews by 75% | F26: Cross-division proof that embedded Expert AI can create measurable workflow savings | G26: Supporting benchmark only | H26: Passport AI matter summaries
A27: 2026 | B27: Enterprise AI adoption | C27: Legal & Regulatory | D27: CRIDO selected Libra after a pilot and benchmark against alternative AI tools. | E27: Nearly 200 lawyers/advisors adopting the AI workspace | F27: Customer validation / commercial adoption precedent | G27: Supporting adoption precedent only | H27: CRIDO chooses Libra
A28: 2026 | B28: Finance workflow / AI evidence | C28: Corporate Performance & ESG | D28: CCH Tagetik evidence highlights demand for unified cloud finance platforms with AI-enabled forecasting, automation and reporting. | E28: Customer example accelerated financial close by ≈5 working days | F28: Finance-AI workflow value / integration evidence | G28: Context for AI-in-finance thesis, not T&A revenue | H28: 2026 CCH Tagetik analyst recognitions
A30: C. Management Commentary Linking Financial Performance to Operating Drivers
A31: Year | B31: Financial Area | C31: Reported Result / Direction | D31: AI / Digital Relevance | E31: Attribution Treatment | F31: Forecast Driver | G31: Grade | H31: Page / Section
A32: 2021 | B32: Group / T&A | C32: Group revenue €4,771m; margin 25.3%; T&A PF organic +5%; T&A margin 30.8% | D32: Cloud workflow foundation before GenAI acceleration | E32: Do not attribute 2021 results to GenAI | F32: Recurring/cloud migration; normalized cost base | G32: A+ | H32: Group review / T&A section
A33: 2022 | B33: Group / T&A | C33: Group organic +6%; margin 26.1%; T&A PF organic +8%; margin 32.6% | D33: Digital/cloud scale and product investment are the economic baseline | E33: Baseline only | F33: Recurring/cloud growth + operating leverage + innovation spend | G33: A+ | H33: Group/T&A review
A34: 2023 | B34: T&A | C34: Revenue €1,466m; organic +8%; margin 32.7% | D34: GenAI experimentation started to scale late in the year | E34: Correlation only; no AI revenue attribution | F34: Recurring software + cloud + product/personnel investment | G34: A+ | H34: T&A section
A35: 2024 | B35: T&A | C35: Revenue €1,561m; organic +7%; margin 33.2% | D35: Commercial GenAI features introduced alongside cloud/module expansion | E35: Association only; direct AI revenue not disclosed | F35: Cloud/module adoption + operating leverage; GenAI supports future upsell | G35: A+ | H35: T&A p.23 / FY Results p.9
A36: 2025 | B36: T&A | C36: Revenue €1,660m; organic +7%; margin 35.2%; CCH Axcess native cloud +19% | D36: Expert AI becomes a commercial module layer; management identifies retention, upsell, new products and adjacencies | E36: Do not attribute all 2025 CCH Axcess growth to AI | F36: Cloud/module penetration + AI attach rate + operating leverage | G36: A+ | H36: T&A p.25 / FY Results p.9
A37: 2026 H1 | B37: T&A / Group | C37: Group organic +5%; T&A organic +6%; T&A margin 36.3%; ≈250 AI firms | D37: First observed commercial adoption anchor for agentic AI | E37: Use adoption point, not company growth, for AI ROI attribution | F37: 7% FY T&A growth guidance; higher AI investment; continuing cloud adoption | G37: A+ | H37: T&A p.10 / outlook p.2

Sheet Historical Data
A2: Financial Statement Model for Wolters Kluwer
A3: € mm except per share
A5: Company name | B5: Wolters Kluwer N.V.
A6: Ticker | B6: WKL / WKL.AS
A7: Historical baseline | B7: 2021A–2023A
A8: GenAI commercialization | B8: 2024A
A9: Agentic AI launch | B9: 2025A
A10: Diluted weighted-average shares (m) | B10: 231.8
A11: Project objective | B11: Quantify financial value from AI and return from continued agentic-AI scaling
A13: INCOME STATEMENT
B14: 2021A | C14: 2022A | D14: 2023A | E14: 2024A | F14: 2025A
A16: Revenue | B16: 4771 | C16: 5453 | D16: 5584 | E16: 5916 | F16: 6125
A17: Cost of revenue (enter as -) | B17: -1374 | C17: -1578 | D17: -1576 | E17: -1626 | F17: -1625
A18: Gross Profit | B18: =SUM(B16:B17) -> 3397 | C18: =SUM(C16:C17) -> 3875 | D18: =SUM(D16:D17) -> 4008 | E18: =SUM(E16:E17) -> 4290 | F18: =SUM(F16:F17) -> 4500
A19: Product development / R&D & editorial (enter as -) | B19: -466 | C19: -541 | D19: -591 | E19: -688 | F19: -724
A20: Sales & Marketing (enter as -) | B20: -806 | C20: -914 | D20: -929 | E20: -969 | F20: -975
A21: General & Administrative (enter as -) | B21: -920 | C21: -996 | D21: -1012 | E21: -1033 | F21: -1114
A22: Amortization of acquired intangibles (enter as -) | B22: -164 | C22: -160 | D22: -146 | E22: -149 | F22: -157
A23: Other operating income / (expense), net | B23: -29 | C23: 69 | D23: -7 | E23: -10 | F23: 205
A24: Operating profit (EBIT) | B24: =SUM(B18:B23) -> 1012 | C24: =SUM(C18:C23) -> 1333 | D24: =SUM(D18:D23) -> 1323 | E24: =SUM(E18:E23) -> 1441 | F24: =SUM(F18:F23) -> 1735
A25: Financing income | B25: 4 | C25: 21 | D25: 55 | E25: 52 | F25: 29
A26: Financing expense (enter as -) | B26: -82 | C26: -77 | D26: -82 | E26: -114 | F26: -115
A27: Other finance income / (expense), net | B27: -6 | C27: -1 | D27: 0 | E27: -3 | F27: -2
A28: Pretax profit | B28: =SUM(B24:B27) -> 928 | C28: =SUM(C24:C27) -> 1276 | D28: =SUM(D24:D27) -> 1296 | E28: =SUM(E24:E27) -> 1376 | F28: =SUM(F24:F27) -> 1647
A29: Taxes (enter expense as -) | B29: -201 | C29: -249 | D29: -290 | E29: -299 | F29: -341
A30: Net income | B30: =SUM(B28:B29) -> 727 | C30: =SUM(C28:C29) -> 1027 | D30: =SUM(D28:D29) -> 1006 | E30: =SUM(E28:E29) -> 1077 | F30: =SUM(F28:F29) -> 1306
A32: Depreciation & amortization | B32: 473 | C32: 466 | D32: 445 | E32: 479 | F32: 477
A33: EBITDA | B33: =B24+B32 -> 1485 | C33: =C24+C32 -> 1799 | D33: =D24+D32 -> 1768 | E33: =E24+E32 -> 1920 | F33: =F24+F32 -> 2212
A34: Adjusted operating profit | B34: 1205 | C34: 1424 | D34: 1476 | E34: 1600 | F34: 1687
A35: Adjusted EBITDA | B35: 1514 | C35: 1730 | D35: 1775 | E35: 1930 | F35: 2007
A38: Growth rates & margins
A39: Revenue growth | C39: =C16/B16-1 -> 0.14294697 | D39: =D16/C16-1 -> 0.024023473 | E39: =E16/D16-1 -> 0.059455587 | F39: =F16/E16-1 -> 0.035327924
A40: Gross profit margin | B40: =B18/B16 -> 0.71201006 | C40: =C18/C16 -> 0.71061801 | D40: =D18/D16 -> 0.71776504 | E40: =E18/E16 -> 0.72515213 | F40: =F18/F16 -> 0.73469388
A41: Product development / R&D % of revenue | B41: =-B19/B16 -> 0.097673444 | C41: =-C19/C16 -> 0.099211443 | D41: =-D19/D16 -> 0.10583811 | E41: =-E19/E16 -> 0.11629479 | F41: =-F19/F16 -> 0.11820408
A42: S&M % of revenue | B42: =-B20/B16 -> 0.16893733 | C42: =-C20/C16 -> 0.16761416 | D42: =-D20/D16 -> 0.16636819 | E42: =-E20/E16 -> 0.1637931 | F42: =-F20/F16 -> 0.15918367
A43: G&A % of revenue | B43: =-SUM(B21:B22)/B16 -> 0.22720604 | C43: =-SUM(C21:C22)/C16 -> 0.2119934 | D43: =-SUM(D21:D22)/D16 -> 0.20737822 | E43: =-SUM(E21:E22)/E16 -> 0.19979716 | F43: =-SUM(F21:F22)/F16 -> 0.2075102
A44: Operating margin | B44: =B24/B16 -> 0.21211486 | C44: =C24/C16 -> 0.24445259 | D44: =D24/D16 -> 0.23692693 | E44: =E24/E16 -> 0.24357674 | F44: =F24/F16 -> 0.28326531
A45: Effective tax rate | B45: =-B29/B28 -> 0.21659483 | C45: =-C29/C28 -> 0.19514107 | D45: =-D29/D28 -> 0.22376543 | E45: =-E29/E28 -> 0.21729651 | F45: =-F29/F28 -> 0.20704311
A46: Adjusted operating margin | B46: =B34/B16 -> 0.2525676 | C46: =C34/C16 -> 0.26114066 | D46: =D34/D16 -> 0.26432665 | E46: =E34/E16 -> 0.27045301 | F46: =F34/F16 -> 0.27542857
A47: Total product development % of revenue | B47: 0.1 | C47: 0.11 | D47: 0.11 | E47: 0.11 | F47: 0.11 | G47: Sourced from latest annual report
A50: BALANCE SHEET
B51: 2021A | C51: 2022A | D51: 2023A | E51: 2024A | F51: 2025A
A53: Cash & equivalents | B53: 1001 | C53: 1346 | D53: 1135 | E53: 954 | F53: 932
A54: Accounts receivable | B54: 1008 | C54: 1088 | D54: 1087 | E54: 1129 | F54: 1075
A55: Inventories | B55: 65 | C55: 79 | D55: 84 | E55: 79 | F55: 62
A56: Other current assets | B56: 664 | C56: 464 | D56: 448 | E56: 495 | F56: 564
A57: Property, plant & equipment | B57: 75 | C57: 79 | D57: 79 | E57: 79 | F57: 68
A58: Other non current assets | B58: 6215 | C58: 6454 | D58: 6261 | E58: 6762 | F58: 6883
A60: Total assets | B60: =SUM(B53:B58) -> 9028 | C60: =SUM(C53:C58) -> 9510 | D60: =SUM(D53:D58) -> 9094 | E60: =SUM(E53:E58) -> 9498 | F60: =SUM(F53:F58) -> 9584
A62: Trade & other payables | B62: 944 | C62: 990 | D62: 997 | E62: 1087 | F62: 1118
A63: Other current liabilities | B63: 323 | C63: 236 | D63: 235 | E63: 221 | F63: 251
A64: Deferred / unearned revenue | B64: 1709 | C64: 1858 | D64: 1899 | E64: 2054 | F64: 1911
A65: Debt, current / revolver | B65: 9 | C65: 716 | D65: 596 | E65: 359 | F65: 721
A66: Long term debt | B66: 2791 | C66: 2586 | D66: 2877 | E66: 3484 | F66: 4033
A67: Other non current liabilities | B67: 835 | C67: 814 | D67: 741 | E67: 748 | F67: 752
A69: Total liabilities | B69: =SUM(B62:B67) -> 6611 | C69: =SUM(C62:C67) -> 7200 | D69: =SUM(D62:D67) -> 7345 | E69: =SUM(E62:E67) -> 7953 | F69: =SUM(F62:F67) -> 8786
A71: Common stock / share capital | B71: 32 | C71: 31 | D71: 30 | E71: 29 | F71: 28
A72: Retained earnings | B72: 2330 | C72: 2461 | D72: 2038 | E72: 1359 | F72: 1171
A73: Other Equity | B73: 55 | C73: -182 | D73: -319 | E73: 157 | F73: -401
A74: Total equity | B74: =SUM(B71:B73) -> 2417 | C74: =SUM(C71:C73) -> 2310 | D74: =SUM(D71:D73) -> 1749 | E74: =SUM(E71:E73) -> 1545 | F74: =SUM(F71:F73) -> 798
A76: Balance check | B76: =B60-B69-B74 -> 0 | C76: =C60-C69-C74 -> 0 | D76: =D60-D69-D74 -> 0 | E76: =E60-E69-E74 -> 0 | F76: =F60-F69-F74 -> 0
A79: Additional data
A80: Capital expenditures (enter as +) | B80: 240 | C80: 295 | D80: 324 | E80: 314 | F80: 305
A81: D&A related only to PP&E (enter as -) | B81: -56 | C81: -64 | D81: -68 | E81: -70 | F81: -66
A82: Dividends | B82: -373 | C82: -424 | D82: -467 | E82: -521 | F82: -563
A83: Repurchases | B83: -410 | C83: -1000 | D83: -1000 | E83: -1000 | F83: -1096
A84: Implied interest rate on debt | B84: 0.0262 | C84: 0.0213 | D84: 0.0219 | E84: 0.0279 | F84: 0.0231
A85: Implied interest rate on cash | B85: 0.004 | C85: 0.0156 | D85: 0.0485 | E85: 0.0545 | F85: 0.0311
A86: Interest Expense | B86: 82 | C86: 77 | D86: 82 | E86: 114 | F86: 115
A87: Total Debt incl. leases | B87: 3131 | C87: 3615 | D87: 3745 | E87: 4085 | F87: 4971
A88: Interest Income | B88: 4 | C88: 21 | D88: 55 | E88: 52 | F88: 29
A89: Total interest earning assets | B89: 1001 | C89: 1346 | D89: 1135 | E89: 954 | F89: 932
A90: Adjusted free cash flow | B90: 1010 | C90: 1220 | D90: 1164 | E90: 1276 | F90: 1348
A91: ROIC | B91: 0.137 | C91: 0.155 | D91: 0.168 | E91: 0.181 | F91: 0.18
... A93: Company-reported net debt | B93: 2131 | C93: 2253 | D93: 2612 | E93: 3134 | F93: 4024

Sheet Forecast
A2: Financial Statement Model for Wolters Kluwer
A3: € mm except per share
A5: Company name | B5: Wolters Kluwer N.V.
A6: Ticker | B6: WKL / WKL.AS
A7: Use average balances = 1, Use BOP balances = 0 | B7: 1
A8: Latest closing share price
A9: Latest closing share price date
A10: Latest fiscal year end date | B10: 2025-12-31
A11: Shares outstanding (millions) | B11: 231.8
A12: Select an operating scenario | B12: Base case
A14: INCOME STATEMENT | K14: 5 Year | M14: Comments
B15: 2024A | C15: 2025A | D15: 2026E | E15: 2027E | F15: 2028E | G15: 2029E | H15: 2030E | I15: 2031E | K15: CAGR
A17: Revenue | B17: ='Historical Data'!E16 -> 5916 | C17: ='Historical Data'!F16 -> 6125 | D17: =C17*(1+D38) -> 6431.25 | E17: =D17*(1+E38) -> 6813.9094 | F17: =E17*(1+F38) -> 7203.665 | G17: =F17*(1+G38) -> 7591.2222 | H17: =G17*(1+H38) -> 7969.265 | I17: =H17*(1+I38) -> 8333.4604 | K17: =(I17/C17)^(1/5)-1 -> 0.063515581 | M17: Prior-year revenue × forecast growth assumption.
A18: Cost of revenue (enter as -) | B18: ='Historical Data'!E17 -> -1626 | C18: ='Historical Data'!F17 -> -1625 | D18: =-D17*(1-D39) -> -1672.125 | E18: =-E17*(1-E39) -> -1757.9886 | F18: =-F17*(1-F39) -> -1851.3419 | G18: =-G17*(1-G39) -> -1943.3529 | H18: =-H17*(1-H39) -> -2032.1626 | I18: =-I17*(1-I39) -> -2116.699 | M18: Derived from forecast gross margin.
A19: Gross Profit | B19: ='Historical Data'!E18 -> 4290 | C19: ='Historical Data'!F18 -> 4500 | D19: =SUM(D17:D18) -> 4759.125 | E19: =SUM(E17:E18) -> 5055.9208 | F19: =SUM(F17:F18) -> 5352.3231 | G19: =SUM(G17:G18) -> 5647.8693 | H19: =SUM(H17:H18) -> 5937.1024 | I19: =SUM(I17:I18) -> 6216.7615 | M19: Revenue less cost of revenue
A20: Product development / R&D & editorial (enter as -) | B20: ='Historical Data'!E19 -> -688 | C20: ='Historical Data'!F19 -> -724 | D20: =-D17*D40 -> -771.75 | E20: =-E17*E40 -> -824.48303 | F20: =-F17*F40 -> -878.84713 | G20: =-G17*G40 -> -926.1291 | H20: =-H17*H40 -> -972.25033 | I20: =-I17*I40 -> -1016.6822 | M20: Revenue × forecast R&D expense %.
A21: Sales & Marketing (enter as -) | B21: ='Historical Data'!E20 -> -969 | C21: ='Historical Data'!F20 -> -975 | D21: =-D17*D41 -> -1016.1375 | E21: =-E17*E41 -> -1069.7838 | F21: =-F17*F41 -> -1123.7717 | G21: =-G17*G41 -> -1176.6394 | H21: =-H17*H41 -> -1227.2668 | I21: =-I17*I41 -> -1275.0194 | M21: Revenue × forecast S&M %.
A22: General & Administrative (enter as -) | B22: ='Historical Data'!E21 -> -1033 | C22: ='Historical Data'!F21 -> -1114 | D22: =-D17*0.182 -> -1170.4875 | E22: =-E17*0.18 -> -1226.5037 | F22: =-F17*0.177 -> -1275.0487 | G22: =-G17*0.175 -> -1328.4639 | H22: =-H17*0.174 -> -1386.6521 | I22: =-I17*0.174 -> -1450.0221 | M22: Revenue × forecast G&A %
A23: Amortization of acquired intangibles (enter as -) | B23: ='Historical Data'!E22 -> -149 | C23: ='Historical Data'!F22 -> -157 | D23: =-D17*0.025 -> -160.78125 | E23: =-E17*0.024 -> -163.53382 | F23: =-F17*0.023 -> -165.68429 | G23: =-G17*0.022 -> -167.00689 | H23: =-H17*0.021 -> -167.35457 | I23: =-I17*0.02 -> -166.66921 | M23: Forecast as declining % of revenue as existing acquisition intangibles amortize.
A24: Operating profit (EBIT) | B24: ='Historical Data'!E24 -> 1441 | C24: ='Historical Data'!F24 -> 1735 | D24: =SUM(D19:D23) -> 1639.9688 | E24: =SUM(E19:E23) -> 1771.6164 | F24: =SUM(F19:F23) -> 1908.9712 | G24: =SUM(G19:G23) -> 2049.63 | H24: =SUM(H19:H23) -> 2183.5786 | I24: =SUM(I19:I23) -> 2308.3685 | K24: =(I24/C24)^(1/5)-1 -> 0.058768797 | M24: Gross profit less operating expenses
A25: Interest income | B25: ='Historical Data'!E25 -> 52 | C25: ='Historical Data'!F25 -> 29 | D25: =D170 -> 27.96 | E25: =E170 -> 40.060284 | F25: =F170 -> 54.166749 | G25: =G170 -> 68.167026 | H25: =H170 -> 82.181737 | I25: =I170 -> 95.709334 | M25: Based on beginning cash and assumed cash yield.
A26: Interest expense (enter as -) | B26: ='Historical Data'!E26 -> -114 | C26: ='Historical Data'!F26 -> -115 | D26: =D166+D168 -> -142.62 | E26: =E166+E168 -> -142.62 | F26: =F166+F168 -> -142.62 | G26: =G166+G168 -> -147.374 | H26: =H166+H168 -> -147.374 | I26: =I166+I168 -> -147.374 | M26: Based on debt balances and assumed borrowing rate.
A27: Other expense, net (enter as -) | B27: ='Historical Data'!E27 -> -3 | C27: ='Historical Data'!F27 -> -2 | D27: -2 | E27: -2 | F27: -2 | G27: -2 | H27: -2 | I27: -2
A28: Pretax profit | B28: ='Historical Data'!E28 -> 1376 | C28: ='Historical Data'!F28 -> 1647 | D28: =SUM(D24:D27) -> 1523.3088 | E28: =SUM(E24:E27) -> 1667.0567 | F28: =SUM(F24:F27) -> 1818.518 | G28: =SUM(G24:G27) -> 1968.423 | H28: =SUM(H24:H27) -> 2116.3864 | I28: =SUM(I24:I27) -> 2254.7039 | M28: EBIT + net financing result.
A29: Taxes (enter expense as -) | B29: ='Historical Data'!E29 -> -299 | C29: ='Historical Data'!F29 -> -341 | D29: =-D28*D44 -> -319.89484 | E29: =-E28*E44 -> -350.08191 | F29: =-F28*F44 -> -381.88877 | G29: =-G28*G44 -> -413.36883 | H29: =-H28*H44 -> -444.44113 | I29: =-I28*I44 -> -473.48781 | M29: Pretax profit × forecast effective tax rate.
A30: Net income | B30: ='Historical Data'!E30 -> 1077 | C30: ='Historical Data'!F30 -> 1306 | D30: =SUM(D28:D29) -> 1203.4139 | E30: =SUM(E28:E29) -> 1316.9748 | F30: =SUM(F28:F29) -> 1436.6292 | G30: =SUM(G28:G29) -> 1555.0542 | H30: =SUM(H28:H29) -> 1671.9452 | I30: =SUM(I28:I29) -> 1781.2161 | K30: =(I30/C30)^(1/5)-1 -> 0.06403199 | M30: Pretax profit less taxes.
A32: Depreciation & amortization | B32: ='Historical Data'!E32 -> 479 | C32: ='Historical Data'!F32 -> 477 | D32: =D135 -> 334.425 | E32: =E135 -> 354.32329 | F32: =F135 -> 367.38691 | G32: =G135 -> 387.15233 | H32: =H135 -> 398.46325 | I32: =I135 -> 416.67302 | M32: Based on PP&E/intangible schedules and historical D&A intensity.
A33: EBITDA | B33: ='Historical Data'!E33 -> 1920 | C33: ='Historical Data'!F33 -> 2212 | D33: =D24+D32 -> 1974.3938 | E33: =E24+E32 -> 2125.9397 | F33: =F24+F32 -> 2276.3581 | G33: =G24+G32 -> 2436.7823 | H33: =H24+H32 -> 2582.0419 | I33: =I24+I32 -> 2725.0416 | K33: =(I33/C33)^(1/5)-1 -> 0.042599714
A34: Adjusted operating profit | B34: ='Historical Data'!E34 -> 1600 | C34: ='Historical Data'!F34 -> 1687 | D34: =D17*0.28 -> 1800.75 | E34: =E17*0.284 -> 1935.1503 | F34: =F17*0.288 -> 2074.6555 | G34: =G17*0.292 -> 2216.6369 | H34: =H17*0.295 -> 2350.9332 | I34: =I17*0.297 -> 2475.0378 | M34: Operating profit excluding acquired-intangible amortization / benchmark adjustments.
A35: Adjusted EBITDA | B35: ='Historical Data'!E35 -> 1930 | C35: ='Historical Data'!F35 -> 2007 | D35: =D34+D32 -> 2135.175 | E35: =E34+E32 -> 2289.4735 | F35: =F34+F32 -> 2442.0424 | G35: =G34+G32 -> 2603.7892 | H35: =H34+H32 -> 2749.3964 | I35: =I34+I32 -> 2891.7108 | M35: Adjusted operating profit + applicable D&A
A37: Growth rates & margins | K37: Step | M37: Comments
A38: Revenue growth | C38: =C17/B17-1 -> 0.035327924 | D38: 0.05 | E38: 0.0595 | F38: 0.0572 | G38: 0.0538 | H38: 0.0498 | I38: 0.0457 | M38: 2026E anchored to management’s expectation for “good organic growth”; later years gradually normalize toward mature mid-single-digit growth.
A39: Gross profit margin | B39: =B19/B17 -> 0.72515213 | C39: =C19/C17 -> 0.73469388 | D39: 0.74 | E39: 0.742 | F39: 0.743 | G39: 0.744 | H39: 0.745 | I39: 0.746 | M39: Assumes gradual improvement from higher recurring/cloud mix and operating leverage; model assumption based on historical margin trend.
A40: Product development / R&D % of revenue | B40: =-B20/B17 -> 0.11629479 | C40: =-C20/C17 -> 0.11820408 | D40: 0.12 | E40: 0.121 | F40: 0.122 | G40: 0.122 | H40: 0.122 | I40: 0.122 | M40: Increased to reflect heavier AI/product investment; 2026 guided product-development spending is 12–13% of revenue
A41: S&M % of revenue | B41: =-B21/B17 -> 0.1637931 | C41: =-C21/C17 -> 0.15918367 | D41: 0.158 | E41: 0.157 | F41: 0.156 | G41: 0.155 | H41: 0.154 | I41: 0.153 | M41: Gradual decline assumes scale efficiencies as recurring/cloud revenue grows; model assumption based on historical trend.
A42: G&A % of revenue | B42: =-SUM(B22:B23)/B17 -> 0.19979716 | C42: =-SUM(C22:C23)/C17 -> 0.2075102 | D42: =-SUM(D22:D23)/D17 -> 0.207 | E42: =-SUM(E22:E23)/E17 -> 0.204 | F42: =-SUM(F22:F23)/F17 -> 0.2 | G42: =-SUM(G22:G23)/G17 -> 0.197 | H42: =-SUM(H22:H23)/H17 -> 0.195 | I42: =-SUM(I22:I23)/I17 -> 0.194 | M42: Gradual decline assumes operating leverage and productivity gains as revenue scales; model assumption.
A43: Operating margin | B43: =B24/B17 -> 0.24357674 | C43: =C24/C17 -> 0.28326531 | D43: =D24/D17 -> 0.255 | E43: =E24/E17 -> 0.26 | F43: =F24/F17 -> 0.265 | G43: =G24/G17 -> 0.27 | H43: =H24/H17 -> 0.274 | I43: =I24/I17 -> 0.277 | M43: Formula-driven from gross margin and operating expenses; improves as revenue growth and operating leverage outweigh higher product investment.
A44: Effective tax rate | B44: =-B29/B28 -> 0.21729651 | C44: =-C29/C28 -> 0.20704311 | D44: 0.21 | E44: 0.21 | F44: 0.21 | G44: 0.21 | H44: 0.21 | I44: 0.21 | M44: Normalized model assumption; note that Wolters Kluwer’s 2026 benchmark tax-rate guidance is 23.5–24.5%, so 21% is more appropriate for IFRS effective tax only if separately justified
A45: Adjusted operating margin | B45: =B34/B17 -> 0.27045301 | C45: =C34/C17 -> 0.27542857 | D45: =D34/D17 -> 0.28 | E45: =E34/E17 -> 0.284 | F45: =F34/F17 -> 0.288 | G45: =G34/G17 -> 0.292 | H45: =H34/H17 -> 0.295 | I45: =I34/I17 -> 0.297 | M45: 2026E anchored directly to management guidance of ~28.0%; later years assume modest continued operating leverage.
A46: Total product development % of revenue | B46: ='Historical Data'!E47 -> 0.11 | C46: ='Historical Data'!F47 -> 0.11 | D46: 0.125 | E46: 0.125 | F46: 0.125 | G46: 0.125 | H46: 0.125 | I46: 0.125 | M46: 2026E–2031E held at 12.5%, the midpoint of management’s 2026 guidance range of 12–13%, explicitly linked to advancing the AI strategy.
A48: BALANCE SHEET | K48: Comments
B49: 2024A | C49: 2025A | D49: 2026E | E49: 2027E | F49: 2028E | G49: 2029E | H49: 2030E | I49: 2031E
A51: Cash & equivalents | B51: ='Historical Data'!E53 -> 954 | C51: ='Historical Data'!F53 -> 932 | D51: =C51+D98 -> 1381.3891 | E51: =D51+E98 -> 1934.5268 | F51: =E51+F98 -> 2524.7047 | G51: =F51+G98 -> 3160.8361 | H51: =G51+H98 -> 3828.3733 | I51: =H51+I98 -> 4536.2063
A52: Accounts receivable | B52: ='Historical Data'!E54 -> 1129 | C52: ='Historical Data'!F54 -> 1075 | D52: =D107 -> 1127.6712 | E52: =E107 -> 1194.7677 | F52: =F107 -> 1263.1084 | G52: =G107 -> 1331.0636 | H52: =H107 -> 1397.3506 | I52: =I107 -> 1461.2095
A53: Inventories | B53: ='Historical Data'!E55 -> 79 | C53: ='Historical Data'!F55 -> 62 | D53: =D114 -> 64.136301 | E53: =E114 -> 67.4297 | F53: =F114 -> 71.010374 | G53: =G114 -> 74.539562 | H53: =H114 -> 77.945962 | I53: =I114 -> 81.188453
A54: Other current assets | B54: ='Historical Data'!E56 -> 495 | C54: ='Historical Data'!F56 -> 564 | D54: =D17*9.2% -> 591.675 | E54: =E17*9.2% -> 626.87966 | F54: =F17*9.2% -> 662.73718 | G54: =G17*9.2% -> 698.39244 | H54: =H17*9.2% -> 733.17238 | I54: =I17*9.2% -> 766.67836
A55: Property, plant & equipment | B55: ='Historical Data'!E57 -> 79 | C55: ='Historical Data'!F57 -> 68 | D55: =D130 -> 75.8975 | E55: =E130 -> 82.564339 | F55: =F130 -> 88.338577 | G55: =G130 -> 93.416488 | H55: =H130 -> 97.906143 | I55: =I130 -> 101.86814
A56: Other non current assets | B56: ='Historical Data'!E58 -> 6762 | C56: ='Historical Data'!F58 -> 6883 | D56: =D141+D17*4.4% -> 6861.3525 | E56: =E141+E17*4.4% -> 6813.6044 | F56: =F141+F17*4.4% -> 6770.952 | G56: =G141+G17*4.4% -> 6725.9924 | H56: =H141+H17*4.4% -> 6686.3364 | I56: =I141+I17*4.4% -> 6644.2315
A58: Total assets | B58: ='Historical Data'!E60 -> 9498 | C58: ='Historical Data'!F60 -> 9584 | D58: =SUM(D51:D56) -> 10102.122 | E58: =SUM(E51:E56) -> 10719.773 | F58: =SUM(F51:F56) -> 11380.851 | G58: =SUM(G51:G56) -> 12084.241 | H58: =SUM(H51:H56) -> 12821.085 | I58: =SUM(I51:I56) -> 13591.382
A60: Trade & other payables | B60: ='Historical Data'!E62 -> 1087 | C60: ='Historical Data'!F62 -> 1118 | D60: =D17*18.3% -> 1176.9188 | E60: =E17*18.3% -> 1246.9454 | F60: =F17*18.3% -> 1318.2707 | G60: =G17*18.3% -> 1389.1937 | H60: =H17*18.3% -> 1458.3755 | I60: =I17*18.3% -> 1525.0233
A61: Other current liabilities | B61: ='Historical Data'!E63 -> 221 | C61: ='Historical Data'!F63 -> 251 | D61: =D17*4.1% -> 263.68125 | E61: =E17*4.1% -> 279.37028 | F61: =F17*4.1% -> 295.35026 | G61: =G17*4.1% -> 311.24011 | H61: =H17*4.1% -> 326.73987 | I61: =I17*4.1% -> 341.67188
A62: Deferred / unearned revenue | B62: ='Historical Data'!E64 -> 2054 | C62: ='Historical Data'!F64 -> 1911 | D62: =D121 -> 2025.8438 | E62: =E121 -> 2146.3815 | F62: =F121 -> 2269.1545 | G62: =G121 -> 2391.235 | H62: =H121 -> 2510.3185 | I62: =I121 -> 2625.04
A63: Debt, current / revolver | B63: ='Historical Data'!E65 -> 359 | C63: ='Historical Data'!F65 -> 721 | D63: =D159 -> 721 | E63: =E159 -> 721 | F63: =F159 -> 721 | G63: =G159 -> 721 | H63: =H159 -> 721 | I63: =I159 -> 721
A64: Long term debt | B64: ='Historical Data'!E66 -> 3484 | C64: ='Historical Data'!F66 -> 4033 | D64: =D162 -> 4033 | E64: =E162 -> 4033 | F64: =F162 -> 4033 | G64: =G162 -> 4033 | H64: =H162 -> 4033 | I64: =I162 -> 4033
A65: Other non current liabilities | B65: ='Historical Data'!E67 -> 748 | C65: ='Historical Data'!F67 -> 752 | D65: =D17*12.2% -> 784.6125 | E65: =E17*12.2% -> 831.29694 | F65: =F17*12.2% -> 878.84713 | G65: =G17*12.2% -> 926.1291 | H65: =H17*12.2% -> 972.25033 | I65: =I17*12.2% -> 1016.6822
A67: Total liabilities | B67: ='Historical Data'!E69 -> 7953 | C67: ='Historical Data'!F69 -> 8786 | D67: =SUM(D60:D65) -> 9005.0562 | E67: =SUM(E60:E65) -> 9257.9941 | F67: =SUM(F60:F65) -> 9515.6226 | G67: =SUM(G60:G65) -> 9771.7979 | H67: =SUM(H60:H65) -> 10021.684 | I67: =SUM(I60:I65) -> 10262.417
A69: Common stock / share capital | B69: ='Historical Data'!E71 -> 29 | C69: ='Historical Data'!F71 -> 28 | D69: =C69 -> 28 | E69: =D69 -> 28 | F69: =E69 -> 28 | G69: =F69 -> 28 | H69: =G69 -> 28 | I69: =H69 -> 28
A70: Retained earnings | B70: ='Historical Data'!E72 -> 1359 | C70: ='Historical Data'!F72 -> 1171 | D70: =D147 -> 1856.9459 | E70: =E147 -> 2607.6216 | F70: =F147 -> 3426.5002 | G70: =G147 -> 4312.8811 | H70: =H147 -> 5265.8899 | I70: =I147 -> 6281.183
A71: Other Equity | B71: ='Historical Data'!E73 -> 157 | C71: ='Historical Data'!F73 -> -401 | D71: =D72-D69-D70 -> -787.88053 | E71: =E72-E69-E70 -> -1173.8431 | F71: =F72-F69-F70 -> -1589.2716 | G71: =G72-G69-G70 -> -2028.4384 | H71: =H72-H69-H70 -> -2494.4892 | I71: =I72-I69-I70 -> -2980.2181
A72: Total equity | B72: ='Historical Data'!E74 -> 1545 | C72: ='Historical Data'!F74 -> 798 | D72: =D58-D67 -> 1097.0654 | E72: =E58-E67 -> 1461.7785 | F72: =F58-F67 -> 1865.2286 | G72: =G58-G67 -> 2312.4427 | H72: =H58-H67 -> 2799.4006 | I72: =I58-I67 -> 3328.965
A74: Balance check | B74: ='Historical Data'!E76 -> 0 | C74: ='Historical Data'!F76 -> 0 | D74: =D58-D67-D72 -> 0 | E74: =E58-E67-E72 -> 0 | F74: =F58-F67-F72 -> 0 | G74: =G58-G67-G72 -> 0 | H74: =H58-H67-H72 -> 0 | I74: =I58-I67-I72 -> 0
A76: CASH FLOW STATEMENT | K76: Comments
D77: 2026 | E77: 2027 | F77: 2028 | G77: 2029 | H77: 2030 | I77: 2031
A79: Net income | D79: =D30 -> 1203.4139 | E79: =E30 -> 1316.9748 | F79: =F30 -> 1436.6292 | G79: =G30 -> 1555.0542 | H79: =H30 -> 1671.9452 | I79: =I30 -> 1781.2161
A80: Depreciation and amortization | D80: =D32 -> 334.425 | E80: =E32 -> 354.32329 | F80: =F32 -> 367.38691 | G80: =G32 -> 387.15233 | H80: =H32 -> 398.46325 | I80: =I32 -> 416.67302
A81: Stock based compensation | D81: =D17*0.42% -> 27.01125 | E81: =E17*0.42% -> 28.618419 | F81: =F17*0.42% -> 30.255393 | G81: =G17*0.42% -> 31.883133 | H81: =H17*0.42% -> 33.470913 | I81: =I17*0.42% -> 35.000534
A82: Decreases / (Increases) in working capital assets | D82: =-((D52+D53+D54)-(C52+C53+C54)) -> -82.482534 | E82: =-((E52+E53+E54)-(D52+D53+D54)) -> -105.5945 | F82: =-((F52+F53+F54)-(E52+E53+E54)) -> -107.7789 | G82: =-((G52+G53+G54)-(F52+F53+F54)) -> -107.13968 | H82: =-((H52+H53+H54)-(G52+G53+G54)) -> -104.47331 | I82: =-((I52+I53+I54)-(H52+H53+H54)) -> -100.60739
A83: Increases / (Decreases) in working capital liabilities | D83: =(D60+D61+D62)-(C60+C61+C62) -> 186.44375 | E83: =(E60+E61+E62)-(D60+D61+D62) -> 206.2534 | F83: =(F60+F61+F62)-(E60+E61+E62) -> 210.07828 | G83: =(G60+G61+G62)-(F60+F61+F62) -> 208.89332 | H83: =(H60+H61+H62)-(G60+G61+G62) -> 203.7651 | I83: =(I60+I61+I62)-(H60+H61+H62) -> 196.30133
A84: Other non current assets | D84: =-(D56-C56) -> 21.6475 | E84: =-(E56-D56) -> 47.748056 | F84: =-(F56-E56) -> 42.652478 | G84: =-(G56-F56) -> 44.959562 | H84: =-(H56-G56) -> 39.655992 | I84: =-(I56-H56) -> 42.104894
A85: Other non current liabilities | D85: =D65-C65 -> 32.6125 | E85: =E65-D65 -> 46.684444 | F85: =F65-E65 -> 47.550185 | G85: =G65-F65 -> 47.281976 | H85: =H65-G65 -> 46.121229 | I85: =I65-H65 -> 44.43184
A86: Cash from operating activities | D86: =SUM(D79:D85) -> 1723.0714 | E86: =SUM(E79:E85) -> 1895.0079 | F86: =SUM(F79:F85) -> 2026.7735 | G86: =SUM(G79:G85) -> 2168.0848 | H86: =SUM(H79:H85) -> 2288.9484 | I86: =SUM(I79:I85) -> 2415.1203
A88: Capital expenditures | D88: =-D17*0.055 -> -353.71875 | E88: =-E17*0.054 -> -367.95111 | F88: =-F17*0.053 -> -381.79424 | G88: =-G17*0.052 -> -394.74355 | H88: =-H17*0.051 -> -406.43252 | I88: =-I17*0.05 -> -416.67302
A89: Acquisitions, net | D89: =-D17*0.02 -> -128.625 | E89: =-E17*0.015 -> -102.20864 | F89: =-F17*0.015 -> -108.05497 | G89: =-G17*0.015 -> -113.86833 | H89: =-H17*0.015 -> -119.53898 | I89: =-I17*0.015 -> -125.00191
A90: Cash from investing activities | D90: =SUM(D88:D89) -> -482.34375 | E90: =SUM(E88:E89) -> -470.15975 | F90: =SUM(F88:F89) -> -489.84922 | G90: =SUM(G88:G89) -> -508.61189 | H90: =SUM(H88:H89) -> -525.97149 | I90: =SUM(I88:I89) -> -541.67493
A92: Long term debt | D92: 0 | E92: 0 | F92: 0 | G92: 0 | H92: 0 | I92: 0
A93: Revolver / current debt | D93: 0 | E93: 0 | F93: 0 | G93: 0 | H93: 0 | I93: 0
A94: Share repurchases | D94: =-MAX(0,(D86+D88)*20%) -> -273.87053 | E94: =-MAX(0,(E86+E88)*20%) -> -305.41136 | F94: =-MAX(0,(F86+F88)*20%) -> -328.99586 | G94: =-MAX(0,(G86+G88)*20%) -> -354.66825 | H94: =-MAX(0,(H86+H88)*20%) -> -376.50318 | I94: =-MAX(0,(I86+I88)*20%) -> -399.68945
A95: Common dividends | D95: =-D79*43% -> -517.46798 | E95: =-E79*43% -> -566.29917 | F95: =-F79*43% -> -617.75056 | G95: =-G79*43% -> -668.6733 | H95: =-H79*43% -> -718.93645 | I95: =-I79*43% -> -765.92291
A96: Cash from financing activities | D96: =SUM(D92:D95) -> -791.33851 | E96: =SUM(E92:E95) -> -871.71053 | F96: =SUM(F92:F95) -> -946.74642 | G96: =SUM(G92:G95) -> -1023.3416 | H96: =SUM(H92:H95) -> -1095.4396 | I96: =SUM(I92:I95) -> -1165.6124
A98: Net change in cash during period | D98: =SUM(D86,D90,D96) -> 449.38912 | E98: =SUM(E86,E90,E96) -> 553.13764 | F98: =SUM(F86,F90,F96) -> 590.17791 | G98: =SUM(G86,G90,G96) -> 636.13138 | H98: =SUM(H86,H90,H96) -> 667.53729 | I98: =SUM(I86,I90,I96) -> 707.833
A101: WORKING CAPITAL
A102: ACCOUNTS RECEIVABLE
A105: Beginning of period | D105: =C107 -> 1075 | E105: =D107 -> 1127.6712 | F105: =E107 -> 1194.7677 | G105: =F107 -> 1263.1084 | H105: =G107 -> 1331.0636 | I105: =H107 -> 1397.3506
A106: Increases / (decreases) | D106: =D107-D105 -> 52.671233 | E106: =E107-E105 -> 67.096438 | F106: =F107-F105 -> 68.340711 | G106: =G107-G105 -> 67.955231 | H106: =H107-H105 -> 66.286968 | I106: =I107-I105 -> 63.858922
A107: End of period | B107: =B52 -> 1129 | C107: =C52 -> 1075 | D107: =D17*D109/365 -> 1127.6712 | E107: =E17*E109/365 -> 1194.7677 | F107: =F17*F109/365 -> 1263.1084 | G107: =G17*G109/365 -> 1331.0636 | H107: =H17*H109/365 -> 1397.3506 | I107: =I17*I109/365 -> 1461.2095
A109: Days sales outstanding (DSO) assumption | D109: 64 | E109: 64 | F109: 64 | G109: 64 | H109: 64 | I109: 64
A111: INVENTORIES
A112: Beginning of period | D112: =C114 -> 62 | E112: =D114 -> 64.136301 | F112: =E114 -> 67.4297 | G112: =F114 -> 71.010374 | H112: =G114 -> 74.539562 | I112: =H114 -> 77.945962
A113: Increases / (decreases) | D113: =D114-D112 -> 2.1363014 | E113: =E114-E112 -> 3.2933991 | F113: =F114-F112 -> 3.5806739 | G113: =G114-G112 -> 3.529188 | H113: =H114-H112 -> 3.4063998 | I113: =I114-I112 -> 3.2424909
A114: End of period | B114: =B53 -> 79 | C114: =C53 -> 62 | D114: =-D18*D116/365 -> 64.136301 | E114: =-E18*E116/365 -> 67.4297 | F114: =-F18*F116/365 -> 71.010374 | G114: =-G18*G116/365 -> 74.539562 | H114: =-H18*H116/365 -> 77.945962 | I114: =-I18*I116/365 -> 81.188453
A116: Inventory days on cost of revenue | D116: 14 | E116: 14 | F116: 14 | G116: 14 | H116: 14 | I116: 14
A118: DEFERRED / UNEARNED REVENUE
A119: Beginning of period | D119: =C121 -> 1911 | E119: =D121 -> 2025.8438 | F119: =E121 -> 2146.3815 | G119: =F121 -> 2269.1545 | H119: =G121 -> 2391.235 | I119: =H121 -> 2510.3185
A120: Increases / (decreases) | D120: =D121-D119 -> 114.84375 | E120: =E121-E119 -> 120.5377 | F120: =F121-F119 -> 122.77302 | G120: =G121-G119 -> 122.08051 | H120: =H121-H119 -> 119.0835 | I120: =I121-I119 -> 114.72155
A121: End of period | B121: =B62 -> 2054 | C121: =C62 -> 1911 | D121: =D17*D123 -> 2025.8438 | E121: =E17*E123 -> 2146.3815 | F121: =F17*F123 -> 2269.1545 | G121: =G17*G123 -> 2391.235 | H121: =H17*H123 -> 2510.3185 | I121: =I17*I123 -> 2625.04
A123: Deferred revenue % of revenue | D123: 0.315 | E123: 0.315 | F123: 0.315 | G123: 0.315 | H123: 0.315 | I123: 0.315
A125: PROPERTY, PLANT & EQUIPMENT
B126: 2024 | C126: 2025 | D126: 2026 | E126: 2027 | F126: 2028 | G126: 2029 | H126: 2030 | I126: 2031
A127: Beginning of period | D127: =C130 -> 68 | E127: =D130 -> 75.8975 | F127: =E130 -> 82.564339 | G127: =F130 -> 88.338577 | H127: =G130 -> 93.416488 | I127: =H130 -> 97.906143
A128: Plus: PP&E capital expenditures | D128: =-D88*8% -> 28.2975 | E128: =-E88*8% -> 29.436088 | F128: =-F88*8% -> 30.54354 | G128: =-G88*8% -> 31.579484 | H128: =-H88*8% -> 32.514601 | I128: =-I88*8% -> 33.333842
...

Sheet Revenue Build_Empty
A2: CCH Axcess Expert AI - Price / Volume Build
A3: Fiscal year | B3: 2024 | C3: 2025 | D3: 2026 | E3: 2027 | F3: 2028 | G3: 2029 | H3: 2030 | I3: 2031
A4: Fiscal year end date | B4: 2024A | C4: 2025A | D4: 2026E | E4: 2027E | F4: 2028E | G4: 2029E | H4: 2030E | I4: 2031E
A5: Revenue & AI value build
A6: Core T&A revenue (without incremental AI scaling) | B6: 1561 | C6: 1660 | D6: =C6*(1+D25) -> 1776.2 | E6: =D6*(1+E25) -> 1900.534 | F6: =E6*(1+F25) -> 2024.0687 | G6: =F6*(1+G25) -> 2145.5128 | H6: =G6*(1+H25) -> 2263.516 | I6: =H6*(1+I25) -> 2376.6918
A7: Direct AI module revenue | B7: 0 | C7: 0 | D7: =D17*D18/1000000 -> 6.25 | E7: =E17*E18/1000000 -> 15.3 | F7: =F17*F18/1000000 -> 27.539625 | G7: =G17*G18/1000000 -> 43.191891 | H7: =H17*H18/1000000 -> 62.531303 | I7: =I17*I18/1000000 -> 85.848184
A8: Commercial expansion value | B8: 0 | C8: 0 | D8: =D7*D19 -> 0.9375 | E8: =E7*E19 -> 2.295 | F8: =F7*F19 -> 4.1309438 | G8: =G7*G19 -> 6.4787837 | H8: =H7*H19 -> 9.3796954 | I8: =I7*I19 -> 12.877228
A9: Total AI economic benefit | B9: 0 | C9: 0 | D9: =SUM(D7:D8) -> 7.1875 | E9: =SUM(E7:E8) -> 17.595 | F9: =SUM(F7:F8) -> 31.670569 | G9: =SUM(G7:G8) -> 49.670675 | H9: =SUM(H7:H8) -> 71.910998 | I9: =SUM(I7:I8) -> 98.725412
A10: T&A revenue incl. modeled AI benefit | B10: =B6+B9 -> 1561 | C10: =C6+C9 -> 1660 | D10: =D6+D9 -> 1783.3875 | E10: =E6+E9 -> 1918.129 | F10: =F6+F9 -> 2055.7393 | G10: =G6+G9 -> 2195.1835 | H10: =H6+H9 -> 2335.427 | I10: =I6+I9 -> 2475.4173
A11: % growth | C11: =C10/B10-1 -> 0.063420884 | D11: =D10/C10-1 -> 0.074329819 | E11: =E10/D10-1 -> 0.075553686 | F11: =F10/E10-1 -> 0.071741931 | G11: =G10/F10-1 -> 0.06783167 | H11: =H10/G10-1 -> 0.063886927 | I11: =I10/H10-1 -> 0.059942021
A13: Operating drivers
A14: CCH Axcess installed firms | D14: 10000 | E14: =D14*(1+E26) -> 10300 | F14: =E14*(1+F26) -> 10609 | G14: =F14*(1+G26) -> 10927.27 | H14: =G14*(1+H26) -> 11255.088 | I14: =H14*(1+I26) -> 11592.741
A15: AI adoption rate | B15: 0 | C15: 0 | D15: 0.04 | E15: 0.08 | F15: 0.13 | G15: 0.19 | H15: 0.26 | I15: 0.34
A16: Year-end agentic AI customers | B16: 0 | C16: 0 | D16: =D14*D15 -> 400 | E16: =E14*E15 -> 824 | F16: =F14*F15 -> 1379.17 | G16: =G14*G15 -> 2076.1813 | H16: =H14*H15 -> 2926.3229 | I16: =I14*I15 -> 3941.5319
A17: Average subscribed firms | B17: 0 | C17: 0 | D17: 250 | E17: =AVERAGE(D16,E16) -> 612 | F17: =AVERAGE(E16,F16) -> 1101.585 | G17: =AVERAGE(F16,G16) -> 1727.6757 | H17: =AVERAGE(G16,H16) -> 2501.2521 | I17: =AVERAGE(H16,I16) -> 3433.9274
A18: Incremental AI ARPU (€ / firm-year) | B18: 0 | C18: 0 | D18: 25000 | E18: 25000 | F18: 25000 | G18: 25000 | H18: 25000 | I18: 25000
A19: Commercial expansion value (% of direct revenue) | B19: 0 | C19: 0 | D19: 0.15 | E19: 0.15 | F19: 0.15 | G19: 0.15 | H19: 0.15 | I19: 0.15
A21: AI investment & cash flow build
A22: Product development intensity | B22: 0.11 | C22: 0.11 | D22: 0.125 | E22: 0.125 | F22: 0.125 | G22: 0.125 | H22: 0.125 | I22: 0.125
A23: T&A product development proxy | B23: =B6*B22 -> 171.71 | C23: =C6*C22 -> 182.6 | D23: =D6*D22 -> 222.025 | E23: =E6*E22 -> 237.56675 | F23: =F6*F22 -> 253.00859 | G23: =G6*G22 -> 268.1891 | H23: =H6*H22 -> 282.9395 | I23: =I6*I22 -> 297.08648
A24: AI share of T&A product development | B24: 0 | C24: 0.08 | D24: 0.08 | E24: 0.08 | F24: 0.08 | G24: 0.08 | H24: 0.08 | I24: 0.08
A25: T&A core revenue growth | C25: 0.07 | D25: 0.07 | E25: 0.07 | F25: 0.065 | G25: 0.06 | H25: 0.055 | I25: 0.05
A26: Installed-base growth | D26: 0.03 | E26: 0.03 | F26: 0.03 | G26: 0.03 | H26: 0.03 | I26: 0.03
A27: AI-attributed development investment | B27: =B23*B24 -> 0 | C27: =C23*C24 -> 14.608 | D27: =D23*D24 -> 17.762 | E27: =E23*E24 -> 19.00534 | F27: =F23*F24 -> 20.240687 | G27: =G23*G24 -> 21.455128 | H27: =H23*H24 -> 22.63516 | I27: =I23*I24 -> 23.766918
A28: AI delivery cost (% of direct AI revenue) | B28: 0.15 | C28: 0.15 | D28: 0.15 | E28: 0.15 | F28: 0.15 | G28: 0.15 | H28: 0.15 | I28: 0.15
A29: AI variable delivery cost | B29: =B7*B28 -> 0 | C29: =C7*C28 -> 0 | D29: =D7*D28 -> 0.9375 | E29: =E7*E28 -> 2.295 | F29: =F7*F28 -> 4.1309438 | G29: =G7*G28 -> 6.4787837 | H29: =H7*H28 -> 9.3796954 | I29: =I7*I28 -> 12.877228
A30: Recurring AI platform / governance fixed cost | B30: 0 | C30: 3 | D30: 5 | E30: =D30*1.03 -> 5.15 | F30: =E30*1.03 -> 5.3045 | G30: =F30*1.03 -> 5.463635 | H30: =G30*1.03 -> 5.6275441 | I30: =H30*1.03 -> 5.7963704
A31: Total AI cost | B31: =SUM(B27,B29,B30) -> 0 | C31: =SUM(C27,C29,C30) -> 17.608 | D31: =SUM(D27,D29,D30) -> 23.6995 | E31: =SUM(E27,E29,E30) -> 26.45034 | F31: =SUM(F27,F29,F30) -> 29.676131 | G31: =SUM(G27,G29,G30) -> 33.397547 | H31: =SUM(H27,H29,H30) -> 37.6424 | I31: =SUM(I27,I29,I30) -> 42.440516
A32: AI EBIT before tax | B32: =B9-B31 -> 0 | C32: =C9-C31 -> -17.608 | D32: =D9-D31 -> -16.512 | E32: =E9-E31 -> -8.85534 | F32: =F9-F31 -> 1.9944379 | G32: =G9-G31 -> 16.273128 | H32: =H9-H31 -> 34.268598 | I32: =I9-I31 -> 56.284896
A33: Cash tax on positive AI EBIT | B33: =IF(B32>0,B32*23.6%,0) -> 0 | C33: =IF(C32>0,C32*23.6%,0) -> 0 | D33: =IF(D32>0,D32*23.6%,0) -> 0 | E33: =IF(E32>0,E32*23.6%,0) -> 0 | F33: =IF(F32>0,F32*23.6%,0) -> 0.47068734 | G33: =IF(G32>0,G32*23.6%,0) -> 3.8404582 | H33: =IF(H32>0,H32*23.6%,0) -> 8.0873892 | I33: =IF(I32>0,I32*23.6%,0) -> 13.283235
A34: Incremental AI free cash flow | B34: =B32-B33 -> 0 | C34: =C32-C33 -> -17.608 | D34: =D32-D33 -> -16.512 | E34: =E32-E33 -> -8.85534 | F34: =F32-F33 -> 1.5237506 | G34: =G32-G33 -> 12.43267 | H34: =H32-H33 -> 26.181209 | I34: =I32-I33 -> 43.00166
A35: Cumulative AI ROI | C35: =(SUM($C$9:C9)-SUM($C$31:C31))/SUM($C$31:C31) -> -1 | D35: =(SUM($C$9:D9)-SUM($C$31:D31))/SUM($C$31:D31) -> -0.82600012 | E35: =(SUM($C$9:E9)-SUM($C$31:E31))/SUM($C$31:E31) -> -0.63424897 | F35: =(SUM($C$9:F9)-SUM($C$31:F31))/SUM($C$31:F31) -> -0.42060179 | G35: =(SUM($C$9:G9)-SUM($C$31:G31))/SUM($C$31:G31) -> -0.18885185 | H35: =(SUM($C$9:H9)-SUM($C$31:H31))/SUM($C$31:H31) -> 0.056749579 | I35: =(SUM($C$9:I9)-SUM($C$31:I31))/SUM($C$31:I31) -> 0.31219162

Sheet Integrated DCF
A2: Discounted Cash Flow Valuation - Wolters Kluwer
A3: € and shares in millions, except per share data
A4: Most recent fiscal year end | C4: 2025A | E4: Discount rate (WACC) | F4: =WACC!E21 -> 0.0798266
A5: First forecast year | C5: 2026E | E5: Long-term growth rate | F5: 0.025
A6: Valuation date | C6: 2026-08-25 | E6: Exit EBITDA multiple | F6: 12
A7: Primary method | C7: UFCF DCF | E7: AI incremental value | F7: =DCF!B49 -> 14.817892
A10: Unlevered Free Cash Flows
B11: 2025A | C11: 2026E | D11: 2027E | E11: 2028E | F11: 2029E | G11: 2030E | H11: 2031E
A13: Revenue | B13: =Forecast!C17 -> 6125 | C13: =Forecast!D17 -> 6431.25 | D13: =Forecast!E17 -> 6813.9094 | E13: =Forecast!F17 -> 7203.665 | F13: =Forecast!G17 -> 7591.2222 | G13: =Forecast!H17 -> 7969.265 | H13: =Forecast!I17 -> 8333.4604
A14: % growth | C14: =C13/B13-1 -> 0.05 | D14: =D13/C13-1 -> 0.0595 | E14: =E13/D13-1 -> 0.0572 | F14: =F13/E13-1 -> 0.0538 | G14: =G13/F13-1 -> 0.0498 | H14: =H13/G13-1 -> 0.0457
A15: EBITDA | B15: =Forecast!C35 -> 2007 | C15: =Forecast!D35 -> 2135.175 | D15: =Forecast!E35 -> 2289.4735 | E15: =Forecast!F35 -> 2442.0424 | F15: =Forecast!G35 -> 2603.7892 | G15: =Forecast!H35 -> 2749.3964 | H15: =Forecast!I35 -> 2891.7108
A16: % margin | B16: =B15/B13 -> 0.32767347 | C16: =C15/C13 -> 0.332 | D16: =D15/D13 -> 0.336 | E16: =E15/E13 -> 0.339 | F16: =F15/F13 -> 0.343 | G16: =G15/G13 -> 0.345 | H16: =H15/H13 -> 0.347
A17: EBIT | B17: =Forecast!C24 -> 1735 | C17: =Forecast!D24 -> 1639.9688 | D17: =Forecast!E24 -> 1771.6164 | E17: =Forecast!F24 -> 1908.9712 | F17: =Forecast!G24 -> 2049.63 | G17: =Forecast!H24 -> 2183.5786 | H17: =Forecast!I24 -> 2308.3685
A18: % margin | B18: =B17/B13 -> 0.28326531 | C18: =C17/C13 -> 0.255 | D18: =D17/D13 -> 0.26 | E18: =E17/E13 -> 0.265 | F18: =F17/F13 -> 0.27 | G18: =G17/G13 -> 0.274 | H18: =H17/H13 -> 0.277
A20: Tax on EBIT | B20: =-B17*21% -> -364.35 | C20: =-C17*21% -> -344.39344 | D20: =-D17*21% -> -372.03945 | E20: =-E17*21% -> -400.88396 | F20: =-F17*21% -> -430.4223 | G20: =-G17*21% -> -458.55151 | H20: =-H17*21% -> -484.75739
A21: Tax rate | B21: 0.21 | C21: 0.21 | D21: 0.21 | E21: 0.21 | F21: 0.21 | G21: 0.21 | H21: 0.21
A22: NOPAT (aka EBIAT) | B22: =B17+B20 -> 1370.65 | C22: =C17+C20 -> 1295.5753 | D22: =D17+D20 -> 1399.577 | E22: =E17+E20 -> 1508.0873 | F22: =F17+F20 -> 1619.2077 | G22: =G17+G20 -> 1725.0271 | H22: =H17+H20 -> 1823.6111
A25: Depreciation & amortization | B25: =Forecast!C32 -> 477 | C25: =Forecast!D32 -> 334.425 | D25: =Forecast!E32 -> 354.32329 | E25: =Forecast!F32 -> 367.38691 | F25: =Forecast!G32 -> 387.15233 | G25: =Forecast!H32 -> 398.46325 | H25: =Forecast!I32 -> 416.67302
A26: Changes in net working capital | B26: 0 | C26: =B31-C31 -> 103.96122 | D26: =C31-D31 -> 100.6589 | E26: =D31-E31 -> 102.29938 | F26: =E31-F31 -> 101.75364 | G26: =F31-G31 -> 99.291792 | H26: =G31-H31 -> 95.693937
A27: Capital expenditures | B27: =-'Historical Data'!F80 -> -305 | C27: =Forecast!D88 -> -353.71875 | D27: =Forecast!E88 -> -367.95111 | E27: =Forecast!F88 -> -381.79424 | F27: =Forecast!G88 -> -394.74355 | G27: =Forecast!H88 -> -406.43252 | H27: =Forecast!I88 -> -416.67302
A28: as % of revenue | B28: =-B27/B13 -> 0.049795918 | C28: =-C27/C13 -> 0.055 | D28: =-D27/D13 -> 0.054 | E28: =-E27/E13 -> 0.053 | F28: =-F27/F13 -> 0.052 | G28: =-G27/G13 -> 0.051 | H28: =-H27/H13 -> 0.05
A30: Unlevered free cash flows (UFCF) | B30: =SUM(B22,B25,B26,B27) -> 1542.65 | C30: =SUM(C22,C25,C26,C27) -> 1380.2428 | D30: =SUM(D22,D25,D26,D27) -> 1486.6081 | E30: =SUM(E22,E25,E26,E27) -> 1595.9793 | F30: =SUM(F22,F25,F26,F27) -> 1713.3701 | G30: =SUM(G22,G25,G26,G27) -> 1816.3496 | H30: =SUM(H22,H25,H26,H27) -> 1919.3051
A31: Net working capital | B31: ='Historical Data'!F54+'Historical Data'!F55+'Historical Data'!F56-'Historical Data'!F62-'Historical Data'!F63-'Historical Data'!F64 -> -1579 | C31: =Forecast!D52+Forecast!D53+Forecast!D54-Forecast!D60-Forecast!D61-Forecast!D62 -> -1682.9612 | D31: =Forecast!E52+Forecast!E53+Forecast!E54-Forecast!E60-Forecast!E61-Forecast!E62 -> -1783.6201 | E31: =Forecast!F52+Forecast!F53+Forecast!F54-Forecast!F60-Forecast!F61-Forecast!F62 -> -1885.9195 | F31: =Forecast!G52+Forecast!G53+Forecast!G54-Forecast!G60-Forecast!G61-Forecast!G62 -> -1987.6731 | G31: =Forecast!H52+Forecast!H53+Forecast!H54-Forecast!H60-Forecast!H61-Forecast!H62 -> -2086.9649 | H31: =Forecast!I52+Forecast!I53+Forecast!I54-Forecast!I60-Forecast!I61-Forecast!I62 -> -2182.6589
A32: as % of revenue | B32: =B31/B13 -> -0.25779592 | C32: =C31/C13 -> -0.26168493 | D32: =D31/D13 -> -0.26176164 | E32: =E31/E13 -> -0.2618 | F32: =F31/F13 -> -0.26183836 | G32: =G31/G13 -> -0.26187671 | H32: =H31/H13 -> -0.26191507
A35: Present value of UFCF
B36: 2025A | C36: 2026E | D36: 2027E | E36: 2028E | F36: 2029E | G36: 2030E | H36: 2031E
A37: Discount period | B37: 0 | C37: 1 | D37: 2 | E37: 3 | F37: 4 | G37: 5 | H37: 6
A38: Discount factor | B38: =1/(1+$F$4)^B37 -> 1 | C38: =1/(1+$F$4)^C37 -> 0.92607461 | D38: =1/(1+$F$4)^D37 -> 0.85761419 | E38: =1/(1+$F$4)^E37 -> 0.79421473 | F38: =1/(1+$F$4)^F37 -> 0.73550209 | G38: =1/(1+$F$4)^G37 -> 0.68112982 | H38: =1/(1+$F$4)^H37 -> 0.63077703
A39: UFCF | B39: =B30 -> 1542.65 | C39: =C30 -> 1380.2428 | D39: =D30 -> 1486.6081 | E39: =E30 -> 1595.9793 | F39: =F30 -> 1713.3701 | G39: =G30 -> 1816.3496 | H39: =H30 -> 1919.3051
A40: Present value of UFCF | B40: =B39*B38 -> 1542.65 | C40: =C39*C38 -> 1278.2078 | D40: =D39*D38 -> 1274.9362 | E40: =E39*E38 -> 1267.5503 | F40: =F39*F38 -> 1260.1873 | G40: =G39*G38 -> 1237.1699 | H40: =H39*H38 -> 1210.6536
A43: Terminal value - growth in perpetuity approach | E43: Terminal value - EBITDA multiple approach
A44: Long term growth rate | B44: =$F$5 -> 0.025 | E44: Terminal year EBITDA | H44: =H15 -> 2891.7108
A45: 2031 FCF x (1+g) | B45: =H30*(1+B44) -> 1967.2877 | E45: EBITDA multiple | H45: =$F$6 -> 12
A46: Terminal value in 2031 | B46: =B45/($F$4-B44) -> 35881.994 | E46: Terminal value in 2031 | H46: =H44*H45 -> 34700.529
A47: Present value of terminal value | B47: =B46*H38 -> 22633.537 | E47: Present value of terminal value | H47: =H46*H38 -> 21888.297
A48: Present value of stage 1 cash flows | B48: =SUM(C40:H40) -> 7528.705 | E48: Present value of stage 1 cash flows | H48: =B48 -> 7528.705
A49: Total enterprise value (TEV) | B49: =SUM(B47:B48) -> 30162.242 | E49: Enterprise value (stage 1 + 2) | H49: =SUM(H47:H48) -> 29417.002
A56: Net debt / AI value / shares
A57: Source doc | B57: 2025 Annual Report | E57: Source doc | F57: Date | G57: Shares
A58: Gross debt and equivalents | B58: ='Historical Data'!F87 -> 4971 | E58: Diluted share proxy | F58: 2026E | G58: =Shares!D12 -> 228
A59: Cash | B59: ='Historical Data'!F53 -> 932 | E59: Net diluted shares | G59: =G58 -> 228
A60: Net debt | B60: ='Historical Data'!F93 -> 4024
A61: AI incremental NPV | B61: =DCF!B49 -> 14.817892
A62: AI value as % of TEV | B62: =B61/B49 -> 0.0004912729
A63: AI value per share | B63: =B61/Shares!D12 -> 0.064990756
A66: Valuation
B67: Perpetuity | C67: EBITDA
A68: Enterprise value | B68: =B49 -> 30162.242 | C68: =H49 -> 29417.002
A69: Net debt | B69: =$B$60 -> 4024 | C69: =$B$60 -> 4024
A70: Equity value | B70: =B68-B69 -> 26138.242 | C70: =C68-C69 -> 25393.002
A71: Shares outstanding | B71: =$G$59 -> 228 | C71: =$G$59 -> 228
A72: Equity value per share | B72: =B70/B71 -> 114.64141 | C72: =C70/C71 -> 111.37282
A73: AI-adjusted equity value per share | B73: =(B70+$B$61)/B71 -> 114.7064 | C73: =(C70+$B$61)/C71 -> 111.43781

Sheet DCF
A2: CCH Axcess Expert AI - Incremental DCF / ROI
A3: € millions except per share data
A4: Most recent fiscal year end | C4: 2025A | E4: Discount rate (WACC) | F4: =WACC!E21 -> 0.0798266
A5: First forecast year | C5: 2026E | E5: Terminal growth rate | F5: 0.025
A6: Primary method | C6: Finite AI cash flows through 2031 | E6: AI investment hurdle reference | F6: 0.08
A7: Scenario | C7: Base case
A10: Incremental AI Cash Flows
B11: 2025A | C11: 2026E | D11: 2027E | E11: 2028E | F11: 2029E | G11: 2030E | H11: 2031E
A13: Total AI economic benefit | B13: ='Revenue Build_Empty'!C9 -> 0 | C13: ='Revenue Build_Empty'!D9 -> 7.1875 | D13: ='Revenue Build_Empty'!E9 -> 17.595 | E13: ='Revenue Build_Empty'!F9 -> 31.670569 | F13: ='Revenue Build_Empty'!G9 -> 49.670675 | G13: ='Revenue Build_Empty'!H9 -> 71.910998 | H13: ='Revenue Build_Empty'!I9 -> 98.725412
A14: Total AI cost | B14: ='Revenue Build_Empty'!C31 -> 17.608 | C14: ='Revenue Build_Empty'!D31 -> 23.6995 | D14: ='Revenue Build_Empty'!E31 -> 26.45034 | E14: ='Revenue Build_Empty'!F31 -> 29.676131 | F14: ='Revenue Build_Empty'!G31 -> 33.397547 | G14: ='Revenue Build_Empty'!H31 -> 37.6424 | H14: ='Revenue Build_Empty'!I31 -> 42.440516
A15: AI EBIT before tax | B15: ='Revenue Build_Empty'!C32 -> -17.608 | C15: ='Revenue Build_Empty'!D32 -> -16.512 | D15: ='Revenue Build_Empty'!E32 -> -8.85534 | E15: ='Revenue Build_Empty'!F32 -> 1.9944379 | F15: ='Revenue Build_Empty'!G32 -> 16.273128 | G15: ='Revenue Build_Empty'!H32 -> 34.268598 | H15: ='Revenue Build_Empty'!I32 -> 56.284896
A16: Cash tax on positive AI EBIT | B16: ='Revenue Build_Empty'!C33 -> 0 | C16: ='Revenue Build_Empty'!D33 -> 0 | D16: ='Revenue Build_Empty'!E33 -> 0 | E16: ='Revenue Build_Empty'!F33 -> 0.47068734 | F16: ='Revenue Build_Empty'!G33 -> 3.8404582 | G16: ='Revenue Build_Empty'!H33 -> 8.0873892 | H16: ='Revenue Build_Empty'!I33 -> 13.283235
A17: Incremental AI free cash flow | B17: ='Revenue Build_Empty'!C34 -> -17.608 | C17: ='Revenue Build_Empty'!D34 -> -16.512 | D17: ='Revenue Build_Empty'!E34 -> -8.85534 | E17: ='Revenue Build_Empty'!F34 -> 1.5237506 | F17: ='Revenue Build_Empty'!G34 -> 12.43267 | G17: ='Revenue Build_Empty'!H34 -> 26.181209 | H17: ='Revenue Build_Empty'!I34 -> 43.00166
A18: Cumulative AI benefit | B18: =SUM($B$13:B13) -> 0 | C18: =SUM($B$13:C13) -> 7.1875 | D18: =SUM($B$13:D13) -> 24.7825 | E18: =SUM($B$13:E13) -> 56.453069 | F18: =SUM($B$13:F13) -> 106.12374 | G18: =SUM($B$13:G13) -> 178.03474 | H18: =SUM($B$13:H13) -> 276.76015
A19: Cumulative AI cost | B19: =SUM($B$14:B14) -> 17.608 | C19: =SUM($B$14:C14) -> 41.3075 | D19: =SUM($B$14:D14) -> 67.75784 | E19: =SUM($B$14:E14) -> 97.433971 | F19: =SUM($B$14:F14) -> 130.83152 | G19: =SUM($B$14:G14) -> 168.47392 | H19: =SUM($B$14:H14) -> 210.91443
A20: Cumulative AI ROI | B20: =IF(B19=0,0,(B18-B19)/B19) -> -1 | C20: =IF(C19=0,0,(C18-C19)/C19) -> -0.82600012 | D20: =IF(D19=0,0,(D18-D19)/D19) -> -0.63424897 | E20: =IF(E19=0,0,(E18-E19)/E19) -> -0.42060179 | F20: =IF(F19=0,0,(F18-F19)/F19) -> -0.18885185 | G20: =IF(G19=0,0,(G18-G19)/G19) -> 0.056749579 | H20: =IF(H19=0,0,(H18-H19)/H19) -> 0.31219162
A21: Cumulative AI FCF | B21: =SUM($B$17:B17) -> -17.608 | C21: =SUM($B$17:C17) -> -34.12 | D21: =SUM($B$17:D17) -> -42.97534 | E21: =SUM($B$17:E17) -> -41.451589 | F21: =SUM($B$17:F17) -> -29.01892 | G21: =SUM($B$17:G17) -> -2.8377107 | H21: =SUM($B$17:H17) -> 40.16395
A23: Present Value of AI Free Cash Flows
B24: 2025A | C24: 2026E | D24: 2027E | E24: 2028E | F24: 2029E | G24: 2030E | H24: 2031E
A25: Discount period | B25: 0 | C25: 1 | D25: 2 | E25: 3 | F25: 4 | G25: 5 | H25: 6
A26: Discount factor | B26: =1/(1+$F$4)^B25 -> 1 | C26: =1/(1+$F$4)^C25 -> 0.92607461 | D26: =1/(1+$F$4)^D25 -> 0.85761419 | E26: =1/(1+$F$4)^E25 -> 0.79421473 | F26: =1/(1+$F$4)^F25 -> 0.73550209 | G26: =1/(1+$F$4)^G25 -> 0.68112982 | H26: =1/(1+$F$4)^H25 -> 0.63077703
A27: Incremental AI FCF | B27: =B17 -> -17.608 | C27: =C17 -> -16.512 | D27: =D17 -> -8.85534 | E27: =E17 -> 1.5237506 | F27: =F17 -> 12.43267 | G27: =G17 -> 26.181209 | H27: =H17 -> 43.00166
A28: Present value of AI FCF | B28: =B27*B26 -> -17.608 | C28: =C27*C26 -> -15.291344 | D28: =D27*D26 -> -7.5944652 | E28: =E27*E26 -> 1.2101851 | F28: =F27*F26 -> 9.1442546 | G28: =G27*G26 -> 17.832802 | H28: =H27*H26 -> 27.12446
A31: Primary valuation - finite cash flows
A32: NPV through 2031 (No TV) | B32: =SUM(B28:H28) -> 14.817892
A33: IRR | B33: =IF(AND(MIN(B17:H17)<0,MAX(B17:H17)>0),IRR(B17:H17),"N/M") -> 0.15687343
A34: Payback year | B34: =IF(C21>=0,2025+ABS(B21)/C17,IF(D21>=0,2026+ABS(C21)/D17,IF(E21>=0,2027+ABS(D21)/E17,IF(F21>=0,2028+ABS(E21)/F17,IF(G21>=0,2029+ABS(F21)/G17,IF(H21>=0,2030+ABS(G21)/H17,">2031")))))) -> 2030.066
A35: 2031 cumulative AI ROI | B35: =H20 -> 0.31219162
A36: Benefit / cost ratio | B36: =SUM(B13:H13)/SUM(B14:H14) -> 1.3121916
A39: Secondary valuation - terminal value
A40: Terminal growth rate | B40: =$F$5 -> 0.025
A41: Terminal value at 2031 | B41: =IF(H17<=0,0,H17*(1+B40)/($F$4-B40)) -> 803.92915
A42: PV of terminal value | B42: =B41*H26 -> 507.10004
A43: NPV incl. terminal value | B43: =B32+B42 -> 521.91793
A44: Terminal value % of total | B44: =IF(B43=0,0,B42/B43) -> 0.97160877
A48: Linked primary output
A49: AI NPV used in Integrated DCF | B49: =B32 -> 14.817892
A53: AI NPV Sensitivity - ARPU x Adoption
A54: Adoption multiplier | B54: 10000 | C54: 17500 | D54: 25000 | E54: 32500 | F54: 40000
A55: 0.7 | B55: =$B$17+(IF(((('Revenue Build_Empty'!D17*$A55*B$54/1000000)*(1+'Revenue Build_Empty'!D19))-(('Revenue Build_Empty'!D17*$A55*B$54/1000000)*'Revenue Build_Empty'!D28)-'Revenue Build_Empty'!D27-'Revenue Build_Empty'!D30)>0,((('Revenue Build_Empty'!D17*$A55*B$54/1000000)*(1+'Revenue Build_Empty'!D19))-(('Revenue Build_Empty'!D17*$A55*B$54/1000000)*'Revenue Build_Empty'!D28)-'Revenue Build_Empty'!D27-'Revenue Build_Empty'!D30)*(1-23.6%),((('Revenue Build_Empty'!D17*$A55*B$54/1000000)*(1+'Revenue Build_Empty'!D19))-(('Revenue Build_Empty'!D17*$A55*B$54/1000000)*'Revenue Build_Empty'!D28)-'Revenue Build_Empty'!D27-'Revenue Build_Empty'!D30)))/(1+$F$4)^1+(IF(((('Revenue Build_Empty'!E17*$A55*B$54/1000000)*(1+'Revenue Build_Empty'!E19))-(('Revenue Build_Empty'!E17*$A55*B$54/1000000)*'Revenue Build_Empty'!E28)-'Revenue Build_Empty'!E27-'Revenue Build_Empty'!E30)>0,((('Revenue Build_Empty'!E17*$A55*B$54/1000000)*(1+'Revenue Build_Empty'!E19))-(('Revenue Build_Empty'!E17*$A55*B$54/1000000)*'Revenue Build_Empty'!E28)-'Revenue Build_Empty'!E27-'Revenue Build_Empty'!E30)*(1-23.6%),((('Revenue Build_Empty'!E17*$A55*B$54/1000000)*(1+'Revenue Build_Empty'!E19))-(('Revenue Build_Empty'!E17*$A55*B$54/1000000)*'Revenue Build_Empty'!E28)-'Revenue Build_Empty'!E27-'Revenue Build_Empty'!E30)))/(1+$F$4)^2+(IF(((('Revenue Build_Empty'!F17*$A55*B$54/1000000)*(1+'Revenue Build_Empty'!F19))-(('Revenue Build_Empty'!F17*$A55*B$54/1000000)*'Revenue Build_Empty'!F28)-'Revenue Build_Empty'!F27-'Revenue Build_Empty'!F30)>0,((('Revenue Build_Empty'!F17*$A55*B$54/1000000)*(1+'Revenue Build_Empty'!F19))-(('Revenue Build_Empty'!F17*$A55*B$54/1000000)*'Revenue Build_Empty'!F28)-'Revenue Build_Empty'!F27-'Revenue Build_Empty'!F30)*(1-23.6%),((('Revenue Build_Empty'!F17*$A55*B$54/1000000)*(1+'Revenue Build_Empty'!F19))-(('Revenue Build_Empty'!F17*$A55*B$54/1000000)*'Revenue Build_Empty'!F28)-'Revenue Build_Empty'!F27-'Revenue Build_Empty'!F30)))/(1+$F$4)^3+(IF(((('Revenue Build_Empty'!G17*$A55*B$54/1000000)*(1+'Revenue Build_Empty'!G19))-(('Revenue Build_Empty'!G17*$A55*B$54/1000000)*'Revenue Build_Empty'!G28)-'Revenue Build_Empty'!G27-'Revenue Build_Empty'!G30)>0,((('Revenue Build_Empty'!G17*$A55*B$54/1000000)*(1+'Revenue Build_Empty'!G19))-(('Revenue Build_Empty'!G17*$A55*B$54/1000000)*'Revenue Build_Empty'!G28)-'Revenue Build_Empty'!G27-'Revenue Build_Empty'!G30)*(1-23.6%),((('Revenue Build_Empty'!G17*$A55*B$54/1000000)*(1+'Revenue Build_Empty'!G19))-(('Revenue Build_Empty'!G17*$A55*B$54/1000000)*'Revenue Build_Empty'!G28)-'Revenue Build_Empty'!G27-'Revenue Build_Empty'!G30)))/(1+$F$4)^4+(IF(((('Revenue Build_Empty'!H17*$A55*B$54/1000000)*(1+'Revenue Build_Empty'!H19))-(('Revenue Build_Empty'!H17*$A55*B$54/1000000)*'Revenue Build_Empty'!H28)-'Revenue Build_Empty'!H27-'Revenue Build_Empty'!H30)>0,((('Revenue Build_Empty'!H17*$A55*B$54/1000000)*(1+'Revenue Build_Empty'!H19))-(('Revenue Build_Empty'!H17*$A55*B$54/1000000)*'Revenue Build_Empty'!H28)-'Revenue Build_Empty'!H27-'Revenue Build_Empty'!H30)*(1-23.6%),((('Revenue Build_Empty'!H17*$A55*B$54/1000000)*(1+'Revenue Build_Empty'!H19))-(('Revenue Build_Empty'!H17*$A55*B$54/1000000)*'Revenue Build_Empty'!H28)-'Revenue Build_Empty'!H27-'Revenue Build_Empty'!H30)))/(1+$F$4)^5+(IF(((('Revenue Build_Empty'!I17*$A55*B$54/1000000)*(1+'Revenue Build_Empty'!I19))-(('Revenue Build_Empty'!I17*$A55*B$54/1000000)*'Revenue Build_Empty'!I28)-'Revenue Build_Empty'!I27-'Revenue Build_Empty'!I30)>0,((('Revenue Build_Empty'!I17*$A55*B$54/1000000)*(1+'Revenue Build_Empty'!I19))-(('Revenue Build_Empty'!I17*$A55*B$54/1000000)*'Revenue Build_Empty'!I28)-'Revenue Build_Empty'!I27-'Revenue Build_Empty'!I30)*(1-23.6%),((('Revenue Build_Empty'!I17*$A55*B$54/1000000)*(1+'Revenue Build_Empty'!I19))-(('Revenue Build_Empty'!I17*$A55*B$54/1000000)*'Revenue Build_Empty'!I28)-'Revenue Build_Empty'!I27-'Revenue Build_Empty'!I30)))/(1+$F$4)^6 -> -89.98694 | C55: =$B$17+(IF(((('Revenue Build_Empty'!D17*$A55*C$54/1000000)*(1+'Revenue Build_Empty'!D19))-(('Revenue Build_Empty'!D17*$A55*C$54/1000000)*'Revenue Build_Empty'!D28)-'Revenue Build_Empty'!D27-'Revenue Build_Empty'!D30)>0,((('Revenue Build_Empty'!D17*$A55*C$54/1000000)*(1+'Revenue Build_Empty'!D19))-(('Revenue Build_Empty'!D17*$A55*C$54/1000000)*'Revenue Build_Empty'!D28)-'Revenue Build_Empty'!D27-'Revenue Build_Empty'!D30)*(1-23.6%),((('Revenue Build_Empty'!D17*$A55*C$54/1000000)*(1+'Revenue Build_Empty'!D19))-(('Revenue Build_Empty'!D17*$A55*C$54/1000000)*'Revenue Build_Empty'!D28)-'Revenue Build_Empty'!D27-'Revenue Build_Empty'!D30)))/(1+$F$4)^1+(IF(((('Revenue Build_Empty'!E17*$A55*C$54/1000000)*(1+'Revenue Build_Empty'!E19))-(('Revenue Build_Empty'!E17*$A55*C$54/1000000)*'Revenue Build_Empty'!E28)-'Revenue Build_Empty'!E27-'Revenue Build_Empty'!E30)>0,((('Revenue Build_Empty'!E17*$A55*C$54/1000000)*(1+'Revenue Build_Empty'!E19))-(('Revenue Build_Empty'!E17*$A55*C$54/1000000)*'Revenue Build_Empty'!E28)-'Revenue Build_Empty'!E27-'Revenue Build_Empty'!E30)*(1-23.6%),((('Revenue Build_Empty'!E17*$A55*C$54/1000000)*(1+'Revenue Build_Empty'!E19))-(('Revenue Build_Empty'!E17*$A55*C$54/1000000)*'Revenue Build_Empty'!E28)-'Revenue Build_Empty'!E27-'Revenue Build_Empty'!E30)))/(1+$F$4)^2+(IF(((('Revenue Build_Empty'!F17*$A55*C$54/1000000)*(1+'Revenue Build_Empty'!F19))-(('Revenue Build_Empty'!F17*$A55*C$54/1000000)*'Revenue Build_Empty'!F28)-'Revenue Build_Empty'!F27-'Revenue Build_Empty'!F30)>0,((('Revenue Build_Empty'!F17*$A55*C$54/1000000)*(1+'Revenue Build_Empty'!F19))-(('Revenue Build_Empty'!F17*$A55*C$54/1000000)*'Revenue Build_Empty'!F28)-'Revenue Build_Empty'!F27-'Revenue Build_Empty'!F30)*(1-23.6%),((('Revenue Build_Empty'!F17*$A55*C$54/1000000)*(1+'Revenue Build_Empty'!F19))-(('Revenue Build_Empty'!F17*$A55*C$54/1000000)*'Revenue Build_Empty'!F28)-'Revenue Build_Empty'!F27-'Revenue Build_Empty'!F30)))/(1+$F$4)^3+(IF(((('Revenue Build_Empty'!G17*$A55*C$54/1000000)*(1+'Revenue Build_Empty'!G19))-(('Revenue Build_Empty'!G17*$A55*C$54/1000000)*'Revenue Build_Empty'!G28)-'Revenue Build_Empty'!G27-'Revenue Build_Empty'!G30)>0,((('Revenue Build_Empty'!G17*$A55*C$54/1000000)*(1+'Revenue Build_Empty'!G19))-(('Revenue Build_Empty'!G17*$A55*C$54/1000000)*'Revenue Build_Empty'!G28)-'Revenue Build_Empty'!G27-'Revenue Build_Empty'!G30)*(1-23.6%),((('Revenue Build_Empty'!G17*$A55*C$54/1000000)*(1+'Revenue Build_Empty'!G19))-(('Revenue Build_Empty'!G17*$A55*C$54/1000000)*'Revenue Build_Empty'!G28)-'Revenue Build_Empty'!G27-'Revenue Build_Empty'!G30)))/(1+$F$4)^4+(IF(((('Revenue Build_Empty'!H17*$A55*C$54/1000000)*(1+'Revenue Build_Empty'!H19))-(('Revenue Build_Empty'!H17*$A55*C$54/1000000)*'Revenue Build_Empty'!H28)-'Revenue Build_Empty'!H27-'Revenue Build_Empty'!H30)>0,((('Revenue Build_Empty'!H17*$A55*C$54/1000000)*(1+'Revenue Build_Empty'!H19))-(('Revenue Build_Empty'!H17*$A55*C$54/1000000)*'Revenue Build_Empty'!H28)-'Revenue Build_Empty'!H27-'Revenue Build_Empty'!H30)*(1-23.6%),((('Revenue Build_Empty'!H17*$A55*C$54/1000000)*(1+'Revenue Build_Empty'!H19))-(('Revenue Build_Empty'!H17*$A55*C$54/1000000)*'Revenue Build_Empty'!H28)-'Revenue Build_Empty'!H27-'Revenue Build_Empty'!H30)))/(1+$F$4)^5+(IF(((('Revenue Build_Empty'!I17*$A55*C$54/1000000)*(1+'Revenue Build_Empty'!I19))-(('Revenue Build_Empty'!I17*$A55*C$54/1000000)*'Revenue Build_Empty'!I28)-'Revenue Build_Empty'!I27-'Revenue Build_Empty'!I30)>0,((('Revenue Build_Empty'!I17*$A55*C$54/1000000)*(1+'Revenue Build_Empty'!I19))-(('Revenue Build_Empty'!I17*$A55*C$54/1000000)*'Revenue Build_Empty'!I28)-'Revenue Build_Empty'!I27-'Revenue Build_Empty'!I30)*(1-23.6%),((('Revenue Build_Empty'!I17*$A55*C$54/1000000)*(1+'Revenue Build_Empty'!I19))-(('Revenue Build_Empty'!I17*$A55*C$54/1000000)*'Revenue Build_Empty'!I28)-'Revenue Build_Empty'!I27-'Revenue Build_Empty'!I30)))/(1+$F$4)^6 -> -56.678836 | D55: =$B$17+(IF(((('Revenue Build_Empty'!D17*$A55*D$54/1000000)*(1+'Revenue Build_Empty'!D19))-(('Revenue Build_Empty'!D17*$A55*D$54/1000000)*'Revenue Build_Empty'!D28)-'Revenue Build_Empty'!D27-'Revenue Build_Empty'!D30)>0,((('Revenue Build_Empty'!D17*$A55*D$54/1000000)*(1+'Revenue Build_Empty'!D19))-(('Revenue Build_Empty'!D17*$A55*D$54/1000000)*'Revenue Build_Empty'!D28)-'Revenue Build_Empty'!D27-'Revenue Build_Empty'!D30)*(1-23.6%),((('Revenue Build_Empty'!D17*$A55*D$54/1000000)*(1+'Revenue Build_Empty'!D19))-(('Revenue Build_Empty'!D17*$A55*D$54/1000000)*'Revenue Build_Empty'!D28)-'Revenue Build_Empty'!D27-'Revenue Build_Empty'!D30)))/(1+$F$4)^1+(IF(((('Revenue Build_Empty'!E17*$A55*D$54/1000000)*(1+'Revenue Build_Empty'!E19))-(('Revenue Build_Empty'!E17*$A55*D$54/1000000)*'Revenue Build_Empty'!E28)-'Revenue Build_Empty'!E27-'Revenue Build_Empty'!E30)>0,((('Revenue Build_Empty'!E17*$A55*D$54/1000000)*(1+'Revenue Build_Empty'!E19))-(('Revenue Build_Empty'!E17*$A55*D$54/1000000)*'Revenue Build_Empty'!E28)-'Revenue Build_Empty'!E27-'Revenue Build_Empty'!E30)*(1-23.6%),((('Revenue Build_Empty'!E17*$A55*D$54/1000000)*(1+'Revenue Build_Empty'!E19))-(('Revenue Build_Empty'!E17*$A55*D$54/1000000)*'Revenue Build_Empty'!E28)-'Revenue Build_Empty'!E27-'Revenue Build_Empty'!E30)))/(1+$F$4)^2+(IF(((('Revenue Build_Empty'!F17*$A55*D$54/1000000)*(1+'Revenue Build_Empty'!F19))-(('Revenue Build_Empty'!F17*$A55*D$54/1000000)*'Revenue Build_Empty'!F28)-'Revenue Build_Empty'!F27-'Revenue Build_Empty'!F30)>0,((('Revenue Build_Empty'!F17*$A55*D$54/1000000)*(1+'Revenue Build_Empty'!F19))-(('Revenue Build_Empty'!F17*$A55*D$54/1000000)*'Revenue Build_Empty'!F28)-'Revenue Build_Empty'!F27-'Revenue Build_Empty'!F30)*(1-23.6%),((('Revenue Build_Empty'!F17*$A55*D$54/1000000)*(1+'Revenue Build_Empty'!F19))-(('Revenue Build_Empty'!F17*$A55*D$54/1000000)*'Revenue Build_Empty'!F28)-'Revenue Build_Empty'!F27-'Revenue Build_Empty'!F30)))/(1+$F$4)^3+(IF(((('Revenue Build_Empty'!G17*$A55*D$54/1000000)*(1+'Revenue Build_Empty'!G19))-(('Revenue Build_Empty'!G17*$A55*D$54/1000000)*'Revenue Build_Empty'!G28)-'Revenue Build_Empty'!G27-'Revenue Build_Empty'!G30)>0,((('Revenue Build_Empty'!G17*$A55*D$54/1000000)*(1+'Revenue Build_Empty'!G19))-(('Revenue Build_Empty'!G17*$A55*D$54/1000000)*'Revenue Build_Empty'!G28)-'Revenue Build_Empty'!G27-'Revenue Build_Empty'!G30)*(1-23.6%),((('Revenue Build_Empty'!G17*$A55*D$54/1000000)*(1+'Revenue Build_Empty'!G19))-(('Revenue Build_Empty'!G17*$A55*D$54/1000000)*'Revenue Build_Empty'!G28)-'Revenue Build_Empty'!G27-'Revenue Build_Empty'!G30)))/(1+$F$4)^4+(IF(((('Revenue Build_Empty'!H17*$A55*D$54/1000000)*(1+'Revenue Build_Empty'!H19))-(('Revenue Build_Empty'!H17*$A55*D$54/1000000)*'Revenue Build_Empty'!H28)-'Revenue Build_Empty'!H27-'Revenue Build_Empty'!H30)>0,((('Revenue Build_Empty'!H17*$A55*D$54/1000000)*(1+'Revenue Build_Empty'!H19))-(('Revenue Build_Empty'!H17*$A55*D$54/1000000)*'Revenue Build_Empty'!H28)-'Revenue Build_Empty'!H27-'Revenue Build_Empty'!H30)*(1-23.6%),((('Revenue Build_Empty'!H17*$A55*D$54/1000000)*(1+'Revenue Build_Empty'!H19))-(('Revenue Build_Empty'!H17*$A55*D$54/1000000)*'Revenue Build_Empty'!H28)-'Revenue Build_Empty'!H27-'Revenue Build_Empty'!H30)))/(1+$F$4)^5+(IF(((('Revenue Build_Empty'!I17*$A55*D$54/1000000)*(1+'Revenue Build_Empty'!I19))-(('Revenue Build_Empty'!I17*$A55*D$54/1000000)*'Revenue Build_Empty'!I28)-'Revenue Build_Empty'!I27-'Revenue Build_Empty'!I30)>0,((('Revenue Build_Empty'!I17*$A55*D$54/1000000)*(1+'Revenue Build_Empty'!I19))-(('Revenue Build_Empty'!I17*$A55*D$54/1000000)*'Revenue Build_Empty'!I28)-'Revenue Build_Empty'!I27-'Revenue Build_Empty'!I30)*(1-23.6%),((('Revenue Build_Empty'!I17*$A55*D$54/1000000)*(1+'Revenue Build_Empty'!I19))-(('Revenue Build_Empty'!I17*$A55*D$54/1000000)*'Revenue Build_Empty'!I28)-'Revenue Build_Empty'!I27-'Revenue Build_Empty'!I30)))/(1+$F$4)^6 -> -26.497491 | E55: =$B$17+(IF(((('Revenue Build_Empty'!D17*$A55*E$54/1000000)*(1+'Revenue Build_Empty'!D19))-(('Revenue Build_Empty'!D17*$A55*E$54/1000000)*'Revenue Build_Empty'!D28)-'Revenue Build_Empty'!D27-'Revenue Build_Empty'!D30)>0,((('Revenue Build_Empty'!D17*$A55*E$54/1000000)*(1+'Revenue Build_Empty'!D19))-(('Revenue Build_Empty'!D17*$A55*E$54/1000000)*'Revenue Build_Empty'!D28)-'Revenue Build_Empty'!D27-'Revenue Build_Empty'!D30)*(1-23.6%),((('Revenue Build_Empty'!D17*$A55*E$54/1000000)*(1+'Revenue Build_Empty'!D19))-(('Revenue Build_Empty'!D17*$A55*E$54/1000000)*'Revenue Build_Empty'!D28)-'Revenue Build_Empty'!D27-'Revenue Build_Empty'!D30)))/(1+$F$4)^1+(IF(((('Revenue Build_Empty'!E17*$A55*E$54/1000000)*(1+'Revenue Build_Empty'!E19))-(('Revenue Build_Empty'!E17*$A55*E$54/1000000)*'Revenue Build_Empty'!E28)-'Revenue Build_Empty'!E27-'Revenue Build_Empty'!E30)>0,((('Revenue Build_Empty'!E17*$A55*E$54/1000000)*(1+'Revenue Build_Empty'!E19))-(('Revenue Build_Empty'!E17*$A55*E$54/1000000)*'Revenue Build_Empty'!E28)-'Revenue Build_Empty'!E27-'Revenue Build_Empty'!E30)*(1-23.6%),((('Revenue Build_Empty'!E17*$A55*E$54/1000000)*(1+'Revenue Build_Empty'!E19))-(('Revenue Build_Empty'!E17*$A55*E$54/1000000)*'Revenue Build_Empty'!E28)-'Revenue Build_Empty'!E27-'Revenue Build_Empty'!E30)))/(1+$F$4)^2+(IF(((('Revenue Build_Empty'!F17*$A55*E$54/1000000)*(1+'Revenue Build_Empty'!F19))-(('Revenue Build_Empty'!F17*$A55*E$54/1000000)*'Revenue Build_Empty'!F28)-'Revenue Build_Empty'!F27-'Revenue Build_Empty'!F30)>0,((('Revenue Build_Empty'!F17*$A55*E$54/1000000)*(1+'Revenue Build_Empty'!F19))-(('Revenue Build_Empty'!F17*$A55*E$54/1000000)*'Revenue Build_Empty'!F28)-'Revenue Build_Empty'!F27-'Revenue Build_Empty'!F30)*(1-23.6%),((('Revenue Build_Empty'!F17*$A55*E$54/1000000)*(1+'Revenue Build_Empty'!F19))-(('Revenue Build_Empty'!F17*$A55*E$54/1000000)*'Revenue Build_Empty'!F28)-'Revenue Build_Empty'!F27-'Revenue Build_Empty'!F30)))/(1+$F$4)^3+(IF(((('Revenue Build_Empty'!G17*$A55*E$54/1000000)*(1+'Revenue Build_Empty'!G19))-(('Revenue Build_Empty'!G17*$A55*E$54/1000000)*'Revenue Build_Empty'!G28)-'Revenue Build_Empty'!G27-'Revenue Build_Empty'!G30)>0,((('Revenue Build_Empty'!G17*$A55*E$54/1000000)*(1+'Revenue Build_Empty'!G19))-(('Revenue Build_Empty'!G17*$A55*E$54/1000000)*'Revenue Build_Empty'!G28)-'Revenue Build_Empty'!G27-'Revenue Build_Empty'!G30)*(1-23.6%),((('Revenue Build_Empty'!G17*$A55*E$54/1000000)*(1+'Revenue Build_Empty'!G19))-(('Revenue Build_Empty'!G17*$A55*E$54/1000000)*'Revenue Build_Empty'!G28)-'Revenue Build_Empty'!G27-'Revenue Build_Empty'!G30)))/(1+$F$4)^4+(IF(((('Revenue Build_Empty'!H17*$A55*E$54/1000000)*(1+'Revenue Build_Empty'!H19))-(('Revenue Build_Empty'!H17*$A55*E$54/1000000)*'Revenue Build_Empty'!H28)-'Revenue Build_Empty'!H27-'Revenue Build_Empty'!H30)>0,((('Revenue Build_Empty'!H17*$A55*E$54/1000000)*(1+'Revenue Build_Empty'!H19))-(('Revenue Build_Empty'!H17*$A55*E$54/1000000)*'Revenue Build_Empty'!H28)-'Revenue Build_Empty'!H27-'Revenue Build_Empty'!H30)*(1-23.6%),((('Revenue Build_Empty'!H17*$A55*E$54/1000000)*(1+'Revenue Build_Empty'!H19))-(('Revenue Build_Empty'!H17*$A55*E$54/1000000)*'Revenue Build_Empty'!H28)-'Revenue Build_Empty'!H27-'Revenue Build_Empty'!H30)))/(1+$F$4)^5+(IF(((('Revenue Build_Empty'!I17*$A55*E$54/1000000)*(1+'Revenue Build_Empty'!I19))-(('Revenue Build_Empty'!I17*$A55*E$54/1000000)*'Revenue Build_Empty'!I28)-'Revenue Build_Empty'!I27-'Revenue Build_Empty'!I30)>0,((('Revenue Build_Empty'!I17*$A55*E$54/1000000)*(1+'Revenue Build_Empty'!I19))-(('Revenue Build_Empty'!I17*$A55*E$54/1000000)*'Revenue Build_Empty'!I28)-'Revenue Build_Empty'!I27-'Revenue Build_Empty'!I30)*(1-23.6%),((('Revenue Build_Empty'!I17*$A55*E$54/1000000)*(1+'Revenue Build_Empty'!I19))-(('Revenue Build_Empty'!I17*$A55*E$54/1000000)*'Revenue Build_Empty'!I28)-'Revenue Build_Empty'!I27-'Revenue Build_Empty'!I30)))/(1+$F$4)^6 -> 2.6849562 | F55: =$B$17+(IF(((('Revenue Build_Empty'!D17*$A55*F$54/1000000)*(1+'Revenue Build_Empty'!D19))-(('Revenue Build_Empty'!D17*$A55*F$54/1000000)*'Revenue Build_Empty'!D28)-'Revenue Build_Empty'!D27-'Revenue Build_Empty'!D30)>0,((('Revenue Build_Empty'!D17*$A55*F$54/1000000)*(1+'Revenue Build_Empty'!D19))-(('Revenue Build_Empty'!D17*$A55*F$54/1000000)*'Revenue Build_Empty'!D28)-'Revenue Build_Empty'!D27-'Revenue Build_Empty'!D30)*(1-23.6%),((('Revenue Build_Empty'!D17*$A55*F$54/1000000)*(1+'Revenue Build_Empty'!D19))-(('Revenue Build_Empty'!D17*$A55*F$54/1000000)*'Revenue Build_Empty'!D28)-'Revenue Build_Empty'!D27-'Revenue Build_Empty'!D30)))/(1+$F$4)^1+(IF(((('Revenue Build_Empty'!E17*$A55*F$54/1000000)*(1+'Revenue Build_Empty'!E19))-(('Revenue Build_Empty'!E17*$A55*F$54/1000000)*'Revenue Build_Empty'!E28)-'Revenue Build_Empty'!E27-'Revenue Build_Empty'!E30)>0,((('Revenue Build_Empty'!E17*$A55*F$54/1000000)*(1+'Revenue Build_Empty'!E19))-(('Revenue Build_Empty'!E17*$A55*F$54/1000000)*'Revenue Build_Empty'!E28)-'Revenue Build_Empty'!E27-'Revenue Build_Empty'!E30)*(1-23.6%),((('Revenue Build_Empty'!E17*$A55*F$54/1000000)*(1+'Revenue Build_Empty'!E19))-(('Revenue Build_Empty'!E17*$A55*F$54/1000000)*'Revenue Build_Empty'!E28)-'Revenue Build_Empty'!E27-'Revenue Build_Empty'!E30)))/(1+$F$4)^2+(IF(((('Revenue Build_Empty'!F17*$A55*F$54/1000000)*(1+'Revenue Build_Empty'!F19))-(('Revenue Build_Empty'!F17*$A55*F$54/1000000)*'Revenue Build_Empty'!F28)-'Revenue Build_Empty'!F27-'Revenue Build_Empty'!F30)>0,((('Revenue Build_Empty'!F17*$A55*F$54/1000000)*(1+'Revenue Build_Empty'!F19))-(('Revenue Build_Empty'!F17*$A55*F$54/1000000)*'Revenue Build_Empty'!F28)-'Revenue Build_Empty'!F27-'Revenue Build_Empty'!F30)*(1-23.6%),((('Revenue Build_Empty'!F17*$A55*F$54/1000000)*(1+'Revenue Build_Empty'!F19))-(('Revenue Build_Empty'!F17*$A55*F$54/1000000)*'Revenue Build_Empty'!F28)-'Revenue Build_Empty'!F27-'Revenue Build_Empty'!F30)))/(1+$F$4)^3+(IF(((('Revenue Build_Empty'!G17*$A55*F$54/1000000)*(1+'Revenue Build_Empty'!G19))-(('Revenue Build_Empty'!G17*$A55*F$54/1000000)*'Revenue Build_Empty'!G28)-'Revenue Build_Empty'!G27-'Revenue Build_Empty'!G30)>0,((('Revenue Build_Empty'!G17*$A55*F$54/1000000)*(1+'Revenue Build_Empty'!G19))-(('Revenue Build_Empty'!G17*$A55*F$54/1000000)*'Revenue Build_Empty'!G28)-'Revenue Build_Empty'!G27-'Revenue Build_Empty'!G30)*(1-23.6%),((('Revenue Build_Empty'!G17*$A55*F$54/1000000)*(1+'Revenue Build_Empty'!G19))-(('Revenue Build_Empty'!G17*$A55*F$54/1000000)*'Revenue Build_Empty'!G28)-'Revenue Build_Empty'!G27-'Revenue Build_Empty'!G30)))/(1+$F$4)^4+(IF(((('Revenue Build_Empty'!H17*$A55*F$54/1000000)*(1+'Revenue Build_Empty'!H19))-(('Revenue Build_Empty'!H17*$A55*F$54/1000000)*'Revenue Build_Empty'!H28)-'Revenue Build_Empty'!H27-'Revenue Build_Empty'!H30)>0,((('Revenue Build_Empty'!H17*$A55*F$54/1000000)*(1+'Revenue Build_Empty'!H19))-(('Revenue Build_Empty'!H17*$A55*F$54/1000000)*'Revenue Build_Empty'!H28)-'Revenue Build_Empty'!H27-'Revenue Build_Empty'!H30)*(1-23.6%),((('Revenue Build_Empty'!H17*$A55*F$54/1000000)*(1+'Revenue Build_Empty'!H19))-(('Revenue Build_Empty'!H17*$A55*F$54/1000000)*'Revenue Build_Empty'!H28)-'Revenue Build_Empty'!H27-'Revenue Build_Empty'!H30)))/(1+$F$4)^5+(IF(((('Revenue Build_Empty'!I17*$A55*F$54/1000000)*(1+'Revenue Build_Empty'!I19))-(('Revenue Build_Empty'!I17*$A55*F$54/1000000)*'Revenue Build_Empty'!I28)-'Revenue Build_Empty'!I27-'Revenue Build_Empty'!I30)>0,((('Revenue Build_Empty'!I17*$A55*F$54/1000000)*(1+'Revenue Build_Empty'!I19))-(('Revenue Build_Empty'!I17*$A55*F$54/1000000)*'Revenue Build_Empty'!I28)-'Revenue Build_Empty'!I27-'Revenue Build_Empty'!I30)*(1-23.6%),((('Revenue Build_Empty'!I17*$A55*F$54/1000000)*(1+'Revenue Build_Empty'!I19))-(('Revenue Build_Empty'!I17*$A55*F$54/1000000)*'Revenue Build_Empty'!I28)-'Revenue Build_Empty'!I27-'Revenue Build_Empty'!I30)))/(1+$F$4)^6 -> 30.87415
A56: 0.85 | B56: =$B$17+(IF(((('Revenue Build_Empty'!D17*$A56*B$54/1000000)*(1+'Revenue Build_Empty'!D19))-(('Revenue Build_Empty'!D17*$A56*B$54/1000000)*'Revenue Build_Empty'!D28)-'Revenue Build_Empty'!D27-'Revenue Build_Empty'!D30)>0,((('Revenue Build_Empty'!D17*$A56*B$54/1000000)*(1+'Revenue Build_Empty'!D19))-(('Revenue Build_Empty'!D17*$A56*B$54/1000000)*'Revenue Build_Empty'!D28)-'Revenue Build_Empty'!D27-'Revenue Build_Empty'!D30)*(1-23.6%),((('Revenue Build_Empty'!D17*$A56*B$54/1000000)*(1+'Revenue Build_Empty'!D19))-(('Revenue Build_Empty'!D17*$A56*B$54/1000000)*'Revenue Build_Empty'!D28)-'Revenue Build_Empty'!D27-'Revenue Build_Empty'!D30)))/(1+$F$4)^1+(IF(((('Revenue Build_Empty'!E17*$A56*B$54/1000000)*(1+'Revenue Build_Empty'!E19))-(('Revenue Build_Empty'!E17*$A56*B$54/1000000)*'Revenue Build_Empty'!E28)-'Revenue Build_Empty'!E27-'Revenue Build_Empty'!E30)>0,((('Revenue Build_Empty'!E17*$A56*B$54/1000000)*(1+'Revenue Build_Empty'!E19))-(('Revenue Build_Empty'!E17*$A56*B$54/1000000)*'Revenue Build_Empty'!E28)-'Revenue Build_Empty'!E27-'Revenue Build_Empty'!E30)*(1-23.6%),((('Revenue Build_Empty'!E17*$A56*B$54/1000000)*(1+'Revenue Build_Empty'!E19))-(('Revenue Build_Empty'!E17*$A56*B$54/1000000)*'Revenue Build_Empty'!E28)-'Revenue Build_Empty'!E27-'Revenue Build_Empty'!E30)))/(1+$F$4)^2+(IF(((('Revenue Build_Empty'!F17*$A56*B$54/1000000)*(1+'Revenue Build_Empty'!F19))-(('Revenue Build_Empty'!F17*$A56*B$54/1000000)*'Revenue Build_Empty'!F28)-'Revenue Build_Empty'!F27-'Revenue Build_Empty'!F30)>0,((('Revenue Build_Empty'!F17*$A56*B$54/1000000)*(1+'Revenue Build_Empty'!F19))-(('Revenue Build_Empty'!F17*$A56*B$54/1000000)*'Revenue Build_Empty'!F28)-'Revenue Build_Empty'!F27-'Revenue Build_Empty'!F30)*(1-23.6%),((('Revenue Build_Empty'!F17*$A56*B$54/1000000)*(1+'Revenue Build_Empty'!F19))-(('Revenue Build_Empty'!F17*$A56*B$54/1000000)*'Revenue Build_Empty'!F28)-'Revenue Build_Empty'!F27-'Revenue Build_Empty'!F30)))/(1+$F$4)^3+(IF(((('Revenue Build_Empty'!G17*$A56*B$54/1000000)*(1+'Revenue Build_Empty'!G19))-(('Revenue Build_Empty'!G17*$A56*B$54/1000000)*'Revenue Build_Empty'!G28)-'Revenue Build_Empty'!G27-'Revenue Build_Empty'!G30)>0,((('Revenue Build_Empty'!G17*$A56*B$54/1000000)*(1+'Revenue Build_Empty'!G19))-(('Revenue Build_Empty'!G17*$A56*B$54/1000000)*'Revenue Build_Empty'!G28)-'Revenue Build_Empty'!G27-'Revenue Build_Empty'!G30)*(1-23.6%),((('Revenue Build_Empty'!G17*$A56*B$54/1000000)*(1+'Revenue Build_Empty'!G19))-(('Revenue Build_Empty'!G17*$A56*B$54/1000000)*'Revenue Build_Empty'!G28)-'Revenue Build_Empty'!G27-'Revenue Build_Empty'!G30)))/(1+$F$4)^4+(IF(((('Revenue Build_Empty'!H17*$A56*B$54/1000000)*(1+'Revenue Build_Empty'!H19))-(('Revenue Build_Empty'!H17*$A56*B$54/1000000)*'Revenue Build_Empty'!H28)-'Revenue Build_Empty'!H27-'Revenue Build_Empty'!H30)>0,((('Revenue Build_Empty'!H17*$A56*B$54/1000000)*(1+'Revenue Build_Empty'!H19))-(('Revenue Build_Empty'!H17*$A56*B$54/1000000)*'Revenue Build_Empty'!H28)-'Revenue Build_Empty'!H27-'Revenue Build_Empty'!H30)*(1-23.6%),((('Revenue Build_Empty'!H17*$A56*B$54/1000000)*(1+'Revenue Build_Empty'!H19))-(('Revenue Build_Empty'!H17*$A56*B$54/1000000)*'Revenue Build_Empty'!H28)-'Revenue Build_Empty'!H27-'Revenue Build_Empty'!H30)))/(1+$F$4)^5+(IF(((('Revenue Build_Empty'!I17*$A56*B$54/1000000)*(1+'Revenue Build_Empty'!I19))-(('Revenue Build_Empty'!I17*$A56*B$54/1000000)*'Revenue Build_Empty'!I28)-'Revenue Build_Empty'!I27-'Revenue Build_Empty'!I30)>0,((('Revenue Build_Empty'!I17*$A56*B$54/1000000)*(1+'Revenue Build_Empty'!I19))-(('Revenue Build_Empty'!I17*$A56*B$54/1000000)*'Revenue Build_Empty'!I28)-'Revenue Build_Empty'!I27-'Revenue Build_Empty'!I30)*(1-23.6%),((('Revenue Build_Empty'!I17*$A56*B$54/1000000)*(1+'Revenue Build_Empty'!I19))-(('Revenue Build_Empty'!I17*$A56*B$54/1000000)*'Revenue Build_Empty'!I28)-'Revenue Build_Empty'!I27-'Revenue Build_Empty'!I30)))/(1+$F$4)^6 -> -79.829386 | C56: =$B$17+(IF(((('Revenue Build_Empty'!D17*$A56*C$54/1000000)*(1+'Revenue Build_Empty'!D19))-(('Revenue Build_Empty'!D17*$A56*C$54/1000000)*'Revenue Build_Empty'!D28)-'Revenue Build_Empty'!D27-'Revenue Build_Empty'!D30)>0,((('Revenue Build_Empty'!D17*$A56*C$54/1000000)*(1+'Revenue Build_Empty'!D19))-(('Revenue Build_Empty'!D17*$A56*C$54/1000000)*'Revenue Build_Empty'!D28)-'Revenue Build_Empty'!D27-'Revenue Build_Empty'!D30)*(1-23.6%),((('Revenue Build_Empty'!D17*$A56*C$54/1000000)*(1+'Revenue Build_Empty'!D19))-(('Revenue Build_Empty'!D17*$A56*C$54/1000000)*'Revenue Build_Empty'!D28)-'Revenue Build_Empty'!D27-'Revenue Build_Empty'!D30)))/(1+$F$4)^1+(IF(((('Revenue Build_Empty'!E17*$A56*C$54/1000000)*(1+'Revenue Build_Empty'!E19))-(('Revenue Build_Empty'!E17*$A56*C$54/1000000)*'Revenue Build_Empty'!E28)-'Revenue Build_Empty'!E27-'Revenue Build_Empty'!E30)>0,((('Revenue Build_Empty'!E17*$A56*C$54/1000000)*(1+'Revenue Build_Empty'!E19))-(('Revenue Build_Empty'!E17*$A56*C$54/1000000)*'Revenue Build_Empty'!E28)-'Revenue Build_Empty'!E27-'Revenue Build_Empty'!E30)*(1-23.6%),((('Revenue Build_Empty'!E17*$A56*C$54/1000000)*(1+'Revenue Build_Empty'!E19))-(('Revenue Build_Empty'!E17*$A56*C$54/1000000)*'Revenue Build_Empty'!E28)-'Revenue Build_Empty'!E27-'Revenue Build_Empty'!E30)))/(1+$F$4)^2+(IF(((('Revenue Build_Empty'!F17*$A56*C$54/1000000)*(1+'Revenue Build_Empty'!F19))-(('Revenue Build_Empty'!F17*$A56*C$54/1000000)*'Revenue Build_Empty'!F28)-'Revenue Build_Empty'!F27-'Revenue Build_Empty'!F30)>0,((('Revenue Build_Empty'!F17*$A56*C$54/1000000)*(1+'Revenue Build_Empty'!F19))-(('Revenue Build_Empty'!F17*$A56*C$54/1000000)*'Revenue Build_Empty'!F28)-'Revenue Build_Empty'!F27-'Revenue Build_Empty'!F30)*(1-23.6%),((('Revenue Build_Empty'!F17*$A56*C$54/1000000)*(1+'Revenue Build_Empty'!F19))-(('Revenue Build_Empty'!F17*$A56*C$54/1000000)*'Revenue Build_Empty'!F28)-'Revenue Build_Empty'!F27-'Revenue Build_Empty'!F30)))/(1+$F$4)^3+(IF(((('Revenue Build_Empty'!G17*$A56*C$54/1000000)*(1+'Revenue Build_Empty'!G19))-(('Revenue Build_Empty'!G17*$A56*C$54/1000000)*'Revenue Build_Empty'!G28)-'Revenue Build_Empty'!G27-'Revenue Build_Empty'!G30)>0,((('Revenue Build_Empty'!G17*$A56*C$54/1000000)*(1+'Revenue Build_Empty'!G19))-(('Revenue Build_Empty'!G17*$A56*C$54/1000000)*'Revenue Build_Empty'!G28)-'Revenue Build_Empty'!G27-'Revenue Build_Empty'!G30)*(1-23.6%),((('Revenue Build_Empty'!G17*$A56*C$54/1000000)*(1+'Revenue Build_Empty'!G19))-(('Revenue Build_Empty'!G17*$A56*C$54/1000000)*'Revenue Build_Empty'!G28)-'Revenue Build_Empty'!G27-'Revenue Build_Empty'!G30)))/(1+$F$4)^4+(IF(((('Revenue Build_Empty'!H17*$A56*C$54/1000000)*(1+'Revenue Build_Empty'!H19))-(('Revenue Build_Empty'!H17*$A56*C$54/1000000)*'Revenue Build_Empty'!H28)-'Revenue Build_Empty'!H27-'Revenue Build_Empty'!H30)>0,((('Revenue Build_Empty'!H17*$A56*C$54/1000000)*(1+'Revenue Build_Empty'!H19))-(('Revenue Build_Empty'!H17*$A56*C$54/1000000)*'Revenue Build_Empty'!H28)-'Revenue Build_Empty'!H27-'Revenue Build_Empty'!H30)*(1-23.6%),((('Revenue Build_Empty'!H17*$A56*C$54/1000000)*(1+'Revenue Build_Empty'!H19))-(('Revenue Build_Empty'!H17*$A56*C$54/1000000)*'Revenue Build_Empty'!H28)-'Revenue Build_Empty'!H27-'Revenue Build_Empty'!H30)))/(1+$F$4)^5+(IF(((('Revenue Build_Empty'!I17*$A56*C$54/1000000)*(1+'Revenue Build_Empty'!I19))-(('Revenue Build_Empty'!I17*$A56*C$54/1000000)*'Revenue Build_Empty'!I28)-'Revenue Build_Empty'!I27-'Revenue Build_Empty'!I30)>0,((('Revenue Build_Empty'!I17*$A56*C$54/1000000)*(1+'Revenue Build_Empty'!I19))-(('Revenue Build_Empty'!I17*$A56*C$54/1000000)*'Revenue Build_Empty'!I28)-'Revenue Build_Empty'!I27-'Revenue Build_Empty'!I30)*(1-23.6%),((('Revenue Build_Empty'!I17*$A56*C$54/1000000)*(1+'Revenue Build_Empty'!I19))-(('Revenue Build_Empty'!I17*$A56*C$54/1000000)*'Revenue Build_Empty'!I28)-'Revenue Build_Empty'!I27-'Revenue Build_Empty'!I30)))/(1+$F$4)^6 -> -41.300408 | D56: =$B$17+(IF(((('Revenue Build_Empty'!D17*$A56*D$54/1000000)*(1+'Revenue Build_Empty'!D19))-(('Revenue Build_Empty'!D17*$A56*D$54/1000000)*'Revenue Build_Empty'!D28)-'Revenue Build_Empty'!D27-'Revenue Build_Empty'!D30)>0,((('Revenue Build_Empty'!D17*$A56*D$54/1000000)*(1+'Revenue Build_Empty'!D19))-(('Revenue Build_Empty'!D17*$A56*D$54/1000000)*'Revenue Build_Empty'!D28)-'Revenue Build_Empty'!D27-'Revenue Build_Empty'!D30)*(1-23.6%),((('Revenue Build_Empty'!D17*$A56*D$54/1000000)*(1+'Revenue Build_Empty'!D19))-(('Revenue Build_Empty'!D17*$A56*D$54/1000000)*'Revenue Build_Empty'!D28)-'Revenue Build_Empty'!D27-'Revenue Build_Empty'!D30)))/(1+$F$4)^1+(IF(((('Revenue Build_Empty'!E17*$A56*D$54/1000000)*(1+'Revenue Build_Empty'!E19))-(('Revenue Build_Empty'!E17*$A56*D$54/1000000)*'Revenue Build_Empty'!E28)-'Revenue Build_Empty'!E27-'Revenue Build_Empty'!E30)>0,((('Revenue Build_Empty'!E17*$A56*D$54/1000000)*(1+'Revenue Build_Empty'!E19))-(('Revenue Build_Empty'!E17*$A56*D$54/1000000)*'Revenue Build_Empty'!E28)-'Revenue Build_Empty'!E27-'Revenue Build_Empty'!E30)*(1-23.6%),((('Revenue Build_Empty'!E17*$A56*D$54/1000000)*(1+'Revenue Build_Empty'!E19))-(('Revenue Build_Empty'!E17*$A56*D$54/1000000)*'Revenue Build_Empty'!E28)-'Revenue Build_Empty'!E27-'Revenue Build_Empty'!E30)))/(1+$F$4)^2+(IF(((('Revenue Build_Empty'!F17*$A56*D$54/1000000)*(1+'Revenue Build_Empty'!F19))-(('Revenue Build_Empty'!F17*$A56*D$54/1000000)*'Revenue Build_Empty'!F28)-'Revenue Build_Empty'!F27-'Revenue Build_Empty'!F30)>0,((('Revenue Build_Empty'!F17*$A56*D$54/1000000)*(1+'Revenue Build_Empty'!F19))-(('Revenue Build_Empty'!F17*$A56*D$54/1000000)*'Revenue Build_Empty'!F28)-'Revenue Build_Empty'!F27-'Revenue Build_Empty'!F30)*(1-23.6%),((('Revenue Build_Empty'!F17*$A56*D$54/1000000)*(1+'Revenue Build_Empty'!F19))-(('Revenue Build_Empty'!F17*$A56*D$54/1000000)*'Revenue Build_Empty'!F28)-'Revenue Build_Empty'!F27-'Revenue Build_Empty'!F30)))/(1+$F$4)^3+(IF(((('Revenue Build_Empty'!G17*$A56*D$54/1000000)*(1+'Revenue Build_Empty'!G19))-(('Revenue Build_Empty'!G17*$A56*D$54/1000000)*'Revenue Build_Empty'!G28)-'Revenue Build_Empty'!G27-'Revenue Build_Empty'!G30)>0,((('Revenue Build_Empty'!G17*$A56*D$54/1000000)*(1+'Revenue Build_Empty'!G19))-(('Revenue Build_Empty'!G17*$A56*D$54/1000000)*'Revenue Build_Empty'!G28)-'Revenue Build_Empty'!G27-'Revenue Build_Empty'!G30)*(1-23.6%),((('Revenue Build_Empty'!G17*$A56*D$54/1000000)*(1+'Revenue Build_Empty'!G19))-(('Revenue Build_Empty'!G17*$A56*D$54/1000000)*'Revenue Build_Empty'!G28)-'Revenue Build_Empty'!G27-'Revenue Build_Empty'!G30)))/(1+$F$4)^4+(IF(((('Revenue Build_Empty'!H17*$A56*D$54/1000000)*(1+'Revenue Build_Empty'!H19))-(('Revenue Build_Empty'!H17*$A56*D$54/1000000)*'Revenue Build_Empty'!H28)-'Revenue Build_Empty'!H27-'Revenue Build_Empty'!H30)>0,((('Revenue Build_Empty'!H17*$A56*D$54/1000000)*(1+'Revenue Build_Empty'!H19))-(('Revenue Build_Empty'!H17*$A56*D$54/1000000)*'Revenue Build_Empty'!H28)-'Revenue Build_Empty'!H27-'Revenue Build_Empty'!H30)*(1-23.6%),((('Revenue Build_Empty'!H17*$A56*D$54/1000000)*(1+'Revenue Build_Empty'!H19))-(('Revenue Build_Empty'!H17*$A56*D$54/1000000)*'Revenue Build_Empty'!H28)-'Revenue Build_Empty'!H27-'Revenue Build_Empty'!H30)))/(1+$F$4)^5+(IF(((('Revenue Build_Empty'!I17*$A56*D$54/1000000)*(1+'Revenue Build_Empty'!I19))-(('Revenue Build_Empty'!I17*$A56*D$54/1000000)*'Revenue Build_Empty'!I28)-'Revenue Build_Empty'!I27-'Revenue Build_Empty'!I30)>0,((('Revenue Build_Empty'!I17*$A56*D$54/1000000)*(1+'Revenue Build_Empty'!I19))-(('Revenue Build_Empty'!I17*$A56*D$54/1000000)*'Revenue Build_Empty'!I28)-'Revenue Build_Empty'!I27-'Revenue Build_Empty'!I30)*(1-23.6%),((('Revenue Build_Empty'!I17*$A56*D$54/1000000)*(1+'Revenue Build_Empty'!I19))-(('Revenue Build_Empty'!I17*$A56*D$54/1000000)*'Revenue Build_Empty'!I28)-'Revenue Build_Empty'!I27-'Revenue Build_Empty'!I30)))/(1+$F$4)^6 -> -5.6528858 | E56: =$B$17+(IF(((('Revenue Build_Empty'!D17*$A56*E$54/1000000)*(1+'Revenue Build_Empty'!D19))-(('Revenue Build_Empty'!D17*$A56*E$54/1000000)*'Revenue Build_Empty'!D28)-'Revenue Build_Empty'!D27-'Revenue Build_Empty'!D30)>0,((('Revenue Build_Empty'!D17*$A56*E$54/1000000)*(1+'Revenue Build_Empty'!D19))-(('Revenue Build_Empty'!D17*$A56*E$54/1000000)*'Revenue Build_Empty'!D28)-'Revenue Build_Empty'!D27-'Revenue Build_Empty'!D30)*(1-23.6%),((('Revenue Build_Empty'!D17*$A56*E$54/1000000)*(1+'Revenue Build_Empty'!D19))-(('Revenue Build_Empty'!D17*$A56*E$54/1000000)*'Revenue Build_Empty'!D28)-'Revenue Build_Empty'!D27-'Revenue Build_Empty'!D30)))/(1+$F$4)^1+(IF(((('Revenue Build_Empty'!E17*$A56*E$54/1000000)*(1+'Revenue Build_Empty'!E19))-(('Revenue Build_Empty'!E17*$A56*E$54/1000000)*'Revenue Build_Empty'!E28)-'Revenue Build_Empty'!E27-'Revenue Build_Empty'!E30)>0,((('Revenue Build_Empty'!E17*$A56*E$54/1000000)*(1+'Revenue Build_Empty'!E19))-(('Revenue Build_Empty'!E17*$A56*E$54/1000000)*'Revenue Build_Empty'!E28)-'Revenue Build_Empty'!E27-'Revenue Build_Empty'!E30)*(1-23.6%),((('Revenue Build_Empty'!E17*$A56*E$54/1000000)*(1+'Revenue Build_Empty'!E19))-(('Revenue Build_Empty'!E17*$A56*E$54/1000000)*'Revenue Build_Empty'!E28)-'Revenue Build_Empty'!E27-'Revenue Build_Empty'!E30)))/(1+$F$4)^2+(IF(((('Revenue Build_Empty'!F17*$A56*E$54/1000000)*(1+'Revenue Build_Empty'!F19))-(('Revenue Build_Empty'!F17*$A56*E$54/1000000)*'Revenue Build_Empty'!F28)-'Revenue Build_Empty'!F27-'Revenue Build_Empty'!F30)>0,((('Revenue Build_Empty'!F17*$A56*E$54/1000000)*(1+'Revenue Build_Empty'!F19))-(('Revenue Build_Empty'!F17*$A56*E$54/1000000)*'Revenue Build_Empty'!F28)-'Revenue Build_Empty'!F27-'Revenue Build_Empty'!F30)*(1-23.6%),((('Revenue Build_Empty'!F17*$A56*E$54/1000000)*(1+'Revenue Build_Empty'!F19))-(('Revenue Build_Empty'!F17*$A56*E$54/1000000)*'Revenue Build_Empty'!F28)-'Revenue Build_Empty'!F27-'Revenue Build_Empty'!F30)))/(1+$F$4)^3+(IF(((('Revenue Build_Empty'!G17*$A56*E$54/1000000)*(1+'Revenue Build_Empty'!G19))-(('Revenue Build_Empty'!G17*$A56*E$54/1000000)*'Revenue Build_Empty'!G28)-'Revenue Build_Empty'!G27-'Revenue Build_Empty'!G30)>0,((('Revenue Build_Empty'!G17*$A56*E$54/1000000)*(1+'Revenue Build_Empty'!G19))-(('Revenue Build_Empty'!G17*$A56*E$54/1000000)*'Revenue Build_Empty'!G28)-'Revenue Build_Empty'!G27-'Revenue Build_Empty'!G30)*(1-23.6%),((('Revenue Build_Empty'!G17*$A56*E$54/1000000)*(1+'Revenue Build_Empty'!G19))-(('Revenue Build_Empty'!G17*$A56*E$54/1000000)*'Revenue Build_Empty'!G28)-'Revenue Build_Empty'!G27-'Revenue Build_Empty'!G30)))/(1+$F$4)^4+(IF(((('Revenue Build_Empty'!H17*$A56*E$54/1000000)*(1+'Revenue Build_Empty'!H19))-(('Revenue Build_Empty'!H17*$A56*E$54/1000000)*'Revenue Build_Empty'!H28)-'Revenue Build_Empty'!H27-'Revenue Build_Empty'!H30)>0,((('Revenue Build_Empty'!H17*$A56*E$54/1000000)*(1+'Revenue Build_Empty'!H19))-(('Revenue Build_Empty'!H17*$A56*E$54/1000000)*'Revenue Build_Empty'!H28)-'Revenue Build_Empty'!H27-'Revenue Build_Empty'!H30)*(1-23.6%),((('Revenue Build_Empty'!H17*$A56*E$54/1000000)*(1+'Revenue Build_Empty'!H19))-(('Revenue Build_Empty'!H17*$A56*E$54/1000000)*'Revenue Build_Empty'!H28)-'Revenue Build_Empty'!H27-'Revenue Build_Empty'!H30)))/(1+$F$4)^5+(IF(((('Revenue Build_Empty'!I17*$A56*E$54/1000000)*(1+'Revenue Build_Empty'!I19))-(('Revenue Build_Empty'!I17*$A56*E$54/1000000)*'Revenue Build_Empty'!I28)-'Revenue Build_Empty'!I27-'Revenue Build_Empty'!I30)>0,((('Revenue Build_Empty'!I17*$A56*E$54/1000000)*(1+'Revenue Build_Empty'!I19))-(('Revenue Build_Empty'!I17*$A56*E$54/1000000)*'Revenue Build_Empty'!I28)-'Revenue Build_Empty'!I27-'Revenue Build_Empty'!I30)*(1-23.6%),((('Revenue Build_Empty'!I17*$A56*E$54/1000000)*(1+'Revenue Build_Empty'!I19))-(('Revenue Build_Empty'!I17*$A56*E$54/1000000)*'Revenue Build_Empty'!I28)-'Revenue Build_Empty'!I27-'Revenue Build_Empty'!I30)))/(1+$F$4)^6 -> 28.867118 | F56: =$B$17+(IF(((('Revenue Build_Empty'!D17*$A56*F$54/1000000)*(1+'Revenue Build_Empty'!D19))-(('Revenue Build_Empty'!D17*$A56*F$54/1000000)*'Revenue Build_Empty'!D28)-'Revenue Build_Empty'!D27-'Revenue Build_Empty'!D30)>0,((('Revenue Build_Empty'!D17*$A56*F$54/1000000)*(1+'Revenue Build_Empty'!D19))-(('Revenue Build_Empty'!D17*$A56*F$54/1000000)*'Revenue Build_Empty'!D28)-'Revenue Build_Empty'!D27-'Revenue Build_Empty'!D30)*(1-23.6%),((('Revenue Build_Empty'!D17*$A56*F$54/1000000)*(1+'Revenue Build_Empty'!D19))-(('Revenue Build_Empty'!D17*$A56*F$54/1000000)*'Revenue Build_Empty'!D28)-'Revenue Build_Empty'!D27-'Revenue Build_Empty'!D30)))/(1+$F$4)^1+(IF(((('Revenue Build_Empty'!E17*$A56*F$54/1000000)*(1+'Revenue Build_Empty'!E19))-(('Revenue Build_Empty'!E17*$A56*F$54/1000000)*'Revenue Build_Empty'!E28)-'Revenue Build_Empty'!E27-'Revenue Build_Empty'!E30)>0,((('Revenue Build_Empty'!E17*$A56*F$54/1000000)*(1+'Revenue Build_Empty'!E19))-(('Revenue Build_Empty'!E17*$A56*F$54/1000000)*'Revenue Build_Empty'!E28)-'Revenue Build_Empty'!E27-'Revenue Build_Empty'!E30)*(1-23.6%),((('Revenue Build_Empty'!E17*$A56*F$54/1000000)*(1+'Revenue Build_Empty'!E19))-(('Revenue Build_Empty'!E17*$A56*F$54/1000000)*'Revenue Build_Empty'!E28)-'Revenue Build_Empty'!E27-'Revenue Build_Empty'!E30)))/(1+$F$4)^2+(IF(((('Revenue Build_Empty'!F17*$A56*F$54/1000000)*(1+'Revenue Build_Empty'!F19))-(('Revenue Build_Empty'!F17*$A56*F$54/1000000)*'Revenue Build_Empty'!F28)-'Revenue Build_Empty'!F27-'Revenue Build_Empty'!F30)>0,((('Revenue Build_Empty'!F17*$A56*F$54/1000000)*(1+'Revenue Build_Empty'!F19))-(('Revenue Build_Empty'!F17*$A56*F$54/1000000)*'Revenue Build_Empty'!F28)-'Revenue Build_Empty'!F27-'Revenue Build_Empty'!F30)*(1-23.6%),((('Revenue Build_Empty'!F17*$A56*F$54/1000000)*(1+'Revenue Build_Empty'!F19))-(('Revenue Build_Empty'!F17*$A56*F$54/1000000)*'Revenue Build_Empty'!F28)-'Revenue Build_Empty'!F27-'Revenue Build_Empty'!F30)))/(1+$F$4)^3+(IF(((('Revenue Build_Empty'!G17*$A56*F$54/1000000)*(1+'Revenue Build_Empty'!G19))-(('Revenue Build_Empty'!G17*$A56*F$54/1000000)*'Revenue Build_Empty'!G28)-'Revenue Build_Empty'!G27-'Revenue Build_Empty'!G30)>0,((('Revenue Build_Empty'!G17*$A56*F$54/1000000)*(1+'Revenue Build_Empty'!G19))-(('Revenue Build_Empty'!G17*$A56*F$54/1000000)*'Revenue Build_Empty'!G28)-'Revenue Build_Empty'!G27-'Revenue Build_Empty'!G30)*(1-23.6%),((('Revenue Build_Empty'!G17*$A56*F$54/1000000)*(1+'Revenue Build_Empty'!G19))-(('Revenue Build_Empty'!G17*$A56*F$54/1000000)*'Revenue Build_Empty'!G28)-'Revenue Build_Empty'!G27-'Revenue Build_Empty'!G30)))/(1+$F$4)^4+(IF(((('Revenue Build_Empty'!H17*$A56*F$54/1000000)*(1+'Revenue Build_Empty'!H19))-(('Revenue Build_Empty'!H17*$A56*F$54/1000000)*'Revenue Build_Empty'!H28)-'Revenue Build_Empty'!H27-'Revenue Build_Empty'!H30)>0,((('Revenue Build_Empty'!H17*$A56*F$54/1000000)*(1+'Revenue Build_Empty'!H19))-(('Revenue Build_Empty'!H17*$A56*F$54/1000000)*'Revenue Build_Empty'!H28)-'Revenue Build_Empty'!H27-'Revenue Build_Empty'!H30)*(1-23.6%),((('Revenue Build_Empty'!H17*$A56*F$54/1000000)*(1+'Revenue Build_Empty'!H19))-(('Revenue Build_Empty'!H17*$A56*F$54/1000000)*'Revenue Build_Empty'!H28)-'Revenue Build_Empty'!H27-'Revenue Build_Empty'!H30)))/(1+$F$4)^5+(IF(((('Revenue Build_Empty'!I17*$A56*F$54/1000000)*(1+'Revenue Build_Empty'!I19))-(('Revenue Build_Empty'!I17*$A56*F$54/1000000)*'Revenue Build_Empty'!I28)-'Revenue Build_Empty'!I27-'Revenue Build_Empty'!I30)>0,((('Revenue Build_Empty'!I17*$A56*F$54/1000000)*(1+'Revenue Build_Empty'!I19))-(('Revenue Build_Empty'!I17*$A56*F$54/1000000)*'Revenue Build_Empty'!I28)-'Revenue Build_Empty'!I27-'Revenue Build_Empty'!I30)*(1-23.6%),((('Revenue Build_Empty'!I17*$A56*F$54/1000000)*(1+'Revenue Build_Empty'!I19))-(('Revenue Build_Empty'!I17*$A56*F$54/1000000)*'Revenue Build_Empty'!I28)-'Revenue Build_Empty'!I27-'Revenue Build_Empty'!I30)))/(1+$F$4)^6 -> 62.986667
A57: 1 | B57: =$B$17+(IF(((('Revenue Build_Empty'!D17*$A57*B$54/1000000)*(1+'Revenue Build_Empty'!D19))-(('Revenue Build_Empty'!D17*$A57*B$54/1000000)*'Revenue Build_Empty'!D28)-'Revenue Build_Empty'!D27-'Revenue Build_Empty'!D30)>0,((('Revenue Build_Empty'!D17*$A57*B$54/1000000)*(1+'Revenue Build_Empty'!D19))-(('Revenue Build_Empty'!D17*$A57*B$54/1000000)*'Revenue Build_Empty'!D28)-'Revenue Build_Empty'!D27-'Revenue Build_Empty'!D30)*(1-23.6%),((('Revenue Build_Empty'!D17*$A57*B$54/1000000)*(1+'Revenue Build_Empty'!D19))-(('Revenue Build_Empty'!D17*$A57*B$54/1000000)*'Revenue Build_Empty'!D28)-'Revenue Build_Empty'!D27-'Revenue Build_Empty'!D30)))/(1+$F$4)^1+(IF(((('Revenue Build_Empty'!E17*$A57*B$54/1000000)*(1+'Revenue Build_Empty'!E19))-(('Revenue Build_Empty'!E17*$A57*B$54/1000000)*'Revenue Build_Empty'!E28)-'Revenue Build_Empty'!E27-'Revenue Build_Empty'!E30)>0,((('Revenue Build_Empty'!E17*$A57*B$54/1000000)*(1+'Revenue Build_Empty'!E19))-(('Revenue Build_Empty'!E17*$A57*B$54/1000000)*'Revenue Build_Empty'!E28)-'Revenue Build_Empty'!E27-'Revenue Build_Empty'!E30)*(1-23.6%),((('Revenue Build_Empty'!E17*$A57*B$54/1000000)*(1+'Revenue Build_Empty'!E19))-(('Revenue Build_Empty'!E17*$A57*B$54/1000000)*'Revenue Build_Empty'!E28)-'Revenue Build_Empty'!E27-'Revenue Build_Empty'!E30)))/(1+$F$4)^2+(IF(((('Revenue Build_Empty'!F17*$A57*B$54/1000000)*(1+'Revenue Build_Empty'!F19))-(('Revenue Build_Empty'!F17*$A57*B$54/1000000)*'Revenue Build_Empty'!F28)-'Revenue Build_Empty'!F27-'Revenue Build_Empty'!F30)>0,((('Revenue Build_Empty'!F17*$A57*B$54/1000000)*(1+'Revenue Build_Empty'!F19))-(('Revenue Build_Empty'!F17*$A57*B$54/1000000)*'Revenue Build_Empty'!F28)-'Revenue Build_Empty'!F27-'Revenue Build_Empty'!F30)*(1-23.6%),((('Revenue Build_Empty'!F17*$A57*B$54/1000000)*(1+'Revenue Build_Empty'!F19))-(('Revenue Build_Empty'!F17*$A57*B$54/1000000)*'Revenue Build_Empty'!F28)-'Revenue Build_Empty'!F27-'Revenue Build_Empty'!F30)))/(1+$F$4)^3+(IF(((('Revenue Build_Empty'!G17*$A57*B$54/1000000)*(1+'Revenue Build_Empty'!G19))-(('Revenue Build_Empty'!G17*$A57*B$54/1000000)*'Revenue Build_Empty'!G28)-'Revenue Build_Empty'!G27-'Revenue Build_Empty'!G30)>0,((('Revenue Build_Empty'!G17*$A57*B$54/1000000)*(1+'Revenue Build_Empty'!G19))-(('Revenue Build_Empty'!G17*$A57*B$54/1000000)*'Revenue Build_Empty'!G28)-'Revenue Build_Empty'!G27-'Revenue Build_Empty'!G30)*(1-23.6%),((('Revenue Build_Empty'!G17*$A57*B$54/1000000)*(1+'Revenue Build_Empty'!G19))-(('Revenue Build_Empty'!G17*$A57*B$54/1000000)*'Revenue Build_Empty'!G28)-'Revenue Build_Empty'!G27-'Revenue Build_Empty'!G30)))/(1+$F$4)^4+(IF(((('Revenue Build_Empty'!H17*$A57*B$54/1000000)*(1+'Revenue Build_Empty'!H19))-(('Revenue Build_Empty'!H17*$A57*B$54/1000000)*'Revenue Build_Empty'!H28)-'Revenue Build_Empty'!H27-'Revenue Build_Empty'!H30)>0,((('Revenue Build_Empty'!H17*$A57*B$54/1000000)*(1+'Revenue Build_Empty'!H19))-(('Revenue Build_Empty'!H17*$A57*B$54/1000000)*'Revenue Build_Empty'!H28)-'Revenue Build_Empty'!H27-'Revenue Build_Empty'!H30)*(1-23.6%),((('Revenue Build_Empty'!H17*$A57*B$54/1000000)*(1+'Revenue Build_Empty'!H19))-(('Revenue Build_Empty'!H17*$A57*B$54/1000000)*'Revenue Build_Empty'!H28)-'Revenue Build_Empty'!H27-'Revenue Build_Empty'!H30)))/(1+$F$4)^5+(IF(((('Revenue Build_Empty'!I17*$A57*B$54/1000000)*(1+'Revenue Build_Empty'!I19))-(('Revenue Build_Empty'!I17*$A57*B$54/1000000)*'Revenue Build_Empty'!I28)-'Revenue Build_Empty'!I27-'Revenue Build_Empty'!I30)>0,((('Revenue Build_Empty'!I17*$A57*B$54/1000000)*(1+'Revenue Build_Empty'!I19))-(('Revenue Build_Empty'!I17*$A57*B$54/1000000)*'Revenue Build_Empty'!I28)-'Revenue Build_Empty'!I27-'Revenue Build_Empty'!I30)*(1-23.6%),((('Revenue Build_Empty'!I17*$A57*B$54/1000000)*(1+'Revenue Build_Empty'!I19))-(('Revenue Build_Empty'!I17*$A57*B$54/1000000)*'Revenue Build_Empty'!I28)-'Revenue Build_Empty'!I27-'Revenue Build_Empty'!I30)))/(1+$F$4)^6 -> -70.382801 | C57: =$B$17+(IF(((('Revenue Build_Empty'!D17*$A57*C$54/1000000)*(1+'Revenue Build_Empty'!D19))-(('Revenue Build_Empty'!D17*$A57*C$54/1000000)*'Revenue Build_Empty'!D28)-'Revenue Build_Empty'!D27-'Revenue Build_Empty'!D30)>0,((('Revenue Build_Empty'!D17*$A57*C$54/1000000)*(1+'Revenue Build_Empty'!D19))-(('Revenue Build_Empty'!D17*$A57*C$54/1000000)*'Revenue Build_Empty'!D28)-'Revenue Build_Empty'!D27-'Revenue Build_Empty'!D30)*(1-23.6%),((('Revenue Build_Empty'!D17*$A57*C$54/1000000)*(1+'Revenue Build_Empty'!D19))-(('Revenue Build_Empty'!D17*$A57*C$54/1000000)*'Revenue Build_Empty'!D28)-'Revenue Build_Empty'!D27-'Revenue Build_Empty'!D30)))/(1+$F$4)^1+(IF(((('Revenue Build_Empty'!E17*$A57*C$54/1000000)*(1+'Revenue Build_Empty'!E19))-(('Revenue Build_Empty'!E17*$A57*C$54/1000000)*'Revenue Build_Empty'!E28)-'Revenue Build_Empty'!E27-'Revenue Build_Empty'!E30)>0,((('Revenue Build_Empty'!E17*$A57*C$54/1000000)*(1+'Revenue Build_Empty'!E19))-(('Revenue Build_Empty'!E17*$A57*C$54/1000000)*'Revenue Build_Empty'!E28)-'Revenue Build_Empty'!E27-'Revenue Build_Empty'!E30)*(1-23.6%),((('Revenue Build_Empty'!E17*$A57*C$54/1000000)*(1+'Revenue Build_Empty'!E19))-(('Revenue Build_Empty'!E17*$A57*C$54/1000000)*'Revenue Build_Empty'!E28)-'Revenue Build_Empty'!E27-'Revenue Build_Empty'!E30)))/(1+$F$4)^2+(IF(((('Revenue Build_Empty'!F17*$A57*C$54/1000000)*(1+'Revenue Build_Empty'!F19))-(('Revenue Build_Empty'!F17*$A57*C$54/1000000)*'Revenue Build_Empty'!F28)-'Revenue Build_Empty'!F27-'Revenue Build_Empty'!F30)>0,((('Revenue Build_Empty'!F17*$A57*C$54/1000000)*(1+'Revenue Build_Empty'!F19))-(('Revenue Build_Empty'!F17*$A57*C$54/1000000)*'Revenue Build_Empty'!F28)-'Revenue Build_Empty'!F27-'Revenue Build_Empty'!F30)*(1-23.6%),((('Revenue Build_Empty'!F17*$A57*C$54/1000000)*(1+'Revenue Build_Empty'!F19))-(('Revenue Build_Empty'!F17*$A57*C$54/1000000)*'Revenue Build_Empty'!F28)-'Revenue Build_Empty'!F27-'Revenue Build_Empty'!F30)))/(1+$F$4)^3+(IF(((('Revenue Build_Empty'!G17*$A57*C$54/1000000)*(1+'Revenue Build_Empty'!G19))-(('Revenue Build_Empty'!G17*$A57*C$54/1000000)*'Revenue Build_Empty'!G28)-'Revenue Build_Empty'!G27-'Revenue Build_Empty'!G30)>0,((('Revenue Build_Empty'!G17*$A57*C$54/1000000)*(1+'Revenue Build_Empty'!G19))-(('Revenue Build_Empty'!G17*$A57*C$54/1000000)*'Revenue Build_Empty'!G28)-'Revenue Build_Empty'!G27-'Revenue Build_Empty'!G30)*(1-23.6%),((('Revenue Build_Empty'!G17*$A57*C$54/1000000)*(1+'Revenue Build_Empty'!G19))-(('Revenue Build_Empty'!G17*$A57*C$54/1000000)*'Revenue Build_Empty'!G28)-'Revenue Build_Empty'!G27-'Revenue Build_Empty'!G30)))/(1+$F$4)^4+(IF(((('Revenue Build_Empty'!H17*$A57*C$54/1000000)*(1+'Revenue Build_Empty'!H19))-(('Revenue Build_Empty'!H17*$A57*C$54/1000000)*'Revenue Build_Empty'!H28)-'Revenue Build_Empty'!H27-'Revenue Build_Empty'!H30)>0,((('Revenue Build_Empty'!H17*$A57*C$54/1000000)*(1+'Revenue Build_Empty'!H19))-(('Revenue Build_Empty'!H17*$A57*C$54/1000000)*'Revenue Build_Empty'!H28)-'Revenue Build_Empty'!H27-'Revenue Build_Empty'!H30)*(1-23.6%),((('Revenue Build_Empty'!H17*$A57*C$54/1000000)*(1+'Revenue Build_Empty'!H19))-(('Revenue Build_Empty'!H17*$A57*C$54/1000000)*'Revenue Build_Empty'!H28)-'Revenue Build_Empty'!H27-'Revenue Build_Empty'!H30)))/(1+$F$4)^5+(IF(((('Revenue Build_Empty'!I17*$A57*C$54/1000000)*(1+'Revenue Build_Empty'!I19))-(('Revenue Build_Empty'!I17*$A57*C$54/1000000)*'Revenue Build_Empty'!I28)-'Revenue Build_Empty'!I27-'Revenue Build_Empty'!I30)>0,((('Revenue Build_Empty'!I17*$A57*C$54/1000000)*(1+'Revenue Build_Empty'!I19))-(('Revenue Build_Empty'!I17*$A57*C$54/1000000)*'Revenue Build_Empty'!I28)-'Revenue Build_Empty'!I27-'Revenue Build_Empty'!I30)*(1-23.6%),((('Revenue Build_Empty'!I17*$A57*C$54/1000000)*(1+'Revenue Build_Empty'!I19))-(('Revenue Build_Empty'!I17*$A57*C$54/1000000)*'Revenue Build_Empty'!I28)-'Revenue Build_Empty'!I27-'Revenue Build_Empty'!I30)))/(1+$F$4)^6 -> -26.497491 | D57: =$B$17+(IF(((('Revenue Build_Empty'!D17*$A57*D$54/1000000)*(1+'Revenue Build_Empty'!D19))-(('Revenue Build_Empty'!D17*$A57*D$54/1000000)*'Revenue Build_Empty'!D28)-'Revenue Build_Empty'!D27-'Revenue Build_Empty'!D30)>0,((('Revenue Build_Empty'!D17*$A57*D$54/1000000)*(1+'Revenue Build_Empty'!D19))-(('Revenue Build_Empty'!D17*$A57*D$54/1000000)*'Revenue Build_Empty'!D28)-'Revenue Build_Empty'!D27-'Revenue Build_Empty'!D30)*(1-23.6%),((('Revenue Build_Empty'!D17*$A57*D$54/1000000)*(1+'Revenue Build_Empty'!D19))-(('Revenue Build_Empty'!D17*$A57*D$54/1000000)*'Revenue Build_Empty'!D28)-'Revenue Build_Empty'!D27-'Revenue Build_Empty'!D30)))/(1+$F$4)^1+(IF(((('Revenue Build_Empty'!E17*$A57*D$54/1000000)*(1+'Revenue Build_Empty'!E19))-(('Revenue Build_Empty'!E17*$A57*D$54/1000000)*'Revenue Build_Empty'!E28)-'Revenue Build_Empty'!E27-'Revenue Build_Empty'!E30)>0,((('Revenue Build_Empty'!E17*$A57*D$54/1000000)*(1+'Revenue Build_Empty'!E19))-(('Revenue Build_Empty'!E17*$A57*D$54/1000000)*'Revenue Build_Empty'!E28)-'Revenue Build_Empty'!E27-'Revenue Build_Empty'!E30)*(1-23.6%),((('Revenue Build_Empty'!E17*$A57*D$54/1000000)*(1+'Revenue Build_Empty'!E19))-(('Revenue Build_Empty'!E17*$A57*D$54/1000000)*'Revenue Build_Empty'!E28)-'Revenue Build_Empty'!E27-'Revenue Build_Empty'!E30)))/(1+$F$4)^2+(IF(((('Revenue Build_Empty'!F17*$A57*D$54/1000000)*(1+'Revenue Build_Empty'!F19))-(('Revenue Build_Empty'!F17*$A57*D$54/1000000)*'Revenue Build_Empty'!F28)-'Revenue Build_Empty'!F27-'Revenue Build_Empty'!F30)>0,((('Revenue Build_Empty'!F17*$A57*D$54/1000000)*(1+'Revenue Build_Empty'!F19))-(('Revenue Build_Empty'!F17*$A57*D$54/1000000)*'Revenue Build_Empty'!F28)-'Revenue Build_Empty'!F27-'Revenue Build_Empty'!F30)*(1-23.6%),((('Revenue Build_Empty'!F17*$A57*D$54/1000000)*(1+'Revenue Build_Empty'!F19))-(('Revenue Build_Empty'!F17*$A57*D$54/1000000)*'Revenue Build_Empty'!F28)-'Revenue Build_Empty'!F27-'Revenue Build_Empty'!F30)))/(1+$F$4)^3+(IF(((('Revenue Build_Empty'!G17*$A57*D$54/1000000)*(1+'Revenue Build_Empty'!G19))-(('Revenue Build_Empty'!G17*$A57*D$54/1000000)*'Revenue Build_Empty'!G28)-'Revenue Build_Empty'!G27-'Revenue Build_Empty'!G30)>0,((('Revenue Build_Empty'!G17*$A57*D$54/1000000)*(1+'Revenue Build_Empty'!G19))-(('Revenue Build_Empty'!G17*$A57*D$54/1000000)*'Revenue Build_Empty'!G28)-'Revenue Build_Empty'!G27-'Revenue Build_Empty'!G30)*(1-23.6%),((('Revenue Build_Empty'!G17*$A57*D$54/1000000)*(1+'Revenue Build_Empty'!G19))-(('Revenue Build_Empty'!G17*$A57*D$54/1000000)*'Revenue Build_Empty'!G28)-'Revenue Build_Empty'!G27-'Revenue Build_Empty'!G30)))/(1+$F$4)^4+(IF(((('Revenue Build_Empty'!H17*$A57*D$54/1000000)*(1+'Revenue Build_Empty'!H19))-(('Revenue Build_Empty'!H17*$A57*D$54/1000000)*'Revenue Build_Empty'!H28)-'Revenue Build_Empty'!H27-'Revenue Build_Empty'!H30)>0,((('Revenue Build_Empty'!H17*$A57*D$54/1000000)*(1+'Revenue Build_Empty'!H19))-(('Revenue Build_Empty'!H17*$A57*D$54/1000000)*'Revenue Build_Empty'!H28)-'Revenue Build_Empty'!H27-'Revenue Build_Empty'!H30)*(1-23.6%),((('Revenue Build_Empty'!H17*$A57*D$54/1000000)*(1+'Revenue Build_Empty'!H19))-(('Revenue Build_Empty'!H17*$A57*D$54/1000000)*'Revenue Build_Empty'!H28)-'Revenue Build_Empty'!H27-'Revenue Build_Empty'!H30)))/(1+$F$4)^5+(IF(((('Revenue Build_Empty'!I17*$A57*D$54/1000000)*(1+'Revenue Build_Empty'!I19))-(('Revenue Build_Empty'!I17*$A57*D$54/1000000)*'Revenue Build_Empty'!I28)-'Revenue Build_Empty'!I27-'Revenue Build_Empty'!I30)>0,((('Revenue Build_Empty'!I17*$A57*D$54/1000000)*(1+'Revenue Build_Empty'!I19))-(('Revenue Build_Empty'!I17*$A57*D$54/1000000)*'Revenue Build_Empty'!I28)-'Revenue Build_Empty'!I27-'Revenue Build_Empty'!I30)*(1-23.6%),((('Revenue Build_Empty'!I17*$A57*D$54/1000000)*(1+'Revenue Build_Empty'!I19))-(('Revenue Build_Empty'!I17*$A57*D$54/1000000)*'Revenue Build_Empty'!I28)-'Revenue Build_Empty'!I27-'Revenue Build_Empty'!I30)))/(1+$F$4)^6 -> 14.817892 | E57: =$B$17+(IF(((('Revenue Build_Empty'!D17*$A57*E$54/1000000)*(1+'Revenue Build_Empty'!D19))-(('Revenue Build_Empty'!D17*$A57*E$54/1000000)*'Revenue Build_Empty'!D28)-'Revenue Build_Empty'!D27-'Revenue Build_Empty'!D30)>0,((('Revenue Build_Empty'!D17*$A57*E$54/1000000)*(1+'Revenue Build_Empty'!D19))-(('Revenue Build_Empty'!D17*$A57*E$54/1000000)*'Revenue Build_Empty'!D28)-'Revenue Build_Empty'!D27-'Revenue Build_Empty'!D30)*(1-23.6%),((('Revenue Build_Empty'!D17*$A57*E$54/1000000)*(1+'Revenue Build_Empty'!D19))-(('Revenue Build_Empty'!D17*$A57*E$54/1000000)*'Revenue Build_Empty'!D28)-'Revenue Build_Empty'!D27-'Revenue Build_Empty'!D30)))/(1+$F$4)^1+(IF(((('Revenue Build_Empty'!E17*$A57*E$54/1000000)*(1+'Revenue Build_Empty'!E19))-(('Revenue Build_Empty'!E17*$A57*E$54/1000000)*'Revenue Build_Empty'!E28)-'Revenue Build_Empty'!E27-'Revenue Build_Empty'!E30)>0,((('Revenue Build_Empty'!E17*$A57*E$54/1000000)*(1+'Revenue Build_Empty'!E19))-(('Revenue Build_Empty'!E17*$A57*E$54/1000000)*'Revenue Build_Empty'!E28)-'Revenue Build_Empty'!E27-'Revenue Build_Empty'!E30)*(1-23.6%),((('Revenue Build_Empty'!E17*$A57*E$54/1000000)*(1+'Revenue Build_Empty'!E19))-(('Revenue Build_Empty'!E17*$A57*E$54/1000000)*'Revenue Build_Empty'!E28)-'Revenue Build_Empty'!E27-'Revenue Build_Empty'!E30)))/(1+$F$4)^2+(IF(((('Revenue Build_Empty'!F17*$A57*E$54/1000000)*(1+'Revenue Build_Empty'!F19))-(('Revenue Build_Empty'!F17*$A57*E$54/1000000)*'Revenue Build_Empty'!F28)-'Revenue Build_Empty'!F27-'Revenue Build_Empty'!F30)>0,((('Revenue Build_Empty'!F17*$A57*E$54/1000000)*(1+'Revenue Build_Empty'!F19))-(('Revenue Build_Empty'!F17*$A57*E$54/1000000)*'Revenue Build_Empty'!F28)-'Revenue Build_Empty'!F27-'Revenue Build_Empty'!F30)*(1-23.6%),((('Revenue Build_Empty'!F17*$A57*E$54/1000000)*(1+'Revenue Build_Empty'!F19))-(('Revenue Build_Empty'!F17*$A57*E$54/1000000)*'Revenue Build_Empty'!F28)-'Revenue Build_Empty'!F27-'Revenue Build_Empty'!F30)))/(1+$F$4)^3+(IF(((('Revenue Build_Empty'!G17*$A57*E$54/1000000)*(1+'Revenue Build_Empty'!G19))-(('Revenue Build_Empty'!G17*$A57*E$54/1000000)*'Revenue Build_Empty'!G28)-'Revenue Build_Empty'!G27-'Revenue Build_Empty'!G30)>0,((('Revenue Build_Empty'!G17*$A57*E$54/1000000)*(1+'Revenue Build_Empty'!G19))-(('Revenue Build_Empty'!G17*$A57*E$54/1000000)*'Revenue Build_Empty'!G28)-'Revenue Build_Empty'!G27-'Revenue Build_Empty'!G30)*(1-23.6%),((('Revenue Build_Empty'!G17*$A57*E$54/1000000)*(1+'Revenue Build_Empty'!G19))-(('Revenue Build_Empty'!G17*$A57*E$54/1000000)*'Revenue Build_Empty'!G28)-'Revenue Build_Empty'!G27-'Revenue Build_Empty'!G30)))/(1+$F$4)^4+(IF(((('Revenue Build_Empty'!H17*$A57*E$54/1000000)*(1+'Revenue Build_Empty'!H19))-(('Revenue Build_Empty'!H17*$A57*E$54/1000000)*'Revenue Build_Empty'!H28)-'Revenue Build_Empty'!H27-'Revenue Build_Empty'!H30)>0,((('Revenue Build_Empty'!H17*$A57*E$54/1000000)*(1+'Revenue Build_Empty'!H19))-(('Revenue Build_Empty'!H17*$A57*E$54/1000000)*'Revenue Build_Empty'!H28)-'Revenue Build_Empty'!H27-'Revenue Build_Empty'!H30)*(1-23.6%),((('Revenue Build_Empty'!H17*$A57*E$54/1000000)*(1+'Revenue Build_Empty'!H19))-(('Revenue Build_Empty'!H17*$A57*E$54/1000000)*'Revenue Build_Empty'!H28)-'Revenue Build_Empty'!H27-'Revenue Build_Empty'!H30)))/(1+$F$4)^5+(IF(((('Revenue Build_Empty'!I17*$A57*E$54/1000000)*(1+'Revenue Build_Empty'!I19))-(('Revenue Build_Empty'!I17*$A57*E$54/1000000)*'Revenue Build_Empty'!I28)-'Revenue Build_Empty'!I27-'Revenue Build_Empty'!I30)>0,((('Revenue Build_Empty'!I17*$A57*E$54/1000000)*(1+'Revenue Build_Empty'!I19))-(('Revenue Build_Empty'!I17*$A57*E$54/1000000)*'Revenue Build_Empty'!I28)-'Revenue Build_Empty'!I27-'Revenue Build_Empty'!I30)*(1-23.6%),((('Revenue Build_Empty'!I17*$A57*E$54/1000000)*(1+'Revenue Build_Empty'!I19))-(('Revenue Build_Empty'!I17*$A57*E$54/1000000)*'Revenue Build_Empty'!I28)-'Revenue Build_Empty'!I27-'Revenue Build_Empty'!I30)))/(1+$F$4)^6 -> 54.958538 | F57: =$B$17+(IF(((('Revenue Build_Empty'!D17*$A57*F$54/1000000)*(1+'Revenue Build_Empty'!D19))-(('Revenue Build_Empty'!D17*$A57*F$54/1000000)*'Revenue Build_Empty'!D28)-'Revenue Build_Empty'!D27-'Revenue Build_Empty'!D30)>0,((('Revenue Build_Empty'!D17*$A57*F$54/1000000)*(1+'Revenue Build_Empty'!D19))-(('Revenue Build_Empty'!D17*$A57*F$54/1000000)*'Revenue Build_Empty'!D28)-'Revenue Build_Empty'!D27-'Revenue Build_Empty'!D30)*(1-23.6%),((('Revenue Build_Empty'!D17*$A57*F$54/1000000)*(1+'Revenue Build_Empty'!D19))-(('Revenue Build_Empty'!D17*$A57*F$54/1000000)*'Revenue Build_Empty'!D28)-'Revenue Build_Empty'!D27-'Revenue Build_Empty'!D30)))/(1+$F$4)^1+(IF(((('Revenue Build_Empty'!E17*$A57*F$54/1000000)*(1+'Revenue Build_Empty'!E19))-(('Revenue Build_Empty'!E17*$A57*F$54/1000000)*'Revenue Build_Empty'!E28)-'Revenue Build_Empty'!E27-'Revenue Build_Empty'!E30)>0,((('Revenue Build_Empty'!E17*$A57*F$54/1000000)*(1+'Revenue Build_Empty'!E19))-(('Revenue Build_Empty'!E17*$A57*F$54/1000000)*'Revenue Build_Empty'!E28)-'Revenue Build_Empty'!E27-'Revenue Build_Empty'!E30)*(1-23.6%),((('Revenue Build_Empty'!E17*$A57*F$54/1000000)*(1+'Revenue Build_Empty'!E19))-(('Revenue Build_Empty'!E17*$A57*F$54/1000000)*'Revenue Build_Empty'!E28)-'Revenue Build_Empty'!E27-'Revenue Build_Empty'!E30)))/(1+$F$4)^2+(IF(((('Revenue Build_Empty'!F17*$A57*F$54/1000000)*(1+'Revenue Build_Empty'!F19))-(('Revenue Build_Empty'!F17*$A57*F$54/1000000)*'Revenue Build_Empty'!F28)-'Revenue Build_Empty'!F27-'Revenue Build_Empty'!F30)>0,((('Revenue Build_Empty'!F17*$A57*F$54/1000000)*(1+'Revenue Build_Empty'!F19))-(('Revenue Build_Empty'!F17*$A57*F$54/1000000)*'Revenue Build_Empty'!F28)-'Revenue Build_Empty'!F27-'Revenue Build_Empty'!F30)*(1-23.6%),((('Revenue Build_Empty'!F17*$A57*F$54/1000000)*(1+'Revenue Build_Empty'!F19))-(('Revenue Build_Empty'!F17*$A57*F$54/1000000)*'Revenue Build_Empty'!F28)-'Revenue Build_Empty'!F27-'Revenue Build_Empty'!F30)))/(1+$F$4)^3+(IF(((('Revenue Build_Empty'!G17*$A57*F$54/1000000)*(1+'Revenue Build_Empty'!G19))-(('Revenue Build_Empty'!G17*$A57*F$54/1000000)*'Revenue Build_Empty'!G28)-'Revenue Build_Empty'!G27-'Revenue Build_Empty'!G30)>0,((('Revenue Build_Empty'!G17*$A57*F$54/1000000)*(1+'Revenue Build_Empty'!G19))-(('Revenue Build_Empty'!G17*$A57*F$54/1000000)*'Revenue Build_Empty'!G28)-'Revenue Build_Empty'!G27-'Revenue Build_Empty'!G30)*(1-23.6%),((('Revenue Build_Empty'!G17*$A57*F$54/1000000)*(1+'Revenue Build_Empty'!G19))-(('Revenue Build_Empty'!G17*$A57*F$54/1000000)*'Revenue Build_Empty'!G28)-'Revenue Build_Empty'!G27-'Revenue Build_Empty'!G30)))/(1+$F$4)^4+(IF(((('Revenue Build_Empty'!H17*$A57*F$54/1000000)*(1+'Revenue Build_Empty'!H19))-(('Revenue Build_Empty'!H17*$A57*F$54/1000000)*'Revenue Build_Empty'!H28)-'Revenue Build_Empty'!H27-'Revenue Build_Empty'!H30)>0,((('Revenue Build_Empty'!H17*$A57*F$54/1000000)*(1+'Revenue Build_Empty'!H19))-(('Revenue Build_Empty'!H17*$A57*F$54/1000000)*'Revenue Build_Empty'!H28)-'Revenue Build_Empty'!H27-'Revenue Build_Empty'!H30)*(1-23.6%),((('Revenue Build_Empty'!H17*$A57*F$54/1000000)*(1+'Revenue Build_Empty'!H19))-(('Revenue Build_Empty'!H17*$A57*F$54/1000000)*'Revenue Build_Empty'!H28)-'Revenue Build_Empty'!H27-'Revenue Build_Empty'!H30)))/(1+$F$4)^5+(IF(((('Revenue Build_Empty'!I17*$A57*F$54/1000000)*(1+'Revenue Build_Empty'!I19))-(('Revenue Build_Empty'!I17*$A57*F$54/1000000)*'Revenue Build_Empty'!I28)-'Revenue Build_Empty'!I27-'Revenue Build_Empty'!I30)>0,((('Revenue Build_Empty'!I17*$A57*F$54/1000000)*(1+'Revenue Build_Empty'!I19))-(('Revenue Build_Empty'!I17*$A57*F$54/1000000)*'Revenue Build_Empty'!I28)-'Revenue Build_Empty'!I27-'Revenue Build_Empty'!I30)*(1-23.6%),((('Revenue Build_Empty'!I17*$A57*F$54/1000000)*(1+'Revenue Build_Empty'!I19))-(('Revenue Build_Empty'!I17*$A57*F$54/1000000)*'Revenue Build_Empty'!I28)-'Revenue Build_Empty'!I27-'Revenue Build_Empty'!I30)))/(1+$F$4)^6 -> 95.033473
A58: 1.15 | B58: =$B$17+(IF(((('Revenue Build_Empty'!D17*$A58*B$54/1000000)*(1+'Revenue Build_Empty'!D19))-(('Revenue Build_Empty'!D17*$A58*B$54/1000000)*'Revenue Build_Empty'!D28)-'Revenue Build_Empty'!D27-'Revenue Build_Empty'!D30)>0,((('Revenue Build_Empty'!D17*$A58*B$54/1000000)*(1+'Revenue Build_Empty'!D19))-(('Revenue Build_Empty'!D17*$A58*B$54/1000000)*'Revenue Build_Empty'!D28)-'Revenue Build_Empty'!D27-'Revenue Build_Empty'!D30)*(1-23.6%),((('Revenue Build_Empty'!D17*$A58*B$54/1000000)*(1+'Revenue Build_Empty'!D19))-(('Revenue Build_Empty'!D17*$A58*B$54/1000000)*'Revenue Build_Empty'!D28)-'Revenue Build_Empty'!D27-'Revenue Build_Empty'!D30)))/(1+$F$4)^1+(IF(((('Revenue Build_Empty'!E17*$A58*B$54/1000000)*(1+'Revenue Build_Empty'!E19))-(('Revenue Build_Empty'!E17*$A58*B$54/1000000)*'Revenue Build_Empty'!E28)-'Revenue Build_Empty'!E27-'Revenue Build_Empty'!E30)>0,((('Revenue Build_Empty'!E17*$A58*B$54/1000000)*(1+'Revenue Build_Empty'!E19))-(('Revenue Build_Empty'!E17*$A58*B$54/1000000)*'Revenue Build_Empty'!E28)-'Revenue Build_Empty'!E27-'Revenue Build_Empty'!E30)*(1-23.6%),((('Revenue Build_Empty'!E17*$A58*B$54/1000000)*(1+'Revenue Build_Empty'!E19))-(('Revenue Build_Empty'!E17*$A58*B$54/1000000)*'Revenue Build_Empty'!E28)-'Revenue Build_Empty'!E27-'Revenue Build_Empty'!E30)))/(1+$F$4)^2+(IF(((('Revenue Build_Empty'!F17*$A58*B$54/1000000)*(1+'Revenue Build_Empty'!F19))-(('Revenue Build_Empty'!F17*$A58*B$54/1000000)*'Revenue Build_Empty'!F28)-'Revenue Build_Empty'!F27-'Revenue Build_Empty'!F30)>0,((('Revenue Build_Empty'!F17*$A58*B$54/1000000)*(1+'Revenue Build_Empty'!F19))-(('Revenue Build_Empty'!F17*$A58*B$54/1000000)*'Revenue Build_Empty'!F28)-'Revenue Build_Empty'!F27-'Revenue Build_Empty'!F30)*(1-23.6%),((('Revenue Build_Empty'!F17*$A58*B$54/1000000)*(1+'Revenue Build_Empty'!F19))-(('Revenue Build_Empty'!F17*$A58*B$54/1000000)*'Revenue Build_Empty'!F28)-'Revenue Build_Empty'!F27-'Revenue Build_Empty'!F30)))/(1+$F$4)^3+(IF(((('Revenue Build_Empty'!G17*$A58*B$54/1000000)*(1+'Revenue Build_Empty'!G19))-(('Revenue Build_Empty'!G17*$A58*B$54/1000000)*'Revenue Build_Empty'!G28)-'Revenue Build_Empty'!G27-'Revenue Build_Empty'!G30)>0,((('Revenue Build_Empty'!G17*$A58*B$54/1000000)*(1+'Revenue Build_Empty'!G19))-(('Revenue Build_Empty'!G17*$A58*B$54/1000000)*'Revenue Build_Empty'!G28)-'Revenue Build_Empty'!G27-'Revenue Build_Empty'!G30)*(1-23.6%),((('Revenue Build_Empty'!G17*$A58*B$54/1000000)*(1+'Revenue Build_Empty'!G19))-(('Revenue Build_Empty'!G17*$A58*B$54/1000000)*'Revenue Build_Empty'!G28)-'Revenue Build_Empty'!G27-'Revenue Build_Empty'!G30)))/(1+$F$4)^4+(IF(((('Revenue Build_Empty'!H17*$A58*B$54/1000000)*(1+'Revenue Build_Empty'!H19))-(('Revenue Build_Empty'!H17*$A58*B$54/1000000)*'Revenue Build_Empty'!H28)-'Revenue Build_Empty'!H27-'Revenue Build_Empty'!H30)>0,((('Revenue Build_Empty'!H17*$A58*B$54/1000000)*(1+'Revenue Build_Empty'!H19))-(('Revenue Build_Empty'!H17*$A58*B$54/1000000)*'Revenue Build_Empty'!H28)-'Revenue Build_Empty'!H27-'Revenue Build_Empty'!H30)*(1-23.6%),((('Revenue Build_Empty'!H17*$A58*B$54/1000000)*(1+'Revenue Build_Empty'!H19))-(('Revenue Build_Empty'!H17*$A58*B$54/1000000)*'Revenue Build_Empty'!H28)-'Revenue Build_Empty'!H27-'Revenue Build_Empty'!H30)))/(1+$F$4)^5+(IF(((('Revenue Build_Empty'!I17*$A58*B$54/1000000)*(1+'Revenue Build_Empty'!I19))-(('Revenue Build_Empty'!I17*$A58*B$54/1000000)*'Revenue Build_Empty'!I28)-'Revenue Build_Empty'!I27-'Revenue Build_Empty'!I30)>0,((('Revenue Build_Empty'!I17*$A58*B$54/1000000)*(1+'Revenue Build_Empty'!I19))-(('Revenue Build_Empty'!I17*$A58*B$54/1000000)*'Revenue Build_Empty'!I28)-'Revenue Build_Empty'!I27-'Revenue Build_Empty'!I30)*(1-23.6%),((('Revenue Build_Empty'!I17*$A58*B$54/1000000)*(1+'Revenue Build_Empty'!I19))-(('Revenue Build_Empty'!I17*$A58*B$54/1000000)*'Revenue Build_Empty'!I28)-'Revenue Build_Empty'!I27-'Revenue Build_Empty'!I30)))/(1+$F$4)^6 -> -61.072672 | C58: =$B$17+(IF(((('Revenue Build_Empty'!D17*$A58*C$54/1000000)*(1+'Revenue Build_Empty'!D19))-(('Revenue Build_Empty'!D17*$A58*C$54/1000000)*'Revenue Build_Empty'!D28)-'Revenue Build_Empty'!D27-'Revenue Build_Empty'!D30)>0,((('Revenue Build_Empty'!D17*$A58*C$54/1000000)*(1+'Revenue Build_Empty'!D19))-(('Revenue Build_Empty'!D17*$A58*C$54/1000000)*'Revenue Build_Empty'!D28)-'Revenue Build_Empty'!D27-'Revenue Build_Empty'!D30)*(1-23.6%),((('Revenue Build_Empty'!D17*$A58*C$54/1000000)*(1+'Revenue Build_Empty'!D19))-(('Revenue Build_Empty'!D17*$A58*C$54/1000000)*'Revenue Build_Empty'!D28)-'Revenue Build_Empty'!D27-'Revenue Build_Empty'!D30)))/(1+$F$4)^1+(IF(((('Revenue Build_Empty'!E17*$A58*C$54/1000000)*(1+'Revenue Build_Empty'!E19))-(('Revenue Build_Empty'!E17*$A58*C$54/1000000)*'Revenue Build_Empty'!E28)-'Revenue Build_Empty'!E27-'Revenue Build_Empty'!E30)>0,((('Revenue Build_Empty'!E17*$A58*C$54/1000000)*(1+'Revenue Build_Empty'!E19))-(('Revenue Build_Empty'!E17*$A58*C$54/1000000)*'Revenue Build_Empty'!E28)-'Revenue Build_Empty'!E27-'Revenue Build_Empty'!E30)*(1-23.6%),((('Revenue Build_Empty'!E17*$A58*C$54/1000000)*(1+'Revenue Build_Empty'!E19))-(('Revenue Build_Empty'!E17*$A58*C$54/1000000)*'Revenue Build_Empty'!E28)-'Revenue Build_Empty'!E27-'Revenue Build_Empty'!E30)))/(1+$F$4)^2+(IF(((('Revenue Build_Empty'!F17*$A58*C$54/1000000)*(1+'Revenue Build_Empty'!F19))-(('Revenue Build_Empty'!F17*$A58*C$54/1000000)*'Revenue Build_Empty'!F28)-'Revenue Build_Empty'!F27-'Revenue Build_Empty'!F30)>0,((('Revenue Build_Empty'!F17*$A58*C$54/1000000)*(1+'Revenue Build_Empty'!F19))-(('Revenue Build_Empty'!F17*$A58*C$54/1000000)*'Revenue Build_Empty'!F28)-'Revenue Build_Empty'!F27-'Revenue Build_Empty'!F30)*(1-23.6%),((('Revenue Build_Empty'!F17*$A58*C$54/1000000)*(1+'Revenue Build_Empty'!F19))-(('Revenue Build_Empty'!F17*$A58*C$54/1000000)*'Revenue Build_Empty'!F28)-'Revenue Build_Empty'!F27-'Revenue Build_Empty'!F30)))/(1+$F$4)^3+(IF(((('Revenue Build_Empty'!G17*$A58*C$54/1000000)*(1+'Revenue Build_Empty'!G19))-(('Revenue Build_Empty'!G17*$A58*C$54/1000000)*'Revenue Build_Empty'!G28)-'Revenue Build_Empty'!G27-'Revenue Build_Empty'!G30)>0,((('Revenue Build_Empty'!G17*$A58*C$54/1000000)*(1+'Revenue Build_Empty'!G19))-(('Revenue Build_Empty'!G17*$A58*C$54/1000000)*'Revenue Build_Empty'!G28)-'Revenue Build_Empty'!G27-'Revenue Build_Empty'!G30)*(1-23.6%),((('Revenue Build_Empty'!G17*$A58*C$54/1000000)*(1+'Revenue Build_Empty'!G19))-(('Revenue Build_Empty'!G17*$A58*C$54/1000000)*'Revenue Build_Empty'!G28)-'Revenue Build_Empty'!G27-'Revenue Build_Empty'!G30)))/(1+$F$4)^4+(IF(((('Revenue Build_Empty'!H17*$A58*C$54/1000000)*(1+'Revenue Build_Empty'!H19))-(('Revenue Build_Empty'!H17*$A58*C$54/1000000)*'Revenue Build_Empty'!H28)-'Revenue Build_Empty'!H27-'Revenue Build_Empty'!H30)>0,((('Revenue Build_Empty'!H17*$A58*C$54/1000000)*(1+'Revenue Build_Empty'!H19))-(('Revenue Build_Empty'!H17*$A58*C$54/1000000)*'Revenue Build_Empty'!H28)-'Revenue Build_Empty'!H27-'Revenue Build_Empty'!H30)*(1-23.6%),((('Revenue Build_Empty'!H17*$A58*C$54/1000000)*(1+'Revenue Build_Empty'!H19))-(('Revenue Build_Empty'!H17*$A58*C$54/1000000)*'Revenue Build_Empty'!H28)-'Revenue Build_Empty'!H27-'Revenue Build_Empty'!H30)))/(1+$F$4)^5+(IF(((('Revenue Build_Empty'!I17*$A58*C$54/1000000)*(1+'Revenue Build_Empty'!I19))-(('Revenue Build_Empty'!I17*$A58*C$54/1000000)*'Revenue Build_Empty'!I28)-'Revenue Build_Empty'!I27-'Revenue Build_Empty'!I30)>0,((('Revenue Build_Empty'!I17*$A58*C$54/1000000)*(1+'Revenue Build_Empty'!I19))-(('Revenue Build_Empty'!I17*$A58*C$54/1000000)*'Revenue Build_Empty'!I28)-'Revenue Build_Empty'!I27-'Revenue Build_Empty'!I30)*(1-23.6%),((('Revenue Build_Empty'!I17*$A58*C$54/1000000)*(1+'Revenue Build_Empty'!I19))-(('Revenue Build_Empty'!I17*$A58*C$54/1000000)*'Revenue Build_Empty'!I28)-'Revenue Build_Empty'!I27-'Revenue Build_Empty'!I30)))/(1+$F$4)^6 -> -11.906267 | D58: =$B$17+(IF(((('Revenue Build_Empty'!D17*$A58*D$54/1000000)*(1+'Revenue Build_Empty'!D19))-(('Revenue Build_Empty'!D17*$A58*D$54/1000000)*'Revenue Build_Empty'!D28)-'Revenue Build_Empty'!D27-'Revenue Build_Empty'!D30)>0,((('Revenue Build_Empty'!D17*$A58*D$54/1000000)*(1+'Revenue Build_Empty'!D19))-(('Revenue Build_Empty'!D17*$A58*D$54/1000000)*'Revenue Build_Empty'!D28)-'Revenue Build_Empty'!D27-'Revenue Build_Empty'!D30)*(1-23.6%),((('Revenue Build_Empty'!D17*$A58*D$54/1000000)*(1+'Revenue Build_Empty'!D19))-(('Revenue Build_Empty'!D17*$A58*D$54/1000000)*'Revenue Build_Empty'!D28)-'Revenue Build_Empty'!D27-'Revenue Build_Empty'!D30)))/(1+$F$4)^1+(IF(((('Revenue Build_Empty'!E17*$A58*D$54/1000000)*(1+'Revenue Build_Empty'!E19))-(('Revenue Build_Empty'!E17*$A58*D$54/1000000)*'Revenue Build_Empty'!E28)-'Revenue Build_Empty'!E27-'Revenue Build_Empty'!E30)>0,((('Revenue Build_Empty'!E17*$A58*D$54/1000000)*(1+'Revenue Build_Empty'!E19))-(('Revenue Build_Empty'!E17*$A58*D$54/1000000)*'Revenue Build_Empty'!E28)-'Revenue Build_Empty'!E27-'Revenue Build_Empty'!E30)*(1-23.6%),((('Revenue Build_Empty'!E17*$A58*D$54/1000000)*(1+'Revenue Build_Empty'!E19))-(('Revenue Build_Empty'!E17*$A58*D$54/1000000)*'Revenue Build_Empty'!E28)-'Revenue Build_Empty'!E27-'Revenue Build_Empty'!E30)))/(1+$F$4)^2+(IF(((('Revenue Build_Empty'!F17*$A58*D$54/1000000)*(1+'Revenue Build_Empty'!F19))-(('Revenue Build_Empty'!F17*$A58*D$54/1000000)*'Revenue Build_Empty'!F28)-'Revenue Build_Empty'!F27-'Revenue Build_Empty'!F30)>0,((('Revenue Build_Empty'!F17*$A58*D$54/1000000)*(1+'Revenue Build_Empty'!F19))-(('Revenue Build_Empty'!F17*$A58*D$54/1000000)*'Revenue Build_Empty'!F28)-'Revenue Build_Empty'!F27-'Revenue Build_Empty'!F30)*(1-23.6%),((('Revenue Build_Empty'!F17*$A58*D$54/1000000)*(1+'Revenue Build_Empty'!F19))-(('Revenue Build_Empty'!F17*$A58*D$54/1000000)*'Revenue Build_Empty'!F28)-'Revenue Build_Empty'!F27-'Revenue Build_Empty'!F30)))/(1+$F$4)^3+(IF(((('Revenue Build_Empty'!G17*$A58*D$54/1000000)*(1+'Revenue Build_Empty'!G19))-(('Revenue Build_Empty'!G17*$A58*D$54/1000000)*'Revenue Build_Empty'!G28)-'Revenue Build_Empty'!G27-'Revenue Build_Empty'!G30)>0,((('Revenue Build_Empty'!G17*$A58*D$54/1000000)*(1+'Revenue Build_Empty'!G19))-(('Revenue Build_Empty'!G17*$A58*D$54/1000000)*'Revenue Build_Empty'!G28)-'Revenue Build_Empty'!G27-'Revenue Build_Empty'!G30)*(1-23.6%),((('Revenue Build_Empty'!G17*$A58*D$54/1000000)*(1+'Revenue Build_Empty'!G19))-(('Revenue Build_Empty'!G17*$A58*D$54/1000000)*'Revenue Build_Empty'!G28)-'Revenue Build_Empty'!G27-'Revenue Build_Empty'!G30)))/(1+$F$4)^4+(IF(((('Revenue Build_Empty'!H17*$A58*D$54/1000000)*(1+'Revenue Build_Empty'!H19))-(('Revenue Build_Empty'!H17*$A58*D$54/1000000)*'Revenue Build_Empty'!H28)-'Revenue Build_Empty'!H27-'Revenue Build_Empty'!H30)>0,((('Revenue Build_Empty'!H17*$A58*D$54/1000000)*(1+'Revenue Build_Empty'!H19))-(('Revenue Build_Empty'!H17*$A58*D$54/1000000)*'Revenue Build_Empty'!H28)-'Revenue Build_Empty'!H27-'Revenue Build_Empty'!H30)*(1-23.6%),((('Revenue Build_Empty'!H17*$A58*D$54/1000000)*(1+'Revenue Build_Empty'!H19))-(('Revenue Build_Empty'!H17*$A58*D$54/1000000)*'Revenue Build_Empty'!H28)-'Revenue Build_Empty'!H27-'Revenue Build_Empty'!H30)))/(1+$F$4)^5+(IF(((('Revenue Build_Empty'!I17*$A58*D$54/1000000)*(1+'Revenue Build_Empty'!I19))-(('Revenue Build_Empty'!I17*$A58*D$54/1000000)*'Revenue Build_Empty'!I28)-'Revenue Build_Empty'!I27-'Revenue Build_Empty'!I30)>0,((('Revenue Build_Empty'!I17*$A58*D$54/1000000)*(1+'Revenue Build_Empty'!I19))-(('Revenue Build_Empty'!I17*$A58*D$54/1000000)*'Revenue Build_Empty'!I28)-'Revenue Build_Empty'!I27-'Revenue Build_Empty'!I30)*(1-23.6%),((('Revenue Build_Empty'!I17*$A58*D$54/1000000)*(1+'Revenue Build_Empty'!I19))-(('Revenue Build_Empty'!I17*$A58*D$54/1000000)*'Revenue Build_Empty'!I28)-'Revenue Build_Empty'!I27-'Revenue Build_Empty'!I30)))/(1+$F$4)^6 -> 34.888215 | E58: =$B$17+(IF(((('Revenue Build_Empty'!D17*$A58*E$54/1000000)*(1+'Revenue Build_Empty'!D19))-(('Revenue Build_Empty'!D17*$A58*E$54/1000000)*'Revenue Build_Empty'!D28)-'Revenue Build_Empty'!D27-'Revenue Build_Empty'!D30)>0,((('Revenue Build_Empty'!D17*$A58*E$54/1000000)*(1+'Revenue Build_Empty'!D19))-(('Revenue Build_Empty'!D17*$A58*E$54/1000000)*'Revenue Build_Empty'!D28)-'Revenue Build_Empty'!D27-'Revenue Build_Empty'!D30)*(1-23.6%),((('Revenue Build_Empty'!D17*$A58*E$54/1000000)*(1+'Revenue Build_Empty'!D19))-(('Revenue Build_Empty'!D17*$A58*E$54/1000000)*'Revenue Build_Empty'!D28)-'Revenue Build_Empty'!D27-'Revenue Build_Empty'!D30)))/(1+$F$4)^1+(IF(((('Revenue Build_Empty'!E17*$A58*E$54/1000000)*(1+'Revenue Build_Empty'!E19))-(('Revenue Build_Empty'!E17*$A58*E$54/1000000)*'Revenue Build_Empty'!E28)-'Revenue Build_Empty'!E27-'Revenue Build_Empty'!E30)>0,((('Revenue Build_Empty'!E17*$A58*E$54/1000000)*(1+'Revenue Build_Empty'!E19))-(('Revenue Build_Empty'!E17*$A58*E$54/1000000)*'Revenue Build_Empty'!E28)-'Revenue Build_Empty'!E27-'Revenue Build_Empty'!E30)*(1-23.6%),((('Revenue Build_Empty'!E17*$A58*E$54/1000000)*(1+'Revenue Build_Empty'!E19))-(('Revenue Build_Empty'!E17*$A58*E$54/1000000)*'Revenue Build_Empty'!E28)-'Revenue Build_Empty'!E27-'Revenue Build_Empty'!E30)))/(1+$F$4)^2+(IF(((('Revenue Build_Empty'!F17*$A58*E$54/1000000)*(1+'Revenue Build_Empty'!F19))-(('Revenue Build_Empty'!F17*$A58*E$54/1000000)*'Revenue Build_Empty'!F28)-'Revenue Build_Empty'!F27-'Revenue Build_Empty'!F30)>0,((('Revenue Build_Empty'!F17*$A58*E$54/1000000)*(1+'Revenue Build_Empty'!F19))-(('Revenue Build_Empty'!F17*$A58*E$54/1000000)*'Revenue Build_Empty'!F28)-'Revenue Build_Empty'!F27-'Revenue Build_Empty'!F30)*(1-23.6%),((('Revenue Build_Empty'!F17*$A58*E$54/1000000)*(1+'Revenue Build_Empty'!F19))-(('Revenue Build_Empty'!F17*$A58*E$54/1000000)*'Revenue Build_Empty'!F28)-'Revenue Build_Empty'!F27-'Revenue Build_Empty'!F30)))/(1+$F$4)^3+(IF(((('Revenue Build_Empty'!G17*$A58*E$54/1000000)*(1+'Revenue Build_Empty'!G19))-(('Revenue Build_Empty'!G17*$A58*E$54/1000000)*'Revenue Build_Empty'!G28)-'Revenue Build_Empty'!G27-'Revenue Build_Empty'!G30)>0,((('Revenue Build_Empty'!G17*$A58*E$54/1000000)*(1+'Revenue Build_Empty'!G19))-(('Revenue Build_Empty'!G17*$A58*E$54/1000000)*'Revenue Build_Empty'!G28)-'Revenue Build_Empty'!G27-'Revenue Build_Empty'!G30)*(1-23.6%),((('Revenue Build_Empty'!G17*$A58*E$54/1000000)*(1+'Revenue Build_Empty'!G19))-(('Revenue Build_Empty'!G17*$A58*E$54/1000000)*'Revenue Build_Empty'!G28)-'Revenue Build_Empty'!G27-'Revenue Build_Empty'!G30)))/(1+$F$4)^4+(IF(((('Revenue Build_Empty'!H17*$A58*E$54/1000000)*(1+'Revenue Build_Empty'!H19))-(('Revenue Build_Empty'!H17*$A58*E$54/1000000)*'Revenue Build_Empty'!H28)-'Revenue Build_Empty'!H27-'Revenue Build_Empty'!H30)>0,((('Revenue Build_Empty'!H17*$A58*E$54/1000000)*(1+'Revenue Build_Empty'!H19))-(('Revenue Build_Empty'!H17*$A58*E$54/1000000)*'Revenue Build_Empty'!H28)-'Revenue Build_Empty'!H27-'Revenue Build_Empty'!H30)*(1-23.6%),((('Revenue Build_Empty'!H17*$A58*E$54/1000000)*(1+'Revenue Build_Empty'!H19))-(('Revenue Build_Empty'!H17*$A58*E$54/1000000)*'Revenue Build_Empty'!H28)-'Revenue Build_Empty'!H27-'Revenue Build_Empty'!H30)))/(1+$F$4)^5+(IF(((('Revenue Build_Empty'!I17*$A58*E$54/1000000)*(1+'Revenue Build_Empty'!I19))-(('Revenue Build_Empty'!I17*$A58*E$54/1000000)*'Revenue Build_Empty'!I28)-'Revenue Build_Empty'!I27-'Revenue Build_Empty'!I30)>0,((('Revenue Build_Empty'!I17*$A58*E$54/1000000)*(1+'Revenue Build_Empty'!I19))-(('Revenue Build_Empty'!I17*$A58*E$54/1000000)*'Revenue Build_Empty'!I28)-'Revenue Build_Empty'!I27-'Revenue Build_Empty'!I30)*(1-23.6%),((('Revenue Build_Empty'!I17*$A58*E$54/1000000)*(1+'Revenue Build_Empty'!I19))-(('Revenue Build_Empty'!I17*$A58*E$54/1000000)*'Revenue Build_Empty'!I28)-'Revenue Build_Empty'!I27-'Revenue Build_Empty'!I30)))/(1+$F$4)^6 -> 81.049957 | F58: =$B$17+(IF(((('Revenue Build_Empty'!D17*$A58*F$54/1000000)*(1+'Revenue Build_Empty'!D19))-(('Revenue Build_Empty'!D17*$A58*F$54/1000000)*'Revenue Build_Empty'!D28)-'Revenue Build_Empty'!D27-'Revenue Build_Empty'!D30)>0,((('Revenue Build_Empty'!D17*$A58*F$54/1000000)*(1+'Revenue Build_Empty'!D19))-(('Revenue Build_Empty'!D17*$A58*F$54/1000000)*'Revenue Build_Empty'!D28)-'Revenue Build_Empty'!D27-'Revenue Build_Empty'!D30)*(1-23.6%),((('Revenue Build_Empty'!D17*$A58*F$54/1000000)*(1+'Revenue Build_Empty'!D19))-(('Revenue Build_Empty'!D17*$A58*F$54/1000000)*'Revenue Build_Empty'!D28)-'Revenue Build_Empty'!D27-'Revenue Build_Empty'!D30)))/(1+$F$4)^1+(IF(((('Revenue Build_Empty'!E17*$A58*F$54/1000000)*(1+'Revenue Build_Empty'!E19))-(('Revenue Build_Empty'!E17*$A58*F$54/1000000)*'Revenue Build_Empty'!E28)-'Revenue Build_Empty'!E27-'Revenue Build_Empty'!E30)>0,((('Revenue Build_Empty'!E17*$A58*F$54/1000000)*(1+'Revenue Build_Empty'!E19))-(('Revenue Build_Empty'!E17*$A58*F$54/1000000)*'Revenue Build_Empty'!E28)-'Revenue Build_Empty'!E27-'Revenue Build_Empty'!E30)*(1-23.6%),((('Revenue Build_Empty'!E17*$A58*F$54/1000000)*(1+'Revenue Build_Empty'!E19))-(('Revenue Build_Empty'!E17*$A58*F$54/1000000)*'Revenue Build_Empty'!E28)-'Revenue Build_Empty'!E27-'Revenue Build_Empty'!E30)))/(1+$F$4)^2+(IF(((('Revenue Build_Empty'!F17*$A58*F$54/1000000)*(1+'Revenue Build_Empty'!F19))-(('Revenue Build_Empty'!F17*$A58*F$54/1000000)*'Revenue Build_Empty'!F28)-'Revenue Build_Empty'!F27-'Revenue Build_Empty'!F30)>0,((('Revenue Build_Empty'!F17*$A58*F$54/1000000)*(1+'Revenue Build_Empty'!F19))-(('Revenue Build_Empty'!F17*$A58*F$54/1000000)*'Revenue Build_Empty'!F28)-'Revenue Build_Empty'!F27-'Revenue Build_Empty'!F30)*(1-23.6%),((('Revenue Build_Empty'!F17*$A58*F$54/1000000)*(1+'Revenue Build_Empty'!F19))-(('Revenue Build_Empty'!F17*$A58*F$54/1000000)*'Revenue Build_Empty'!F28)-'Revenue Build_Empty'!F27-'Revenue Build_Empty'!F30)))/(1+$F$4)^3+(IF(((('Revenue Build_Empty'!G17*$A58*F$54/1000000)*(1+'Revenue Build_Empty'!G19))-(('Revenue Build_Empty'!G17*$A58*F$54/1000000)*'Revenue Build_Empty'!G28)-'Revenue Build_Empty'!G27-'Revenue Build_Empty'!G30)>0,((('Revenue Build_Empty'!G17*$A58*F$54/1000000)*(1+'Revenue Build_Empty'!G19))-(('Revenue Build_Empty'!G17*$A58*F$54/1000000)*'Revenue Build_Empty'!G28)-'Revenue Build_Empty'!G27-'Revenue Build_Empty'!G30)*(1-23.6%),((('Revenue Build_Empty'!G17*$A58*F$54/1000000)*(1+'Revenue Build_Empty'!G19))-(('Revenue Build_Empty'!G17*$A58*F$54/1000000)*'Revenue Build_Empty'!G28)-'Revenue Build_Empty'!G27-'Revenue Build_Empty'!G30)))/(1+$F$4)^4+(IF(((('Revenue Build_Empty'!H17*$A58*F$54/1000000)*(1+'Revenue Build_Empty'!H19))-(('Revenue Build_Empty'!H17*$A58*F$54/1000000)*'Revenue Build_Empty'!H28)-'Revenue Build_Empty'!H27-'Revenue Build_Empty'!H30)>0,((('Revenue Build_Empty'!H17*$A58*F$54/1000000)*(1+'Revenue Build_Empty'!H19))-(('Revenue Build_Empty'!H17*$A58*F$54/1000000)*'Revenue Build_Empty'!H28)-'Revenue Build_Empty'!H27-'Revenue Build_Empty'!H30)*(1-23.6%),((('Revenue Build_Empty'!H17*$A58*F$54/1000000)*(1+'Revenue Build_Empty'!H19))-(('Revenue Build_Empty'!H17*$A58*F$54/1000000)*'Revenue Build_Empty'!H28)-'Revenue Build_Empty'!H27-'Revenue Build_Empty'!H30)))/(1+$F$4)^5+(IF(((('Revenue Build_Empty'!I17*$A58*F$54/1000000)*(1+'Revenue Build_Empty'!I19))-(('Revenue Build_Empty'!I17*$A58*F$54/1000000)*'Revenue Build_Empty'!I28)-'Revenue Build_Empty'!I27-'Revenue Build_Empty'!I30)>0,((('Revenue Build_Empty'!I17*$A58*F$54/1000000)*(1+'Revenue Build_Empty'!I19))-(('Revenue Build_Empty'!I17*$A58*F$54/1000000)*'Revenue Build_Empty'!I28)-'Revenue Build_Empty'!I27-'Revenue Build_Empty'!I30)*(1-23.6%),((('Revenue Build_Empty'!I17*$A58*F$54/1000000)*(1+'Revenue Build_Empty'!I19))-(('Revenue Build_Empty'!I17*$A58*F$54/1000000)*'Revenue Build_Empty'!I28)-'Revenue Build_Empty'!I27-'Revenue Build_Empty'!I30)))/(1+$F$4)^6 -> 126.40279
A59: 1.3 | B59: =$B$17+(IF(((('Revenue Build_Empty'!D17*$A59*B$54/1000000)*(1+'Revenue Build_Empty'!D19))-(('Revenue Build_Empty'!D17*$A59*B$54/1000000)*'Revenue Build_Empty'!D28)-'Revenue Build_Empty'!D27-'Revenue Build_Empty'!D30)>0,((('Revenue Build_Empty'!D17*$A59*B$54/1000000)*(1+'Revenue Build_Empty'!D19))-(('Revenue Build_Empty'!D17*$A59*B$54/1000000)*'Revenue Build_Empty'!D28)-'Revenue Build_Empty'!D27-'Revenue Build_Empty'!D30)*(1-23.6%),((('Revenue Build_Empty'!D17*$A59*B$54/1000000)*(1+'Revenue Build_Empty'!D19))-(('Revenue Build_Empty'!D17*$A59*B$54/1000000)*'Revenue Build_Empty'!D28)-'Revenue Build_Empty'!D27-'Revenue Build_Empty'!D30)))/(1+$F$4)^1+(IF(((('Revenue Build_Empty'!E17*$A59*B$54/1000000)*(1+'Revenue Build_Empty'!E19))-(('Revenue Build_Empty'!E17*$A59*B$54/1000000)*'Revenue Build_Empty'!E28)-'Revenue Build_Empty'!E27-'Revenue Build_Empty'!E30)>0,((('Revenue Build_Empty'!E17*$A59*B$54/1000000)*(1+'Revenue Build_Empty'!E19))-(('Revenue Build_Empty'!E17*$A59*B$54/1000000)*'Revenue Build_Empty'!E28)-'Revenue Build_Empty'!E27-'Revenue Build_Empty'!E30)*(1-23.6%),((('Revenue Build_Empty'!E17*$A59*B$54/1000000)*(1+'Revenue Build_Empty'!E19))-(('Revenue Build_Empty'!E17*$A59*B$54/1000000)*'Revenue Build_Empty'!E28)-'Revenue Build_Empty'!E27-'Revenue Build_Empty'!E30)))/(1+$F$4)^2+(IF(((('Revenue Build_Empty'!F17*$A59*B$54/1000000)*(1+'Revenue Build_Empty'!F19))-(('Revenue Build_Empty'!F17*$A59*B$54/1000000)*'Revenue Build_Empty'!F28)-'Revenue Build_Empty'!F27-'Revenue Build_Empty'!F30)>0,((('Revenue Build_Empty'!F17*$A59*B$54/1000000)*(1+'Revenue Build_Empty'!F19))-(('Revenue Build_Empty'!F17*$A59*B$54/1000000)*'Revenue Build_Empty'!F28)-'Revenue Build_Empty'!F27-'Revenue Build_Empty'!F30)*(1-23.6%),((('Revenue Build_Empty'!F17*$A59*B$54/1000000)*(1+'Revenue Build_Empty'!F19))-(('Revenue Build_Empty'!F17*$A59*B$54/1000000)*'Revenue Build_Empty'!F28)-'Revenue Build_Empty'!F27-'Revenue Build_Empty'!F30)))/(1+$F$4)^3+(IF(((('Revenue Build_Empty'!G17*$A59*B$54/1000000)*(1+'Revenue Build_Empty'!G19))-(('Revenue Build_Empty'!G17*$A59*B$54/1000000)*'Revenue Build_Empty'!G28)-'Revenue Build_Empty'!G27-'Revenue Build_Empty'!G30)>0,((('Revenue Build_Empty'!G17*$A59*B$54/1000000)*(1+'Revenue Build_Empty'!G19))-(('Revenue Build_Empty'!G17*$A59*B$54/1000000)*'Revenue Build_Empty'!G28)-'Revenue Build_Empty'!G27-'Revenue Build_Empty'!G30)*(1-23.6%),((('Revenue Build_Empty'!G17*$A59*B$54/1000000)*(1+'Revenue Build_Empty'!G19))-(('Revenue Build_Empty'!G17*$A59*B$54/1000000)*'Revenue Build_Empty'!G28)-'Revenue Build_Empty'!G27-'Revenue Build_Empty'!G30)))/(1+$F$4)^4+(IF(((('Revenue Build_Empty'!H17*$A59*B$54/1000000)*(1+'Revenue Build_Empty'!H19))-(('Revenue Build_Empty'!H17*$A59*B$54/1000000)*'Revenue Build_Empty'!H28)-'Revenue Build_Empty'!H27-'Revenue Build_Empty'!H30)>0,((('Revenue Build_Empty'!H17*$A59*B$54/1000000)*(1+'Revenue Build_Empty'!H19))-(('Revenue Build_Empty'!H17*$A59*B$54/1000000)*'Revenue Build_Empty'!H28)-'Revenue Build_Empty'!H27-'Revenue Build_Empty'!H30)*(1-23.6%),((('Revenue Build_Empty'!H17*$A59*B$54/1000000)*(1+'Revenue Build_Empty'!H19))-(('Revenue Build_Empty'!H17*$A59*B$54/1000000)*'Revenue Build_Empty'!H28)-'Revenue Build_Empty'!H27-'Revenue Build_Empty'!H30)))/(1+$F$4)^5+(IF(((('Revenue Build_Empty'!I17*$A59*B$54/1000000)*(1+'Revenue Build_Empty'!I19))-(('Revenue Build_Empty'!I17*$A59*B$54/1000000)*'Revenue Build_Empty'!I28)-'Revenue Build_Empty'!I27-'Revenue Build_Empty'!I30)>0,((('Revenue Build_Empty'!I17*$A59*B$54/1000000)*(1+'Revenue Build_Empty'!I19))-(('Revenue Build_Empty'!I17*$A59*B$54/1000000)*'Revenue Build_Empty'!I28)-'Revenue Build_Empty'!I27-'Revenue Build_Empty'!I30)*(1-23.6%),((('Revenue Build_Empty'!I17*$A59*B$54/1000000)*(1+'Revenue Build_Empty'!I19))-(('Revenue Build_Empty'!I17*$A59*B$54/1000000)*'Revenue Build_Empty'!I28)-'Revenue Build_Empty'!I27-'Revenue Build_Empty'!I30)))/(1+$F$4)^6 -> -52.284999 | C59: =$B$17+(IF(((('Revenue Build_Empty'!D17*$A59*C$54/1000000)*(1+'Revenue Build_Empty'!D19))-(('Revenue Build_Empty'!D17*$A59*C$54/1000000)*'Revenue Build_Empty'!D28)-'Revenue Build_Empty'!D27-'Revenue Build_Empty'!D30)>0,((('Revenue Build_Empty'!D17*$A59*C$54/1000000)*(1+'Revenue Build_Empty'!D19))-(('Revenue Build_Empty'!D17*$A59*C$54/1000000)*'Revenue Build_Empty'!D28)-'Revenue Build_Empty'!D27-'Revenue Build_Empty'!D30)*(1-23.6%),((('Revenue Build_Empty'!D17*$A59*C$54/1000000)*(1+'Revenue Build_Empty'!D19))-(('Revenue Build_Empty'!D17*$A59*C$54/1000000)*'Revenue Build_Empty'!D28)-'Revenue Build_Empty'!D27-'Revenue Build_Empty'!D30)))/(1+$F$4)^1+(IF(((('Revenue Build_Empty'!E17*$A59*C$54/1000000)*(1+'Revenue Build_Empty'!E19))-(('Revenue Build_Empty'!E17*$A59*C$54/1000000)*'Revenue Build_Empty'!E28)-'Revenue Build_Empty'!E27-'Revenue Build_Empty'!E30)>0,((('Revenue Build_Empty'!E17*$A59*C$54/1000000)*(1+'Revenue Build_Empty'!E19))-(('Revenue Build_Empty'!E17*$A59*C$54/1000000)*'Revenue Build_Empty'!E28)-'Revenue Build_Empty'!E27-'Revenue Build_Empty'!E30)*(1-23.6%),((('Revenue Build_Empty'!E17*$A59*C$54/1000000)*(1+'Revenue Build_Empty'!E19))-(('Revenue Build_Empty'!E17*$A59*C$54/1000000)*'Revenue Build_Empty'!E28)-'Revenue Build_Empty'!E27-'Revenue Build_Empty'!E30)))/(1+$F$4)^2+(IF(((('Revenue Build_Empty'!F17*$A59*C$54/1000000)*(1+'Revenue Build_Empty'!F19))-(('Revenue Build_Empty'!F17*$A59*C$54/1000000)*'Revenue Build_Empty'!F28)-'Revenue Build_Empty'!F27-'Revenue Build_Empty'!F30)>0,((('Revenue Build_Empty'!F17*$A59*C$54/1000000)*(1+'Revenue Build_Empty'!F19))-(('Revenue Build_Empty'!F17*$A59*C$54/1000000)*'Revenue Build_Empty'!F28)-'Revenue Build_Empty'!F27-'Revenue Build_Empty'!F30)*(1-23.6%),((('Revenue Build_Empty'!F17*$A59*C$54/1000000)*(1+'Revenue Build_Empty'!F19))-(('Revenue Build_Empty'!F17*$A59*C$54/1000000)*'Revenue Build_Empty'!F28)-'Revenue Build_Empty'!F27-'Revenue Build_Empty'!F30)))/(1+$F$4)^3+(IF(((('Revenue Build_Empty'!G17*$A59*C$54/1000000)*(1+'Revenue Build_Empty'!G19))-(('Revenue Build_Empty'!G17*$A59*C$54/1000000)*'Revenue Build_Empty'!G28)-'Revenue Build_Empty'!G27-'Revenue Build_Empty'!G30)>0,((('Revenue Build_Empty'!G17*$A59*C$54/1000000)*(1+'Revenue Build_Empty'!G19))-(('Revenue Build_Empty'!G17*$A59*C$54/1000000)*'Revenue Build_Empty'!G28)-'Revenue Build_Empty'!G27-'Revenue Build_Empty'!G30)*(1-23.6%),((('Revenue Build_Empty'!G17*$A59*C$54/1000000)*(1+'Revenue Build_Empty'!G19))-(('Revenue Build_Empty'!G17*$A59*C$54/1000000)*'Revenue Build_Empty'!G28)-'Revenue Build_Empty'!G27-'Revenue Build_Empty'!G30)))/(1+$F$4)^4+(IF(((('Revenue Build_Empty'!H17*$A59*C$54/1000000)*(1+'Revenue Build_Empty'!H19))-(('Revenue Build_Empty'!H17*$A59*C$54/1000000)*'Revenue Build_Empty'!H28)-'Revenue Build_Empty'!H27-'Revenue Build_Empty'!H30)>0,((('Revenue Build_Empty'!H17*$A59*C$54/1000000)*(1+'Revenue Build_Empty'!H19))-(('Revenue Build_Empty'!H17*$A59*C$54/1000000)*'Revenue Build_Empty'!H28)-'Revenue Build_Empty'!H27-'Revenue Build_Empty'!H30)*(1-23.6%),((('Revenue Build_Empty'!H17*$A59*C$54/1000000)*(1+'Revenue Build_Empty'!H19))-(('Revenue Build_Empty'!H17*$A59*C$54/1000000)*'Revenue Build_Empty'!H28)-'Revenue Build_Empty'!H27-'Revenue Build_Empty'!H30)))/(1+$F$4)^5+(IF(((('Revenue Build_Empty'!I17*$A59*C$54/1000000)*(1+'Revenue Build_Empty'!I19))-(('Revenue Build_Empty'!I17*$A59*C$54/1000000)*'Revenue Build_Empty'!I28)-'Revenue Build_Empty'!I27-'Revenue Build_Empty'!I30)>0,((('Revenue Build_Empty'!I17*$A59*C$54/1000000)*(1+'Revenue Build_Empty'!I19))-(('Revenue Build_Empty'!I17*$A59*C$54/1000000)*'Revenue Build_Empty'!I28)-'Revenue Build_Empty'!I27-'Revenue Build_Empty'!I30)*(1-23.6%),((('Revenue Build_Empty'!I17*$A59*C$54/1000000)*(1+'Revenue Build_Empty'!I19))-(('Revenue Build_Empty'!I17*$A59*C$54/1000000)*'Revenue Build_Empty'!I28)-'Revenue Build_Empty'!I27-'Revenue Build_Empty'!I30)))/(1+$F$4)^6 -> 2.6849562 | D59: =$B$17+(IF(((('Revenue Build_Empty'!D17*$A59*D$54/1000000)*(1+'Revenue Build_Empty'!D19))-(('Revenue Build_Empty'!D17*$A59*D$54/1000000)*'Revenue Build_Empty'!D28)-'Revenue Build_Empty'!D27-'Revenue Build_Empty'!D30)>0,((('Revenue Build_Empty'!D17*$A59*D$54/1000000)*(1+'Revenue Build_Empty'!D19))-(('Revenue Build_Empty'!D17*$A59*D$54/1000000)*'Revenue Build_Empty'!D28)-'Revenue Build_Empty'!D27-'Revenue Build_Empty'!D30)*(1-23.6%),((('Revenue Build_Empty'!D17*$A59*D$54/1000000)*(1+'Revenue Build_Empty'!D19))-(('Revenue Build_Empty'!D17*$A59*D$54/1000000)*'Revenue Build_Empty'!D28)-'Revenue Build_Empty'!D27-'Revenue Build_Empty'!D30)))/(1+$F$4)^1+(IF(((('Revenue Build_Empty'!E17*$A59*D$54/1000000)*(1+'Revenue Build_Empty'!E19))-(('Revenue Build_Empty'!E17*$A59*D$54/1000000)*'Revenue Build_Empty'!E28)-'Revenue Build_Empty'!E27-'Revenue Build_Empty'!E30)>0,((('Revenue Build_Empty'!E17*$A59*D$54/1000000)*(1+'Revenue Build_Empty'!E19))-(('Revenue Build_Empty'!E17*$A59*D$54/1000000)*'Revenue Build_Empty'!E28)-'Revenue Build_Empty'!E27-'Revenue Build_Empty'!E30)*(1-23.6%),((('Revenue Build_Empty'!E17*$A59*D$54/1000000)*(1+'Revenue Build_Empty'!E19))-(('Revenue Build_Empty'!E17*$A59*D$54/1000000)*'Revenue Build_Empty'!E28)-'Revenue Build_Empty'!E27-'Revenue Build_Empty'!E30)))/(1+$F$4)^2+(IF(((('Revenue Build_Empty'!F17*$A59*D$54/1000000)*(1+'Revenue Build_Empty'!F19))-(('Revenue Build_Empty'!F17*$A59*D$54/1000000)*'Revenue Build_Empty'!F28)-'Revenue Build_Empty'!F27-'Revenue Build_Empty'!F30)>0,((('Revenue Build_Empty'!F17*$A59*D$54/1000000)*(1+'Revenue Build_Empty'!F19))-(('Revenue Build_Empty'!F17*$A59*D$54/1000000)*'Revenue Build_Empty'!F28)-'Revenue Build_Empty'!F27-'Revenue Build_Empty'!F30)*(1-23.6%),((('Revenue Build_Empty'!F17*$A59*D$54/1000000)*(1+'Revenue Build_Empty'!F19))-(('Revenue Build_Empty'!F17*$A59*D$54/1000000)*'Revenue Build_Empty'!F28)-'Revenue Build_Empty'!F27-'Revenue Build_Empty'!F30)))/(1+$F$4)^3+(IF(((('Revenue Build_Empty'!G17*$A59*D$54/1000000)*(1+'Revenue Build_Empty'!G19))-(('Revenue Build_Empty'!G17*$A59*D$54/1000000)*'Revenue Build_Empty'!G28)-'Revenue Build_Empty'!G27-'Revenue Build_Empty'!G30)>0,((('Revenue Build_Empty'!G17*$A59*D$54/1000000)*(1+'Revenue Build_Empty'!G19))-(('Revenue Build_Empty'!G17*$A59*D$54/1000000)*'Revenue Build_Empty'!G28)-'Revenue Build_Empty'!G27-'Revenue Build_Empty'!G30)*(1-23.6%),((('Revenue Build_Empty'!G17*$A59*D$54/1000000)*(1+'Revenue Build_Empty'!G19))-(('Revenue Build_Empty'!G17*$A59*D$54/1000000)*'Revenue Build_Empty'!G28)-'Revenue Build_Empty'!G27-'Revenue Build_Empty'!G30)))/(1+$F$4)^4+(IF(((('Revenue Build_Empty'!H17*$A59*D$54/1000000)*(1+'Revenue Build_Empty'!H19))-(('Revenue Build_Empty'!H17*$A59*D$54/1000000)*'Revenue Build_Empty'!H28)-'Revenue Build_Empty'!H27-'Revenue Build_Empty'!H30)>0,((('Revenue Build_Empty'!H17*$A59*D$54/1000000)*(1+'Revenue Build_Empty'!H19))-(('Revenue Build_Empty'!H17*$A59*D$54/1000000)*'Revenue Build_Empty'!H28)-'Revenue Build_Empty'!H27-'Revenue Build_Empty'!H30)*(1-23.6%),((('Revenue Build_Empty'!H17*$A59*D$54/1000000)*(1+'Revenue Build_Empty'!H19))-(('Revenue Build_Empty'!H17*$A59*D$54/1000000)*'Revenue Build_Empty'!H28)-'Revenue Build_Empty'!H27-'Revenue Build_Empty'!H30)))/(1+$F$4)^5+(IF(((('Revenue Build_Empty'!I17*$A59*D$54/1000000)*(1+'Revenue Build_Empty'!I19))-(('Revenue Build_Empty'!I17*$A59*D$54/1000000)*'Revenue Build_Empty'!I28)-'Revenue Build_Empty'!I27-'Revenue Build_Empty'!I30)>0,((('Revenue Build_Empty'!I17*$A59*D$54/1000000)*(1+'Revenue Build_Empty'!I19))-(('Revenue Build_Empty'!I17*$A59*D$54/1000000)*'Revenue Build_Empty'!I28)-'Revenue Build_Empty'!I27-'Revenue Build_Empty'!I30)*(1-23.6%),((('Revenue Build_Empty'!I17*$A59*D$54/1000000)*(1+'Revenue Build_Empty'!I19))-(('Revenue Build_Empty'!I17*$A59*D$54/1000000)*'Revenue Build_Empty'!I28)-'Revenue Build_Empty'!I27-'Revenue Build_Empty'!I30)))/(1+$F$4)^6 -> 54.958538 | E59: =$B$17+(IF(((('Revenue Build_Empty'!D17*$A59*E$54/1000000)*(1+'Revenue Build_Empty'!D19))-(('Revenue Build_Empty'!D17*$A59*E$54/1000000)*'Revenue Build_Empty'!D28)-'Revenue Build_Empty'!D27-'Revenue Build_Empty'!D30)>0,((('Revenue Build_Empty'!D17*$A59*E$54/1000000)*(1+'Revenue Build_Empty'!D19))-(('Revenue Build_Empty'!D17*$A59*E$54/1000000)*'Revenue Build_Empty'!D28)-'Revenue Build_Empty'!D27-'Revenue Build_Empty'!D30)*(1-23.6%),((('Revenue Build_Empty'!D17*$A59*E$54/1000000)*(1+'Revenue Build_Empty'!D19))-(('Revenue Build_Empty'!D17*$A59*E$54/1000000)*'Revenue Build_Empty'!D28)-'Revenue Build_Empty'!D27-'Revenue Build_Empty'!D30)))/(1+$F$4)^1+(IF(((('Revenue Build_Empty'!E17*$A59*E$54/1000000)*(1+'Revenue Build_Empty'!E19))-(('Revenue Build_Empty'!E17*$A59*E$54/1000000)*'Revenue Build_Empty'!E28)-'Revenue Build_Empty'!E27-'Revenue Build_Empty'!E30)>0,((('Revenue Build_Empty'!E17*$A59*E$54/1000000)*(1+'Revenue Build_Empty'!E19))-(('Revenue Build_Empty'!E17*$A59*E$54/1000000)*'Revenue Build_Empty'!E28)-'Revenue Build_Empty'!E27-'Revenue Build_Empty'!E30)*(1-23.6%),((('Revenue Build_Empty'!E17*$A59*E$54/1000000)*(1+'Revenue Build_Empty'!E19))-(('Revenue Build_Empty'!E17*$A59*E$54/1000000)*'Revenue Build_Empty'!E28)-'Revenue Build_Empty'!E27-'Revenue Build_Empty'!E30)))/(1+$F$4)^2+(IF(((('Revenue Build_Empty'!F17*$A59*E$54/1000000)*(1+'Revenue Build_Empty'!F19))-(('Revenue Build_Empty'!F17*$A59*E$54/1000000)*'Revenue Build_Empty'!F28)-'Revenue Build_Empty'!F27-'Revenue Build_Empty'!F30)>0,((('Revenue Build_Empty'!F17*$A59*E$54/1000000)*(1+'Revenue Build_Empty'!F19))-(('Revenue Build_Empty'!F17*$A59*E$54/1000000)*'Revenue Build_Empty'!F28)-'Revenue Build_Empty'!F27-'Revenue Build_Empty'!F30)*(1-23.6%),((('Revenue Build_Empty'!F17*$A59*E$54/1000000)*(1+'Revenue Build_Empty'!F19))-(('Revenue Build_Empty'!F17*$A59*E$54/1000000)*'Revenue Build_Empty'!F28)-'Revenue Build_Empty'!F27-'Revenue Build_Empty'!F30)))/(1+$F$4)^3+(IF(((('Revenue Build_Empty'!G17*$A59*E$54/1000000)*(1+'Revenue Build_Empty'!G19))-(('Revenue Build_Empty'!G17*$A59*E$54/1000000)*'Revenue Build_Empty'!G28)-'Revenue Build_Empty'!G27-'Revenue Build_Empty'!G30)>0,((('Revenue Build_Empty'!G17*$A59*E$54/1000000)*(1+'Revenue Build_Empty'!G19))-(('Revenue Build_Empty'!G17*$A59*E$54/1000000)*'Revenue Build_Empty'!G28)-'Revenue Build_Empty'!G27-'Revenue Build_Empty'!G30)*(1-23.6%),((('Revenue Build_Empty'!G17*$A59*E$54/1000000)*(1+'Revenue Build_Empty'!G19))-(('Revenue Build_Empty'!G17*$A59*E$54/1000000)*'Revenue Build_Empty'!G28)-'Revenue Build_Empty'!G27-'Revenue Build_Empty'!G30)))/(1+$F$4)^4+(IF(((('Revenue Build_Empty'!H17*$A59*E$54/1000000)*(1+'Revenue Build_Empty'!H19))-(('Revenue Build_Empty'!H17*$A59*E$54/1000000)*'Revenue Build_Empty'!H28)-'Revenue Build_Empty'!H27-'Revenue Build_Empty'!H30)>0,((('Revenue Build_Empty'!H17*$A59*E$54/1000000)*(1+'Revenue Build_Empty'!H19))-(('Revenue Build_Empty'!H17*$A59*E$54/1000000)*'Revenue Build_Empty'!H28)-'Revenue Build_Empty'!H27-'Revenue Build_Empty'!H30)*(1-23.6%),((('Revenue Build_Empty'!H17*$A59*E$54/1000000)*(1+'Revenue Build_Empty'!H19))-(('Revenue Build_Empty'!H17*$A59*E$54/1000000)*'Revenue Build_Empty'!H28)-'Revenue Build_Empty'!H27-'Revenue Build_Empty'!H30)))/(1+$F$4)^5+(IF(((('Revenue Build_Empty'!I17*$A59*E$54/1000000)*(1+'Revenue Build_Empty'!I19))-(('Revenue Build_Empty'!I17*$A59*E$54/1000000)*'Revenue Build_Empty'!I28)-'Revenue Build_Empty'!I27-'Revenue Build_Empty'!I30)>0,((('Revenue Build_Empty'!I17*$A59*E$54/1000000)*(1+'Revenue Build_Empty'!I19))-(('Revenue Build_Empty'!I17*$A59*E$54/1000000)*'Revenue Build_Empty'!I28)-'Revenue Build_Empty'!I27-'Revenue Build_Empty'!I30)*(1-23.6%),((('Revenue Build_Empty'!I17*$A59*E$54/1000000)*(1+'Revenue Build_Empty'!I19))-(('Revenue Build_Empty'!I17*$A59*E$54/1000000)*'Revenue Build_Empty'!I28)-'Revenue Build_Empty'!I27-'Revenue Build_Empty'!I30)))/(1+$F$4)^6 -> 106.79697 | F59: =$B$17+(IF(((('Revenue Build_Empty'!D17*$A59*F$54/1000000)*(1+'Revenue Build_Empty'!D19))-(('Revenue Build_Empty'!D17*$A59*F$54/1000000)*'Revenue Build_Empty'!D28)-'Revenue Build_Empty'!D27-'Revenue Build_Empty'!D30)>0,((('Revenue Build_Empty'!D17*$A59*F$54/1000000)*(1+'Revenue Build_Empty'!D19))-(('Revenue Build_Empty'!D17*$A59*F$54/1000000)*'Revenue Build_Empty'!D28)-'Revenue Build_Empty'!D27-'Revenue Build_Empty'!D30)*(1-23.6%),((('Revenue Build_Empty'!D17*$A59*F$54/1000000)*(1+'Revenue Build_Empty'!D19))-(('Revenue Build_Empty'!D17*$A59*F$54/1000000)*'Revenue Build_Empty'!D28)-'Revenue Build_Empty'!D27-'Revenue Build_Empty'!D30)))/(1+$F$4)^1+(IF(((('Revenue Build_Empty'!E17*$A59*F$54/1000000)*(1+'Revenue Build_Empty'!E19))-(('Revenue Build_Empty'!E17*$A59*F$54/1000000)*'Revenue Build_Empty'!E28)-'Revenue Build_Empty'!E27-'Revenue Build_Empty'!E30)>0,((('Revenue Build_Empty'!E17*$A59*F$54/1000000)*(1+'Revenue Build_Empty'!E19))-(('Revenue Build_Empty'!E17*$A59*F$54/1000000)*'Revenue Build_Empty'!E28)-'Revenue Build_Empty'!E27-'Revenue Build_Empty'!E30)*(1-23.6%),((('Revenue Build_Empty'!E17*$A59*F$54/1000000)*(1+'Revenue Build_Empty'!E19))-(('Revenue Build_Empty'!E17*$A59*F$54/1000000)*'Revenue Build_Empty'!E28)-'Revenue Build_Empty'!E27-'Revenue Build_Empty'!E30)))/(1+$F$4)^2+(IF(((('Revenue Build_Empty'!F17*$A59*F$54/1000000)*(1+'Revenue Build_Empty'!F19))-(('Revenue Build_Empty'!F17*$A59*F$54/1000000)*'Revenue Build_Empty'!F28)-'Revenue Build_Empty'!F27-'Revenue Build_Empty'!F30)>0,((('Revenue Build_Empty'!F17*$A59*F$54/1000000)*(1+'Revenue Build_Empty'!F19))-(('Revenue Build_Empty'!F17*$A59*F$54/1000000)*'Revenue Build_Empty'!F28)-'Revenue Build_Empty'!F27-'Revenue Build_Empty'!F30)*(1-23.6%),((('Revenue Build_Empty'!F17*$A59*F$54/1000000)*(1+'Revenue Build_Empty'!F19))-(('Revenue Build_Empty'!F17*$A59*F$54/1000000)*'Revenue Build_Empty'!F28)-'Revenue Build_Empty'!F27-'Revenue Build_Empty'!F30)))/(1+$F$4)^3+(IF(((('Revenue Build_Empty'!G17*$A59*F$54/1000000)*(1+'Revenue Build_Empty'!G19))-(('Revenue Build_Empty'!G17*$A59*F$54/1000000)*'Revenue Build_Empty'!G28)-'Revenue Build_Empty'!G27-'Revenue Build_Empty'!G30)>0,((('Revenue Build_Empty'!G17*$A59*F$54/1000000)*(1+'Revenue Build_Empty'!G19))-(('Revenue Build_Empty'!G17*$A59*F$54/1000000)*'Revenue Build_Empty'!G28)-'Revenue Build_Empty'!G27-'Revenue Build_Empty'!G30)*(1-23.6%),((('Revenue Build_Empty'!G17*$A59*F$54/1000000)*(1+'Revenue Build_Empty'!G19))-(('Revenue Build_Empty'!G17*$A59*F$54/1000000)*'Revenue Build_Empty'!G28)-'Revenue Build_Empty'!G27-'Revenue Build_Empty'!G30)))/(1+$F$4)^4+(IF(((('Revenue Build_Empty'!H17*$A59*F$54/1000000)*(1+'Revenue Build_Empty'!H19))-(('Revenue Build_Empty'!H17*$A59*F$54/1000000)*'Revenue Build_Empty'!H28)-'Revenue Build_Empty'!H27-'Revenue Build_Empty'!H30)>0,((('Revenue Build_Empty'!H17*$A59*F$54/1000000)*(1+'Revenue Build_Empty'!H19))-(('Revenue Build_Empty'!H17*$A59*F$54/1000000)*'Revenue Build_Empty'!H28)-'Revenue Build_Empty'!H27-'Revenue Build_Empty'!H30)*(1-23.6%),((('Revenue Build_Empty'!H17*$A59*F$54/1000000)*(1+'Revenue Build_Empty'!H19))-(('Revenue Build_Empty'!H17*$A59*F$54/1000000)*'Revenue Build_Empty'!H28)-'Revenue Build_Empty'!H27-'Revenue Build_Empty'!H30)))/(1+$F$4)^5+(IF(((('Revenue Build_Empty'!I17*$A59*F$54/1000000)*(1+'Revenue Build_Empty'!I19))-(('Revenue Build_Empty'!I17*$A59*F$54/1000000)*'Revenue Build_Empty'!I28)-'Revenue Build_Empty'!I27-'Revenue Build_Empty'!I30)>0,((('Revenue Build_Empty'!I17*$A59*F$54/1000000)*(1+'Revenue Build_Empty'!I19))-(('Revenue Build_Empty'!I17*$A59*F$54/1000000)*'Revenue Build_Empty'!I28)-'Revenue Build_Empty'!I27-'Revenue Build_Empty'!I30)*(1-23.6%),((('Revenue Build_Empty'!I17*$A59*F$54/1000000)*(1+'Revenue Build_Empty'!I19))-(('Revenue Build_Empty'!I17*$A59*F$54/1000000)*'Revenue Build_Empty'!I28)-'Revenue Build_Empty'!I27-'Revenue Build_Empty'!I30)))/(1+$F$4)^6 -> 157.7721
A63: NPV incl. TV Sensitivity - WACC x Terminal Growth
A64: WACC \ g | B64: 0.01 | C64: 0.015 | D64: 0.02 | E64: 0.025 | F64: 0.03
A65: 0.07 | B65: =$B$17+C17/(1+$A65)^1+D17/(1+$A65)^2+E17/(1+$A65)^3+F17/(1+$A65)^4+G17/(1+$A65)^5+H17/(1+$A65)^6+IF(H17>0,H17*(1+B$64)/($A65-B$64)/(1+$A65)^6,0) -> 499.61428 | C65: =$B$17+C17/(1+$A65)^1+D17/(1+$A65)^2+E17/(1+$A65)^3+F17/(1+$A65)^4+G17/(1+$A65)^5+H17/(1+$A65)^6+IF(H17>0,H17*(1+C$64)/($A65-C$64)/(1+$A65)^6,0) -> 546.06821 | D65: =$B$17+C17/(1+$A65)^1+D17/(1+$A65)^2+E17/(1+$A65)^3+F17/(1+$A65)^4+G17/(1+$A65)^5+H17/(1+$A65)^6+IF(H17>0,H17*(1+D$64)/($A65-D$64)/(1+$A65)^6,0) -> 601.81292 | E65: =$B$17+C17/(1+$A65)^1+D17/(1+$A65)^2+E17/(1+$A65)^3+F17/(1+$A65)^4+G17/(1+$A65)^5+H17/(1+$A65)^6+IF(H17>0,H17*(1+E$64)/($A65-E$64)/(1+$A65)^6,0) -> 669.94534 | F65: =$B$17+C17/(1+$A65)^1+D17/(1+$A65)^2+E17/(1+$A65)^3+F17/(1+$A65)^4+G17/(1+$A65)^5+H17/(1+$A65)^6+IF(H17>0,H17*(1+F$64)/($A65-F$64)/(1+$A65)^6,0) -> 755.11086
A66: 0.08 | B66: =$B$17+C17/(1+$A66)^1+D17/(1+$A66)^2+E17/(1+$A66)^3+F17/(1+$A66)^4+G17/(1+$A66)^5+H17/(1+$A66)^6+IF(H17>0,H17*(1+B$64)/($A66-B$64)/(1+$A66)^6,0) -> 405.76624 | C66: =$B$17+C17/(1+$A66)^1+D17/(1+$A66)^2+E17/(1+$A66)^3+F17/(1+$A66)^4+G17/(1+$A66)^5+H17/(1+$A66)^6+IF(H17>0,H17*(1+C$64)/($A66-C$64)/(1+$A66)^6,0) -> 437.92691 | D66: =$B$17+C17/(1+$A66)^1+D17/(1+$A66)^2+E17/(1+$A66)^3+F17/(1+$A66)^4+G17/(1+$A66)^5+H17/(1+$A66)^6+IF(H17>0,H17*(1+D$64)/($A66-D$64)/(1+$A66)^6,0) -> 475.44769 | E66: =$B$17+C17/(1+$A66)^1+D17/(1+$A66)^2+E17/(1+$A66)^3+F17/(1+$A66)^4+G17/(1+$A66)^5+H17/(1+$A66)^6+IF(H17>0,H17*(1+E$64)/($A66-E$64)/(1+$A66)^6,0) -> 519.79042 | F66: =$B$17+C17/(1+$A66)^1+D17/(1+$A66)^2+E17/(1+$A66)^3+F17/(1+$A66)^4+G17/(1+$A66)^5+H17/(1+$A66)^6+IF(H17>0,H17*(1+F$64)/($A66-F$64)/(1+$A66)^6,0) -> 573.00171
A67: 0.09 | B67: =$B$17+C17/(1+$A67)^1+D17/(1+$A67)^2+E17/(1+$A67)^3+F17/(1+$A67)^4+G17/(1+$A67)^5+H17/(1+$A67)^6+IF(H17>0,H17*(1+B$64)/($A67-B$64)/(1+$A67)^6,0) -> 336.14184 | C67: =$B$17+C17/(1+$A67)^1+D17/(1+$A67)^2+E17/(1+$A67)^3+F17/(1+$A67)^4+G17/(1+$A67)^5+H17/(1+$A67)^6+IF(H17>0,H17*(1+C$64)/($A67-C$64)/(1+$A67)^6,0) -> 359.43195 | D67: =$B$17+C17/(1+$A67)^1+D17/(1+$A67)^2+E17/(1+$A67)^3+F17/(1+$A67)^4+G17/(1+$A67)^5+H17/(1+$A67)^6+IF(H17>0,H17*(1+D$64)/($A67-D$64)/(1+$A67)^6,0) -> 386.04922 | E67: =$B$17+C17/(1+$A67)^1+D17/(1+$A67)^2+E17/(1+$A67)^3+F17/(1+$A67)^4+G17/(1+$A67)^5+H17/(1+$A67)^6+IF(H17>0,H17*(1+E$64)/($A67-E$64)/(1+$A67)^6,0) -> 416.76145 | F67: =$B$17+C17/(1+$A67)^1+D17/(1+$A67)^2+E17/(1+$A67)^3+F17/(1+$A67)^4+G17/(1+$A67)^5+H17/(1+$A67)^6+IF(H17>0,H17*(1+F$64)/($A67-F$64)/(1+$A67)^6,0) -> 452.59238
A68: 0.1 | B68: =$B$17+C17/(1+$A68)^1+D17/(1+$A68)^2+E17/(1+$A68)^3+F17/(1+$A68)^4+G17/(1+$A68)^5+H17/(1+$A68)^6+IF(H17>0,H17*(1+B$64)/($A68-B$64)/(1+$A68)^6,0) -> 282.62946 | C68: =$B$17+C17/(1+$A68)^1+D17/(1+$A68)^2+E17/(1+$A68)^3+F17/(1+$A68)^4+G17/(1+$A68)^5+H17/(1+$A68)^6+IF(H17>0,H17*(1+C$64)/($A68-C$64)/(1+$A68)^6,0) -> 300.08086 | D68: =$B$17+C17/(1+$A68)^1+D17/(1+$A68)^2+E17/(1+$A68)^3+F17/(1+$A68)^4+G17/(1+$A68)^5+H17/(1+$A68)^6+IF(H17>0,H17*(1+D$64)/($A68-D$64)/(1+$A68)^6,0) -> 319.71369 | E68: =$B$17+C17/(1+$A68)^1+D17/(1+$A68)^2+E17/(1+$A68)^3+F17/(1+$A68)^4+G17/(1+$A68)^5+H17/(1+$A68)^6+IF(H17>0,H17*(1+E$64)/($A68-E$64)/(1+$A68)^6,0) -> 341.96423 | F68: =$B$17+C17/(1+$A68)^1+D17/(1+$A68)^2+E17/(1+$A68)^3+F17/(1+$A68)^4+G17/(1+$A68)^5+H17/(1+$A68)^6+IF(H17>0,H17*(1+F$64)/($A68-F$64)/(1+$A68)^6,0) -> 367.39342
A69: 0.11 | B69: =$B$17+C17/(1+$A69)^1+D17/(1+$A69)^2+E17/(1+$A69)^3+F17/(1+$A69)^4+G17/(1+$A69)^5+H17/(1+$A69)^6+IF(H17>0,H17*(1+B$64)/($A69-B$64)/(1+$A69)^6,0) -> 240.36427 | C69: =$B$17+C17/(1+$A69)^1+D17/(1+$A69)^2+E17/(1+$A69)^3+F17/(1+$A69)^4+G17/(1+$A69)^5+H17/(1+$A69)^6+IF(H17>0,H17*(1+C$64)/($A69-C$64)/(1+$A69)^6,0) -> 253.79553 | D69: =$B$17+C17/(1+$A69)^1+D17/(1+$A69)^2+E17/(1+$A69)^3+F17/(1+$A69)^4+G17/(1+$A69)^5+H17/(1+$A69)^6+IF(H17>0,H17*(1+D$64)/($A69-D$64)/(1+$A69)^6,0) -> 268.71915 | E69: =$B$17+C17/(1+$A69)^1+D17/(1+$A69)^2+E17/(1+$A69)^3+F17/(1+$A69)^4+G17/(1+$A69)^5+H17/(1+$A69)^6+IF(H17>0,H17*(1+E$64)/($A69-E$64)/(1+$A69)^6,0) -> 285.39849 | F69: =$B$17+C17/(1+$A69)^1+D17/(1+$A69)^2+E17/(1+$A69)^3+F17/(1+$A69)^4+G17/(1+$A69)^5+H17/(1+$A69)^6+IF(H17>0,H17*(1+F$64)/($A69-F$64)/(1+$A69)^6,0) -> 304.16275

Sheet Shares
B2: Shares - Dilution and Repurchases
B3: € and shares in millions, except per share data
B6: Basic and diluted share count
C7: Reported / Forecast | D7: Shares | E7: Comment
B8: Basic weighted-average shares (2025A) | D8: 231 | E8: Reported 2025
B9: LTIP / RSU dilution | D9: 0.8 | E9: Difference between basic and diluted shares
B10: Diluted weighted-average shares (2025A) | D10: =D8+D9 -> 231.8 | E10: Basic + dilution
B11: Forecast diluted shares (2026E) | D11: =Forecast!D220 -> 228 | E11: Linked from Forecast
B12: Net diluted shares used in DCF | D12: =D11 -> 228 | E12: 2026E proxy
B15: Share repurchase context
B16: 2025 share repurchases (€m) | D16: 1096 | E16: Reported financing cash flow
B17: 2025 share-based payments (€m) | D17: 26 | E17: Reported cash-flow adjustment
B18: 2025 diluted/basic spread (m) | D18: =D10-D8 -> 0.8 | E18: Diluted − basic shares
B21: Convertible securities 'if-converted' test
B22: Convertible debt | D22: 0 | E22: No material convertible instrument modeled
B23: Principal outstanding | D23: 0
B24: Conversion ratio | D24: 0
B25: Common shares convertible into | D25: 0
B26: Dilutive impact | D26: 0
B27: Elimination of liability from net debt | D27: 0

Sheet WACC
B2: WACC Buildup
B3: € and shares in millions, except per share data
B4: Cost of capital assumptions
E5: Source
B6: Cost of debt | C6: 0.038 | E6: Normalized investment-grade debt cost
B7: Tax rate | C7: 0.236 | E7: 2025 benchmark tax rate
B8: Cost of debt (after tax) | C8: =C6*(1-C7) -> 0.029032 | E8: Cost of debt × (1 − tax rate)
B10: Risk free rate | C10: 0.03 | E10: Long-duration EUR sovereign proxy
B11: Beta | C11: 1.05 | E11: Mature information/software beta
B12: Market risk premium | C12: 0.05 | E12: Normalized equity risk premium
B13: Cost of equity | C13: =C10+C11*C12 -> 0.0825 | E13: CAPM
B15: Capital weights (capital structure)
C17: Current | D17: Target | E17: % of total
B18: Equity | D18: 0.95 | E18: =D18/SUM($D$18:$D$19) -> 0.95
B19: Debt | D19: 0.05 | E19: =D19/SUM($D$18:$D$19) -> 0.05
B21: Cost of capital (WACC) | E21: =C13*E18+C8*E19 -> 0.0798266
